Workbook

Sheet Coding Instrument
A1: SDQ / CDQ CODING INSTRUMENT
A2: Sustainability Disclosure Quality (SDQ) and Climate-related Disclosure Quality (CDQ) content-analysis checklist
A3: Derived from IFRS S1 (four pillars: Governance, Strategy, Risk Management, Metrics & Targets) and IFRS S2 (climate-specific items across the same four pillars)
A5: HOW TO USE THIS INSTRUMENT
A6: 1. This tab defines every item scored in the 'Coding Sheet' tab. Score each item 1 (disclosed) or 0 (not disclosed) per firm-year.
A7: 2. Score against the firm's annual report, standalone sustainability report and integrated report for that specific fiscal year - the same documents used for the financial data.
A8: 3. A '1' requires entity-specific, substantive disclosure. Generic boilerplate ('we are committed to sustainability') without specifics scores 0.
A9: 4. SDQ_Score = (sum of 20 SDQ items disclosed / 20) x 100. CDQ_Score = (sum of 15 CDQ items disclosed / 15) x 100. Both computed automatically in the Coding Sheet.
A10: 5. Record the source document and page/section for each firm-year in the Coding_Notes column of the Coding Sheet - this is your audit trail for Chapter Three's reliability discussion.
A11: 6. Recommended reliability check: after scoring roughly 10% of firm-years, recode a random sample of them without looking at your first pass, then compare agreement. Report this in Chapter Three.
A13: WORKED EXAMPLE (illustrative only - not a real firm)
A14: Item SDQ_M1 (metric disclosed): A firm's sustainability report states 'we monitor several environmental indicators across our operations' -> score 0 (no named metric). A different firm states 'total water withdrawal was 482,000 cubic metres in FY2024, down from 511,000 in FY2023' -> score 1 (specific, entity-level metric with a figure).
A16: Code | B16: Pillar
A17: SUSTAINABILITY DISCLOSURE QUALITY (SDQ) - IFRS S1, 20 items
A18: SDQ_G1 | B18: Governance | C18: Board-level oversight of sustainability-related risks and opportunities is described (which committee/body, and how oversight is exercised) | D18: 1 if the firm names a specific board/committee role and describes its oversight activity; 0 if only a generic statement that 'the board oversees sustainability'
A19: SDQ_G2 | B19: Governance | C19: Management's role in assessing and managing sustainability-related risks and opportunities is described (which role/officer, delegated authority) | D19: 1 if a specific management role or function is named with responsibilities; 0 if absent or vague
A20: SDQ_G3 | B20: Governance | C20: Processes and frequency by which the board is informed of sustainability-related matters are disclosed | D20: 1 if a reporting frequency or defined process is stated; 0 if not mentioned
A21: SDQ_G4 | B21: Governance | C21: Whether/how sustainability-related performance is reflected in board or executive oversight mechanisms (e.g. review of targets, sustainability committee minutes referenced) | D21: 1 if a concrete oversight mechanism is described; 0 if absent
A22: SDQ_G5 | B22: Governance | C22: Skills, competencies or expertise relevant to sustainability oversight held by the board or those charged with governance are disclosed | D22: 1 if specific expertise/training is named; 0 if absent
A23: SDQ_S1 | B23: Strategy | C23: Sustainability-related risks and opportunities the entity has identified over short, medium and long term are described | D23: 1 if specific risks/opportunities are named (not generic ESG language); 0 otherwise
A24: SDQ_S2 | B24: Strategy | C24: Effects of sustainability-related risks and opportunities on the business model and value chain are described | D24: 1 if a specific effect on operations/value chain is discussed; 0 if absent
A25: SDQ_S3 | B25: Strategy | C25: Effects of sustainability-related risks and opportunities on strategy and decision-making are described | D25: 1 if strategic responses are named; 0 if absent
A26: SDQ_S4 | B26: Strategy | C26: Effects on financial position, financial performance and cash flows (current or anticipated) are disclosed | D26: 1 if a financial effect, even qualitative, is quantified or specifically described; 0 if absent
A27: SDQ_S5 | B27: Strategy | C27: Resilience of the strategy to sustainability-related risks is discussed (qualitative or scenario-based) | D27: 1 if any resilience assessment or scenario discussion appears; 0 if absent
A28: SDQ_R1 | B28: Risk Management | C28: Processes for identifying sustainability-related risks are described | D28: 1 if a specific process/methodology is named; 0 if absent
A29: SDQ_R2 | B29: Risk Management | C29: Processes for assessing and prioritising sustainability-related risks are described | D29: 1 if criteria for assessment/prioritisation are named; 0 if absent
A30: SDQ_R3 | B30: Risk Management | C30: Processes for monitoring sustainability-related risks are described | D30: 1 if an ongoing monitoring process is named; 0 if absent
A31: SDQ_R4 | B31: Risk Management | C31: Integration of sustainability risk management into the entity's overall enterprise risk management is disclosed | D31: 1 if the disclosure explicitly states integration with ERM; 0 if silent or only implied | F31: 25569
A32: SDQ_R5 | B32: Risk Management | C32: Processes for identifying sustainability-related opportunities are described | D32: 1 if a specific process is named; 0 if absent
A33: SDQ_M1 | B33: Metrics and Targets | C33: Metrics used to measure and monitor sustainability-related performance are disclosed | D33: 1 if at least one named, entity-specific metric is disclosed; 0 if only narrative with no metric
A34: SDQ_M2 | B34: Metrics and Targets | C34: Targets set for sustainability-related performance, and progress against those targets, are disclosed | D34: 1 if a specific target and progress figure/status are both given; 0 if either is missing
A35: SDQ_M3 | B35: Metrics and Targets | C35: Industry-based or cross-industry metrics relevant to the entity's sector are disclosed | D35: 1 if sector-relevant metrics beyond generic ESG figures appear; 0 if absent
A36: SDQ_M4 | B36: Metrics and Targets | C36: Remuneration is linked, in whole or part, to sustainability-related targets or performance | D36: 1 if explicitly stated; 0 if absent or not disclosed
A37: SDQ_M5 | B37: Metrics and Targets | C37: Methodology or basis used to calculate the disclosed metrics is explained | D37: 1 if a calculation basis/standard is named; 0 if figures are given with no stated methodology
A39: CLIMATE-RELATED DISCLOSURE QUALITY (CDQ) - IFRS S2, 15 items
A40: CDQ_G1 | B40: Climate Governance | C40: Board-level oversight specifically of climate-related risks and opportunities is described | D40: 1 if climate oversight is distinguished from general sustainability oversight; 0 if only generic sustainability governance is described
A41: CDQ_G2 | B41: Climate Governance | C41: Management's role in assessing and managing climate-related risks and opportunities is described | D41: 1 if a specific role/officer is named; 0 if absent
A42: CDQ_G3 | B42: Climate Governance | C42: Climate-related skills or expertise represented at board or management level are disclosed | D42: 1 if specific climate expertise/training is named; 0 if absent
A43: CDQ_S1 | B43: Climate Strategy | C43: Climate-related risks and opportunities are described, distinguishing physical risk from transition risk | D43: 1 if both physical and transition risk are addressed; 0 if only one or neither is addressed
A44: CDQ_S2 | B44: Climate Strategy | C44: Effects of climate-related risks and opportunities on the business model and value chain are described | D44: 1 if a specific effect is discussed; 0 if absent
A45: CDQ_S3 | B45: Climate Strategy | C45: Climate scenario analysis is disclosed, showing how the strategy or business model performs under different climate pathways | D45: 1 if any scenario analysis (even qualitative) is disclosed; 0 if absent
A46: CDQ_S4 | B46: Climate Strategy | C46: A climate transition plan or low-carbon transition strategy is disclosed | D46: 1 if a transition plan or stated transition strategy exists; 0 if absent
A47: CDQ_R1 | B47: Climate Risk Management | C47: Processes for identifying, assessing and prioritising climate-related risks are described | D47: 1 if a specific process is named; 0 if absent
A48: CDQ_R2 | B48: Climate Risk Management | C48: Integration of climate risk management into the entity's overall risk management process is disclosed | D48: 1 if explicit integration is stated; 0 if silent or only implied
A49: CDQ_M1 | B49: Climate Metrics and Targets | C49: Scope 1 GHG emissions are disclosed | D49: 1 if a Scope 1 figure is reported; 0 if not reported
A50: CDQ_M2 | B50: Climate Metrics and Targets | C50: Scope 2 GHG emissions are disclosed | D50: 1 if a Scope 2 figure is reported; 0 if not reported
A51: CDQ_M3 | B51: Climate Metrics and Targets | C51: Scope 3 GHG emissions are disclosed (where material) | D51: 1 if a Scope 3 figure is reported, or the firm explains a reasoned basis for omission; 0 if silent with no explanation
... A54: CDQ_M6 | B54: Climate Metrics and Targets | C54: Climate-related financial metrics are disclosed (e.g. internal carbon price, capex/opex aligned to climate transition) | D54: 1 if any such financial metric is disclosed; 0 if absent

Sheet Coding Sheet
A1: Key | B1: S/N | C1: Firm_ID | D1: Ticker | E1: Company Name | F1: Sector | G1: Year | H1: SDQ_G1 | I1: SDQ_G2 | J1: SDQ_G3 | K1: SDQ_G4 | L1: SDQ_G5 | M1: SDQ_S1 | N1: SDQ_S2 | O1: SDQ_S3 | P1: SDQ_S4 | Q1: SDQ_S5 | R1: SDQ_R1 | S1: SDQ_R2 | T1: SDQ_R3 | U1: SDQ_R4 | V1: SDQ_R5 | W1: SDQ_M1 | X1: SDQ_M2 | Y1: SDQ_M3 | Z1: SDQ_M4 | AA1: SDQ_M5 | AB1: SDQ_Items_Disclosed (of 20) | AC1: SDQ_Score (0-100) | AD1: CDQ_G1 | AE1: CDQ_G2 | AF1: CDQ_G3 | AG1: CDQ_S1 | AH1: CDQ_S2 | AI1: CDQ_S3 | AJ1: CDQ_S4 | AK1: CDQ_R1 | AL1: CDQ_R2 | AM1: CDQ_M1 | AN1: CDQ_M2 | AO1: CDQ_M3 | AP1: CDQ_M4 | AQ1: CDQ_M5 | AR1: CDQ_M6 | AS1: CDQ_Items_Disclosed (of 15) | AT1: CDQ_Score (0-100) | AU1: Coding_Notes / Source (document, page/section per firm-year)
A2: =C2&"_"&G2 -> 1_2021 | B2: 1 | C2: ='Panel Data (Long Format)'!B2 -> 1 | D2: ='Panel Data (Long Format)'!C2 -> ABBEYBANK | E2: ='Panel Data (Long Format)'!D2 -> Abbey Mortgage Bank Plc | F2: ='Panel Data (Long Format)'!E2 -> FINANCIAL SERVICES | G2: ='Panel Data (Long Format)'!F2 -> 2021 | H2: 0 | I2: 0 | J2: 0 | K2: 0 | L2: 0 | M2: 0 | N2: 0 | O2: 0 | P2: 0 | Q2: 0 | R2: 0 | S2: 0 | T2: 0 | U2: 0 | V2: 0 | W2: 1 | X2: 0 | Y2: 0 | Z2: 0 | AA2: 0 | AB2: =IF(COUNTBLANK(H2:AA2)>0,"",SUM(H2:AA2)) -> 1 | AC2: =IF(AB2="","",AB2/20*100) -> 5 | AD2: 0 | AE2: 0 | AF2: 0 | AG2: 0 | AH2: 0 | AI2: 0 | AJ2: 0 | AK2: 0 | AL2: 0 | AM2: 0 | AN2: 0 | AO2: 0 | AP2: 0 | AQ2: 0 | AR2: 0 | AS2: =IF(COUNTBLANK(AD2:AR2)>0,"",SUM(AD2:AR2)) -> 0 | AT2: =IF(AS2="","",AS2/15*100) -> 0 | AU2: Abbey Mortgage Bank Plc, Annual Report & Accounts FYE 31-Dec-2021 (Corporate Governance Report pp.33-38, Enterprise Risk Management Policy pp.42-46, Report of the Directors substantial-interest note p.premier). Source: anyflip.com/jfssr/cyis (Abbey Annual Report Final 2021_compressed), full text extracted and read. Board FY2021: Non-Executive Chairman + 4 NEDs + 3 EDs + 1 Independent NED = 9 total. SDQ_G5=0 (unlike FY2024): Ms. Jewel Okwechime, whose bio carries explicit environmental/sustainability credentials, was NOT yet on the board in FY2021 (absent from the FY2021 committee/EXCO membership lists) -- her appointment came later. SDQ_M1=1 (BORDERLINE, same as FY2024, flag for reliability recheck): 'last year there were no recorded cases of incidents in our operations' -- identical boilerplate to the FY2024 filing. All SDQ_R1-R5=0 and all CDQ=0: the FY2021 Enterprise Risk Management Policy lists the identical 9 risk categories as FY2024 (credit, liquidity, capital, operational, regulatory, reputational, legal, cyber, strategic) with no sustainability/ESG/climate risk category named anywhere; full-text keyword search for IFRS S1/S2, ISSB, Scope 1/2/3, GHG/carbon/emissions, scenario analysis, transition/physical risk returned zero matches. IFRS_S1S2_Adopter_Dummy=0 (no explicit or implied statement; CDQ=0/15 so the structural-alignment test also fails). SDQ=1/20=5%, CDQ=0/15=0%.
A3: =C3&"_"&G3 -> 1_2022 | B3: 2 | C3: ='Panel Data (Long Format)'!B3 -> 1 | D3: ='Panel Data (Long Format)'!C3 -> ABBEYBANK | E3: ='Panel Data (Long Format)'!D3 -> Abbey Mortgage Bank Plc | F3: ='Panel Data (Long Format)'!E3 -> FINANCIAL SERVICES | G3: ='Panel Data (Long Format)'!F3 -> 2022 | H3: 0 | I3: 0 | J3: 0 | K3: 0 | L3: 0 | M3: 0 | N3: 0 | O3: 0 | P3: 0 | Q3: 0 | R3: 0 | S3: 0 | T3: 0 | U3: 0 | V3: 0 | W3: 0 | X3: 0 | Y3: 0 | Z3: 0 | AA3: 0 | AB3: =IF(COUNTBLANK(H3:AA3)>0,"",SUM(H3:AA3)) -> 0 | AC3: =IF(AB3="","",AB3/20*100) -> 0 | AD3: 0 | AE3: 0 | AF3: 0 | AG3: 0 | AH3: 0 | AI3: 0 | AJ3: 0 | AK3: 0 | AL3: 0 | AM3: 0 | AN3: 0 | AO3: 0 | AP3: 0 | AQ3: 0 | AR3: 0 | AS3: =IF(COUNTBLANK(AD3:AR3)>0,"",SUM(AD3:AR3)) -> 0 | AT3: =IF(AS3="","",AS3/15*100) -> 0 | AU3: Abbey Mortgage Bank Plc, Annual Report & Audited FS FYE 31-Dec-2022 (NGX doclib doc #38233, filed Apr-2023). Corporate Governance Report pp.11-19 (board/committee structure named, no sustainability-specific oversight); 'Sustainable and Environmental Issues'/CSR section pp.17-18 (generic OH&S boilerplate, no entity-specific metrics/targets); Enterprise Risk Management Policy pp.21-25 (risk taxonomy = credit/capital/operational/liquidity/IT/regulatory/legal/reputational/strategic only, no sustainability/climate risk category); Notes to FS 'Standards issued but not yet effective' p.35 discusses only IFRS 17, no IFRS S1/S2/ISSB mention (Adopter_Dummy left blank).
A4: =C4&"_"&G4 -> 1_2023 | B4: 3 | C4: ='Panel Data (Long Format)'!B4 -> 1 | D4: ='Panel Data (Long Format)'!C4 -> ABBEYBANK | E4: ='Panel Data (Long Format)'!D4 -> Abbey Mortgage Bank Plc | F4: ='Panel Data (Long Format)'!E4 -> FINANCIAL SERVICES | G4: ='Panel Data (Long Format)'!F4 -> 2023 | H4: 0 | I4: 0 | J4: 0 | K4: 0 | L4: 1 | M4: 1 | N4: 0 | O4: 0 | P4: 0 | Q4: 0 | R4: 0 | S4: 0 | T4: 0 | U4: 0 | V4: 0 | W4: 0 | X4: 0 | Y4: 0 | Z4: 0 | AA4: 0 | AB4: =IF(COUNTBLANK(H4:AA4)>0,"",SUM(H4:AA4)) -> 2 | AC4: =IF(AB4="","",AB4/20*100) -> 10 | AD4: 0 | AE4: 0 | AF4: 0 | AG4: 0 | AH4: 0 | AI4: 0 | AJ4: 0 | AK4: 0 | AL4: 0 | AM4: 0 | AN4: 0 | AO4: 0 | AP4: 0 | AQ4: 0 | AR4: 0 | AS4: =IF(COUNTBLANK(AD4:AR4)>0,"",SUM(AD4:AR4)) -> 0 | AT4: =IF(AS4="","",AS4/15*100) -> 0 | AU4: Abbey Mortgage Bank Plc, FY2023 Annual Report (anyflip.com/ukxce/clsu/basic). LIMITATION: fetch returned only a partial preview (~pp.1-50 of 154); ERM Policy, Audit Committee report and Notes to FS (incl. standards-adoption note) not retrievable, so R1-R5/M1-M5 could not be fully verified -- scores likely understate true disclosure, flagged for future re-check if full document becomes accessible. Chairman's Statement 'ESG Focus' p.24: 'We are preparing for the adoption of IFRS S1 and IFRS S2 in accordance with the road map of the FRCN and NGX' -> Adopter_Dummy=0. Directors' Profile p.18 (Ms. Jewel Okwechime, NED): competencies include 'Environmental Engineering...Sustainability Business Development' -> G5=1. MD/CEO Statement p.32: environmental risk discussion (flood/landslide, cost-vs-impact dilemma) -> S1=1.
A5: =C5&"_"&G5 -> 1_2024 | B5: 4 | C5: ='Panel Data (Long Format)'!B5 -> 1 | D5: ='Panel Data (Long Format)'!C5 -> ABBEYBANK | E5: ='Panel Data (Long Format)'!D5 -> Abbey Mortgage Bank Plc | F5: ='Panel Data (Long Format)'!E5 -> FINANCIAL SERVICES | G5: ='Panel Data (Long Format)'!F5 -> 2024 | H5: 0 | I5: 0 | J5: 0 | K5: 0 | L5: 1 | M5: 0 | N5: 0 | O5: 0 | P5: 0 | Q5: 0 | R5: 0 | S5: 0 | T5: 0 | U5: 0 | V5: 0 | W5: 1 | X5: 0 | Y5: 0 | Z5: 0 | AA5: 0 | AB5: =IF(COUNTBLANK(H5:AA5)>0,"",SUM(H5:AA5)) -> 2 | AC5: =IF(AB5="","",AB5/20*100) -> 10 | AD5: 0 | AE5: 0 | AF5: 0 | AG5: 0 | AH5: 0 | AI5: 0 | AJ5: 0 | AK5: 0 | AL5: 0 | AM5: 0 | AN5: 0 | AO5: 0 | AP5: 0 | AQ5: 0 | AR5: 0 | AS5: =IF(COUNTBLANK(AD5:AR5)>0,"",SUM(AD5:AR5)) -> 0 | AT5: =IF(AS5="","",AS5/15*100) -> 0 | AU5: Abbey Mortgage Bank Plc, Annual Report & Accounts FYE 31-Dec-2024 (Corporate Governance Report pp.10-16, Enterprise Risk Management Policy pp.18-22, Report of the Directors pp.2-5). Source: prjdg-unstruc.s3.ca-central-1.amazonaws.com (via proshare.co listing), full text extracted and read. SDQ_G5=1: Board member Ms. Jewel Okwechime's profile explicitly names 'Environmental Engineering... Sustainability Business Development' expertise and prior roles as Senior Environmental Consultant/Adviser (p.13-14) -- specific, named expertise, satisfies the item. SDQ_M1=1 (BORDERLINE, flag for reliability recheck): scored on 'last year there were no recorded cases of incidents in our operations' (p.15, H&S) -- a specific, entity-level claim with an implied zero-figure, but it is a single-year statement, not a tracked/trended metric; a stricter coder could reasonably score this 0. All SDQ_R1-R5=0: the Enterprise Risk Management Policy (pp.18-22) is thorough and names 9 risk categories (credit, liquidity, capital, operational, regulatory, reputational, legal, information/cyber, strategic) but does NOT name sustainability/ESG/climate as a risk category anywhere in the document -- the ERM items score 0 because the risk process described is not sustainability-specific, per the instrument's requirement. All CDQ items=0: no mention of IFRS S1/S2/ISSB, Scope 1/2/3, GHG/carbon/emissions, climate scenario analysis, or physical/transition risk anywhere in the document (confirmed via full-text keyword search). IFRS_S1S2_Adopter_Dummy: left BLANK (not 0) -- no explicit adoption/non-adoption statement found, unlike BUACEMENT/BUAFOODS where the filing explicitly said 'not yet adopted'; silence here is not the same as an evidenced negative. SDQ=2/20=10%, CDQ=0/15=0%.
A6: =C6&"_"&G6 -> 1_2025 | B6: 5 | C6: ='Panel Data (Long Format)'!B6 -> 1 | D6: ='Panel Data (Long Format)'!C6 -> ABBEYBANK | E6: ='Panel Data (Long Format)'!D6 -> Abbey Mortgage Bank Plc | F6: ='Panel Data (Long Format)'!E6 -> FINANCIAL SERVICES | G6: ='Panel Data (Long Format)'!F6 -> 2025 | H6: 0 | I6: 0 | J6: 0 | K6: 0 | L6: 0 | M6: 0 | N6: 0 | O6: 0 | P6: 0 | Q6: 0 | R6: 0 | S6: 0 | T6: 0 | U6: 0 | V6: 0 | W6: 0 | X6: 0 | Y6: 0 | Z6: 0 | AA6: 0 | AB6: =IF(COUNTBLANK(H6:AA6)>0,"",SUM(H6:AA6)) -> 0 | AC6: =IF(AB6="","",AB6/20*100) -> 0 | AD6: 0 | AE6: 0 | AF6: 0 | AG6: 0 | AH6: 0 | AI6: 0 | AJ6: 0 | AK6: 0 | AL6: 0 | AM6: 0 | AN6: 0 | AO6: 0 | AP6: 0 | AQ6: 0 | AR6: 0 | AS6: =IF(COUNTBLANK(AD6:AR6)>0,"",SUM(AD6:AR6)) -> 0 | AT6: =IF(AS6="","",AS6/15*100) -> 0 | AU6: Abbey Mortgage Bank Plc, FY2025 filing (NGX doclib doc #45885, filed Jan-2026) -- condensed interim-style statement only (Introduction, Result-at-a-Glance, primary statements, Notes), no Directors'/Corporate Governance/CSR/ERM section unlike full FY2022/FY2023 ARs. Notes 2.2 'Changes in accounting policies' pp.7-8 lists IFRS 16, IAS 1 (x2), IAS 7/IFRS 7, IAS 21 amendments only -- no IFRS S1/S2/ISSB mention (Adopter_Dummy blank). Full-text keyword search (sustainab/ESG/environment/climate/carbon/emission/diversity/community) = zero hits.
A7: =C7&"_"&G7 -> 2_2021 | B7: 6 | C7: ='Panel Data (Long Format)'!B7 -> 2 | D7: ='Panel Data (Long Format)'!C7 -> ABCTRANS | E7: ='Panel Data (Long Format)'!D7 -> ABC Transport Plc | F7: ='Panel Data (Long Format)'!E7 -> SERVICES | G7: ='Panel Data (Long Format)'!F7 -> 2021 | H7: 0 | I7: 0 | J7: 0 | K7: 0 | L7: 0 | M7: 0 | N7: 0 | O7: 0 | P7: 0 | Q7: 0 | R7: 0 | S7: 0 | T7: 0 | U7: 0 | V7: 0 | W7: 1 | X7: 0 | Y7: 0 | Z7: 0 | AA7: 0 | AB7: =IF(COUNTBLANK(H7:AA7)>0,"",SUM(H7:AA7)) -> 1 | AC7: =IF(AB7="","",AB7/20*100) -> 5 | AD7: 0 | AE7: 0 | AF7: 0 | AG7: 0 | AH7: 0 | AI7: 0 | AJ7: 0 | AK7: 0 | AL7: 0 | AM7: 0 | AN7: 0 | AO7: 0 | AP7: 0 | AQ7: 0 | AR7: 0 | AS7: =IF(COUNTBLANK(AD7:AR7)>0,"",SUM(AD7:AR7)) -> 0 | AT7: =IF(AS7="","",AS7/15*100) -> 0 | AU7: GAP-FILL: ABCTRANS FY2021 (FY2021 Audited Financial Statements, NGX doclib, fetched directly): SDQ_M1=1 - Directors' Report Note 10 'DONATIONS' itemises Book launch N40,000, Youth Empowerments N219,000, Corporate gifts N2,411,250, Condolences/Burial/Weddings N1,611,706, totalling N4,281,956 (labelled N'000 in the source table, though the underlying figure's scale relative to company size suggests this may actually be stated in plain Naira rather than thousands - flagged as a units ambiguity, scored as disclosed regardless per the instrument's literal rule). No sustainability-specific board committee found (Board Risk Management Committee, Corporate Governance and Remuneration Committee, Credit Risk Management Committee - all generic operational/financial remits). No climate/GHG content found. CDQ=0/15.
A8: =C8&"_"&G8 -> 2_2022 | B8: 7 | C8: ='Panel Data (Long Format)'!B8 -> 2 | D8: ='Panel Data (Long Format)'!C8 -> ABCTRANS | E8: ='Panel Data (Long Format)'!D8 -> ABC Transport Plc | F8: ='Panel Data (Long Format)'!E8 -> SERVICES | G8: ='Panel Data (Long Format)'!F8 -> 2022 | H8: 0 | I8: 0 | J8: 0 | K8: 0 | L8: 0 | M8: 0 | N8: 0 | O8: 0 | P8: 0 | Q8: 0 | R8: 0 | S8: 0 | T8: 0 | U8: 0 | V8: 0 | W8: 0 | X8: 0 | Y8: 0 | Z8: 0 | AA8: 0 | AB8: =IF(COUNTBLANK(H8:AA8)>0,"",SUM(H8:AA8)) -> 0 | AC8: =IF(AB8="","",AB8/20*100) -> 0 | AD8: 0 | AE8: 0 | AF8: 0 | AG8: 0 | AH8: 0 | AI8: 0 | AJ8: 0 | AK8: 0 | AL8: 0 | AM8: 0 | AN8: 0 | AO8: 0 | AP8: 0 | AQ8: 0 | AR8: 0 | AS8: =IF(COUNTBLANK(AD8:AR8)>0,"",SUM(AD8:AR8)) -> 0 | AT8: =IF(AS8="","",AS8/15*100) -> 0 | AU8: ABC Transport Plc, Consolidated Financial Statements FYE 31-Dec-2022 (Report of the Directors, Report of the Audit Committee -- this filing has no separate Corporate Governance Report or Enterprise Risk Management Policy section, unlike ABBEYBANK; governance/sustainability content is limited to brief paragraphs embedded in the Directors' Report). Source: doclib.ngxgroup.com (38087_ABC_TRANSPORT_PLC..._2022...pdf), full text extracted and read. All SDQ/CDQ items score 0: the Directors' Report discusses employee safety ('quarterly safety re-orientation and training programmes', 'vehicles fitted with tracking devices and speed limiters', 'accident rate...well within acceptable limits') but gives no specific figure/metric (SDQ_M1 scored 0, stricter than ABBEYBANK's 'zero incidents' claim since this is vaguer, no number at all) and no sustainability-specific governance, strategy, risk, or target content anywhere. No IFRS S1/S2/ISSB, Scope 1/2/3, GHG/carbon, or climate-scenario language found (confirmed via full-text keyword search). No 'substantial interest in shares' table or explicit Non-Executive/Independent board-composition statement found in this filing -- Board_Independence and Ownership_Concentration left blank for FY2022 (optional/opportunistic fields per agreed methodology). IFRS_S1S2_Adopter_Dummy=0 (no statement found either way in this filing; see FY2025 row for this ticker's explicit 'not yet adopted' evidence). SDQ=0/20=0%, CDQ=0/15=0%.
A9: =C9&"_"&G9 -> 2_2023 | B9: 8 | C9: ='Panel Data (Long Format)'!B9 -> 2 | D9: ='Panel Data (Long Format)'!C9 -> ABCTRANS | E9: ='Panel Data (Long Format)'!D9 -> ABC Transport Plc | F9: ='Panel Data (Long Format)'!E9 -> SERVICES | G9: ='Panel Data (Long Format)'!F9 -> 2023 | H9: 0 | I9: 0 | J9: 0 | K9: 0 | L9: 0 | M9: 0 | N9: 0 | O9: 0 | P9: 0 | Q9: 0 | R9: 0 | S9: 0 | T9: 0 | U9: 0 | V9: 0 | W9: 1 | X9: 0 | Y9: 0 | Z9: 0 | AA9: 0 | AB9: =IF(COUNTBLANK(H9:AA9)>0,"",SUM(H9:AA9)) -> 1 | AC9: =IF(AB9="","",AB9/20*100) -> 5 | AD9: 0 | AE9: 0 | AF9: 0 | AG9: 0 | AH9: 0 | AI9: 0 | AJ9: 0 | AK9: 0 | AL9: 0 | AM9: 0 | AN9: 0 | AO9: 0 | AP9: 0 | AQ9: 0 | AR9: 0 | AS9: =IF(COUNTBLANK(AD9:AR9)>0,"",SUM(AD9:AR9)) -> 0 | AT9: =IF(AS9="","",AS9/15*100) -> 0 | AU9: GAP-FILL: ABCTRANS FY2023: SDQ_M1=1 - a GENUINE confirmed comparative figure was located within the FY2024 Annual Report and Consolidated and Separate Financial Statements (NGX doclib, fetched directly), Note 8 'DONATIONS AND GIFTS', showing a two-column table (headers both mislabelled '2024' in the source PDF, but representing FY2024 and its FY2023 comparative per standard AFS format) with a comparative total of N2,326,000 for FY2023 (vs N4,234,000 for FY2024, which was already coded in an earlier batch). No sustainability-specific board committee or climate content found in this document. CDQ=0/15.
A10: =C10&"_"&G10 -> 2_2024 | B10: 9 | C10: ='Panel Data (Long Format)'!B10 -> 2 | D10: ='Panel Data (Long Format)'!C10 -> ABCTRANS | E10: ='Panel Data (Long Format)'!D10 -> ABC Transport Plc | F10: ='Panel Data (Long Format)'!E10 -> SERVICES | G10: ='Panel Data (Long Format)'!F10 -> 2024 | H10: 0 | I10: 0 | J10: 0 | K10: 0 | L10: 0 | M10: 0 | N10: 0 | O10: 0 | P10: 0 | Q10: 0 | R10: 0 | S10: 0 | T10: 0 | U10: 0 | V10: 0 | W10: 0 | X10: 0 | Y10: 0 | Z10: 0 | AA10: 0 | AB10: =IF(COUNTBLANK(H10:AA10)>0,"",SUM(H10:AA10)) -> 0 | AC10: =IF(AB10="","",AB10/20*100) -> 0 | AD10: 0 | AE10: 0 | AF10: 0 | AG10: 0 | AH10: 0 | AI10: 0 | AJ10: 0 | AK10: 0 | AL10: 0 | AM10: 0 | AN10: 0 | AO10: 0 | AP10: 0 | AQ10: 0 | AR10: 0 | AS10: =IF(COUNTBLANK(AD10:AR10)>0,"",SUM(AD10:AR10)) -> 0 | AT10: =IF(AS10="","",AS10/15*100) -> 0 | AU10: ABC Transport Plc, Annual Report and Consolidated and Separate Financial Statements FYE 31-Dec-2024 (Corporate Information p.1, Notes to the Financial Statements -- Adoption of new and revised standards). Source: doclib.ngxgroup.com (43623_ABC_TRANSPORT_PLC..._2024...pdf), full text extracted and read. Board composition identical to FY2025: Chairman + Managing Director + 1 Executive Director + 4 Non-Executive Directors + 1 Independent Non-Executive Director = 8 total -> Board_Independence=12.5%. IFRS_S1S2_Adopter_Dummy=0, EXPLICITLY EVIDENCED: identical 'not yet adopted' note as FY2025 -- 'The mandatory adoption date is 1 January 2028... effective for annual reporting periods beginning on or after 1 January 2028, with earlier application permitted', explicitly listed among standards 'not yet effective as at 31 December 2024 and have not been early adopted by the Company'. All SDQ/CDQ items score 0: same thin-disclosure pattern as FY2022/FY2025 -- 'accident rate...well within acceptable limits' with no specific figure, no sustainability-specific governance/risk/target content, no substantial-interest-in-shares table found. SDQ=0/20=0%, CDQ=0/15=0%.
A11: =C11&"_"&G11 -> 2_2025 | B11: 10 | C11: ='Panel Data (Long Format)'!B11 -> 2 | D11: ='Panel Data (Long Format)'!C11 -> ABCTRANS | E11: ='Panel Data (Long Format)'!D11 -> ABC Transport Plc | F11: ='Panel Data (Long Format)'!E11 -> SERVICES | G11: ='Panel Data (Long Format)'!F11 -> 2025 | H11: 0 | I11: 0 | J11: 0 | K11: 0 | L11: 0 | M11: 0 | N11: 0 | O11: 0 | P11: 0 | Q11: 0 | R11: 0 | S11: 0 | T11: 0 | U11: 0 | V11: 0 | W11: 0 | X11: 0 | Y11: 0 | Z11: 0 | AA11: 0 | AB11: =IF(COUNTBLANK(H11:AA11)>0,"",SUM(H11:AA11)) -> 0 | AC11: =IF(AB11="","",AB11/20*100) -> 0 | AD11: 0 | AE11: 0 | AF11: 0 | AG11: 0 | AH11: 0 | AI11: 0 | AJ11: 0 | AK11: 0 | AL11: 0 | AM11: 0 | AN11: 0 | AO11: 0 | AP11: 0 | AQ11: 0 | AR11: 0 | AS11: =IF(COUNTBLANK(AD11:AR11)>0,"",SUM(AD11:AR11)) -> 0 | AT11: =IF(AS11="","",AS11/15*100) -> 0 | AU11: ABC Transport Plc, Consolidated and Separate Annual Report and Financial Statements FYE 31-Dec-2025 (Corporate Information p.1, Report of the Directors, Notes to the Financial Statements -- Adoption of new and revised standards). Source: doclib.ngxgroup.com (46506_ABC_TRANSPORT_PLC..._2025...pdf), full text extracted and read. Board composition explicitly stated (Corporate Information page): Chairman + Managing Director + 1 Executive Director + 4 Non-Executive Directors + 1 Independent Non-Executive Director = 8 total -> Board_Independence=12.5%. IFRS_S1S2_Adopter_Dummy=0, EXPLICITLY EVIDENCED: Note 2.7/3 'New standards, amendments and interpretations not yet adopted' lists 'IFRS S1 General Requirements for Disclosure of Sustainability-related Financial Information' with 'The mandatory adoption date is 1 January 2028... effective for annual reporting periods beginning on or after 1 January 2028, with earlier application permitted' -- boilerplate acknowledging the future standard exists, with no indication the company chose early/voluntary application, so this is a confirmed NON-adopter, not a blank/unknown. This same note structure also means the standard's four-pillar description in the note itself is NOT scored toward SDQ/CDQ (it describes what the future standard will require, not the entity's own current disclosure practice). All SDQ/CDQ items score 0: same thin-disclosure pattern as FY2022 -- safety/accident -rate language present but no specific figure, no sustainability-specific governance/risk/target content. No 'substantial interest in shares' table found -- Ownership_Concentration left blank (optional field). SDQ=0/20=0%, CDQ=0/15=0%.
A12: =C12&"_"&G12 -> 3_2021 | B12: 11 | C12: ='Panel Data (Long Format)'!B12 -> 3 | D12: ='Panel Data (Long Format)'!C12 -> ACADEMY | E12: ='Panel Data (Long Format)'!D12 -> Academy Press Plc | F12: ='Panel Data (Long Format)'!E12 -> SERVICES | G12: ='Panel Data (Long Format)'!F12 -> 2021 | H12: 0 | I12: 0 | J12: 0 | K12: 0 | L12: 0 | M12: 0 | N12: 0 | O12: 0 | P12: 0 | Q12: 0 | R12: 0 | S12: 0 | T12: 0 | U12: 0 | V12: 0 | W12: 0 | X12: 0 | Y12: 0 | Z12: 0 | AA12: 0 | AB12: =IF(COUNTBLANK(H12:AA12)>0,"",SUM(H12:AA12)) -> 0 | AC12: =IF(AB12="","",AB12/20*100) -> 0 | AD12: 0 | AE12: 0 | AF12: 0 | AG12: 0 | AH12: 0 | AI12: 0 | AJ12: 0 | AK12: 0 | AL12: 0 | AM12: 0 | AN12: 0 | AO12: 0 | AP12: 0 | AQ12: 0 | AR12: 0 | AS12: =IF(COUNTBLANK(AD12:AR12)>0,"",SUM(AD12:AR12)) -> 0 | AT12: =IF(AS12="","",AS12/15*100) -> 0 | AU12: GAP-FILL: ACADEMY FY2021: not verified this session - the only primary source successfully fetched was the Annual Report for the year ended 31 March 2024 (NGX doclib), whose comparative column covers FY2023 only. Scored 0/20 SDQ, 0/15 CDQ, FLAGGED as unconfirmed pending re-verification against a dedicated FY2021 filing.
A13: =C13&"_"&G13 -> 3_2022 | B13: 12 | C13: ='Panel Data (Long Format)'!B13 -> 3 | D13: ='Panel Data (Long Format)'!C13 -> ACADEMY | E13: ='Panel Data (Long Format)'!D13 -> Academy Press Plc | F13: ='Panel Data (Long Format)'!E13 -> SERVICES | G13: ='Panel Data (Long Format)'!F13 -> 2022 | H13: 0 | I13: 0 | J13: 0 | K13: 0 | L13: 0 | M13: 0 | N13: 0 | O13: 0 | P13: 0 | Q13: 0 | R13: 0 | S13: 0 | T13: 0 | U13: 0 | V13: 0 | W13: 0 | X13: 0 | Y13: 0 | Z13: 0 | AA13: 0 | AB13: =IF(COUNTBLANK(H13:AA13)>0,"",SUM(H13:AA13)) -> 0 | AC13: =IF(AB13="","",AB13/20*100) -> 0 | AD13: 0 | AE13: 0 | AF13: 0 | AG13: 0 | AH13: 0 | AI13: 0 | AJ13: 0 | AK13: 0 | AL13: 0 | AM13: 0 | AN13: 0 | AO13: 0 | AP13: 0 | AQ13: 0 | AR13: 0 | AS13: =IF(COUNTBLANK(AD13:AR13)>0,"",SUM(AD13:AR13)) -> 0 | AT13: =IF(AS13="","",AS13/15*100) -> 0 | AU13: GAP-FILL: ACADEMY FY2022: not verified this session - the only primary source successfully fetched was the Annual Report for the year ended 31 March 2024 (NGX doclib), whose comparative column covers FY2023 only. Scored 0/20 SDQ, 0/15 CDQ, FLAGGED as unconfirmed pending re-verification against a dedicated FY2022 filing.
... A23: =C23&"_"&G23 -> 5_2022 | B23: 22 | C23: ='Panel Data (Long Format)'!B23 -> 5 | D23: ='Panel Data (Long Format)'!C23 -> AFRINSURE | E23: ='Panel Data (Long Format)'!D23 -> African Alliance Insurance Plc | F23: ='Panel Data (Long Format)'!E23 -> FINANCIAL SERVICES | G23: ='Panel Data (Long Format)'!F23 -> 2022 | H23: 0 | I23: 0 | J23: 0 | K23: 0 | L23: 0 | M23: 0 | N23: 0 | O23: 0 | P23: 0 | Q23: 0 | R23: 0 | S23: 0 | T23: 0 | U23: 0 | V23: 0 | W23: 0 | X23: 0 | Y23: 0 | Z23: 0 | AA23: 0 | AB23: =IF(COUNTBLANK(H23:AA23)>0,"",SUM(H23:AA23)) -> 0 | AC23: =IF(AB23="","",AB23/20*100) -> 0 | AD23: 0 | AE23: 0 | AF23: 0 | AG23: 0 | AH23: 0 | AI23: 0 | AJ23: 0 | AK23: 0 | AL23: 0 | AM23: 0 | AN23: 0 | AO23: 0 | AP23: 0 | AQ23: 0 | AR23: 0 | AS23: =IF(COUNTBLANK(AD23:AR23)>0,"",SUM(AD23:AR23)) -> 0 | AT23: =IF(AS23="","",AS23/15*100) -> 0 | AU23: African Alliance Insurance Plc FY2022 Consolidated FS (NGX doclib #39898, filed Nov-2023, late-filed). Zero sustainability/climate/ESG keyword occurrences confirmed by full-document search.
A24: =C24&"_"&G24 -> 5_2023 | B24: 23 | C24: ='Panel Data (Long Format)'!B24 -> 5 | D24: ='Panel Data (Long Format)'!C24 -> AFRINSURE | E24: ='Panel Data (Long Format)'!D24 -> African Alliance Insurance Plc | F24: ='Panel Data (Long Format)'!E24 -> FINANCIAL SERVICES | G24: ='Panel Data (Long Format)'!F24 -> 2023 | AB24: =IF(COUNTBLANK(H24:AA24)>0,"",SUM(H24:AA24)) | AC24: =IF(AB24="","",AB24/20*100) | AS24: =IF(COUNTBLANK(AD24:AR24)>0,"",SUM(AD24:AR24)) | AT24: =IF(AS24="","",AS24/15*100) | AU24: GENUINE GAP: NGX suspended AFRINSURE trading for late/non-filing; NAICOM dissolved the company's board and management in October 2024 over solvency concerns; NAICOM only handed control to a new board in June 2026. Web/doclib searches found no FY2023 audited FS filed.
A25: =C25&"_"&G25 -> 5_2024 | B25: 24 | C25: ='Panel Data (Long Format)'!B25 -> 5 | D25: ='Panel Data (Long Format)'!C25 -> AFRINSURE | E25: ='Panel Data (Long Format)'!D25 -> African Alliance Insurance Plc | F25: ='Panel Data (Long Format)'!E25 -> FINANCIAL SERVICES | G25: ='Panel Data (Long Format)'!F25 -> 2024 | AB25: =IF(COUNTBLANK(H25:AA25)>0,"",SUM(H25:AA25)) | AC25: =IF(AB25="","",AB25/20*100) | AS25: =IF(COUNTBLANK(AD25:AR25)>0,"",SUM(AD25:AR25)) | AT25: =IF(AS25="","",AS25/15*100) | AU25: GENUINE GAP: Same regulatory breakdown as FY2023 (board dissolved Oct-2024 mid-year); no FY2024 audited FS located despite search attempts.
A26: =C26&"_"&G26 -> 5_2025 | B26: 25 | C26: ='Panel Data (Long Format)'!B26 -> 5 | D26: ='Panel Data (Long Format)'!C26 -> AFRINSURE | E26: ='Panel Data (Long Format)'!D26 -> African Alliance Insurance Plc | F26: ='Panel Data (Long Format)'!E26 -> FINANCIAL SERVICES | G26: ='Panel Data (Long Format)'!F26 -> 2025 | AB26: =IF(COUNTBLANK(H26:AA26)>0,"",SUM(H26:AA26)) | AC26: =IF(AB26="","",AB26/20*100) | AS26: =IF(COUNTBLANK(AD26:AR26)>0,"",SUM(AD26:AR26)) | AT26: =IF(AS26="","",AS26/15*100) | AU26: GENUINE GAP: Company under NAICOM-appointed interim management through most of FY2025; new board only installed June 2026; no FY2025 audited FS located.
A27: =C27&"_"&G27 -> 6_2021 | B27: 26 | C27: ='Panel Data (Long Format)'!B27 -> 6 | D27: ='Panel Data (Long Format)'!C27 -> AFRIPRUD | E27: ='Panel Data (Long Format)'!D27 -> Africa Prudential Plc | F27: ='Panel Data (Long Format)'!E27 -> FINANCIAL SERVICES | G27: ='Panel Data (Long Format)'!F27 -> 2021 | H27: 0 | I27: 0 | J27: 0 | K27: 0 | L27: 0 | M27: 0 | N27: 0 | O27: 0 | P27: 0 | Q27: 0 | R27: 0 | S27: 0 | T27: 0 | U27: 0 | V27: 0 | W27: 0 | X27: 0 | Y27: 0 | Z27: 0 | AA27: 0 | AB27: =IF(COUNTBLANK(H27:AA27)>0,"",SUM(H27:AA27)) -> 0 | AC27: =IF(AB27="","",AB27/20*100) -> 0 | AD27: 0 | AE27: 0 | AF27: 0 | AG27: 0 | AH27: 0 | AI27: 0 | AJ27: 0 | AK27: 0 | AL27: 0 | AM27: 0 | AN27: 0 | AO27: 0 | AP27: 0 | AQ27: 0 | AR27: 0 | AS27: =IF(COUNTBLANK(AD27:AR27)>0,"",SUM(AD27:AR27)) -> 0 | AT27: =IF(AS27="","",AS27/15*100) -> 0 | AU27: Africa Prudential Plc FY2021 Audited FS (NGX doclib #35166), 'Sustainability and CSR Report' section. No board-level sustainability committee (only Audit&Governance, Finance&Investment, Product&Projects committees exist). Generic CSR narrative only (tree planting, energy-efficient bulbs, EDMMS portal reducing 'fuel use/CO2'); explicitly states 'implementation of Sustainability Principles will continue to remain a work in progress.' No metrics, targets, or specific risks named.
A28: =C28&"_"&G28 -> 6_2022 | B28: 27 | C28: ='Panel Data (Long Format)'!B28 -> 6 | D28: ='Panel Data (Long Format)'!C28 -> AFRIPRUD | E28: ='Panel Data (Long Format)'!D28 -> Africa Prudential Plc | F28: ='Panel Data (Long Format)'!E28 -> FINANCIAL SERVICES | G28: ='Panel Data (Long Format)'!F28 -> 2022 | H28: 0 | I28: 0 | J28: 0 | K28: 0 | L28: 0 | M28: 0 | N28: 0 | O28: 0 | P28: 0 | Q28: 0 | R28: 0 | S28: 0 | T28: 0 | U28: 0 | V28: 0 | W28: 0 | X28: 0 | Y28: 0 | Z28: 0 | AA28: 0 | AB28: =IF(COUNTBLANK(H28:AA28)>0,"",SUM(H28:AA28)) -> 0 | AC28: =IF(AB28="","",AB28/20*100) -> 0 | AD28: 0 | AE28: 0 | AF28: 0 | AG28: 0 | AH28: 0 | AI28: 0 | AJ28: 0 | AK28: 0 | AL28: 0 | AM28: 0 | AN28: 0 | AO28: 0 | AP28: 0 | AQ28: 0 | AR28: 0 | AS28: =IF(COUNTBLANK(AD28:AR28)>0,"",SUM(AD28:AR28)) -> 0 | AT28: =IF(AS28="","",AS28/15*100) -> 0 | AU28: Africa Prudential Plc FY2022 Audited FS (NGX doclib, Africa_Prudential_Plc_-_2022_AFS.pdf). Same boilerplate CR&S pattern as FY2021/2023/2024, confirmed by cross-year text comparison.
A29: =C29&"_"&G29 -> 6_2023 | B29: 28 | C29: ='Panel Data (Long Format)'!B29 -> 6 | D29: ='Panel Data (Long Format)'!C29 -> AFRIPRUD | E29: ='Panel Data (Long Format)'!D29 -> Africa Prudential Plc | F29: ='Panel Data (Long Format)'!E29 -> FINANCIAL SERVICES | G29: ='Panel Data (Long Format)'!F29 -> 2023 | H29: 0 | I29: 0 | J29: 0 | K29: 0 | L29: 0 | M29: 0 | N29: 0 | O29: 0 | P29: 0 | Q29: 0 | R29: 0 | S29: 0 | T29: 0 | U29: 0 | V29: 0 | W29: 0 | X29: 0 | Y29: 0 | Z29: 0 | AA29: 0 | AB29: =IF(COUNTBLANK(H29:AA29)>0,"",SUM(H29:AA29)) -> 0 | AC29: =IF(AB29="","",AB29/20*100) -> 0 | AD29: 0 | AE29: 0 | AF29: 0 | AG29: 0 | AH29: 0 | AI29: 0 | AJ29: 0 | AK29: 0 | AL29: 0 | AM29: 0 | AN29: 0 | AO29: 0 | AP29: 0 | AQ29: 0 | AR29: 0 | AS29: =IF(COUNTBLANK(AD29:AR29)>0,"",SUM(AD29:AR29)) -> 0 | AT29: =IF(AS29="","",AS29/15*100) -> 0 | AU29: Africa Prudential Plc FY2023 Audited FS (NGX doclib #40447). CSR/Sustainability text verbatim-identical to FY2021 report. No IFRS S1/S2/ISSB mention despite FRC Nigeria externally listing AFRIPRUD as a 'voluntary adopter' -- nothing in this document itself supports that as of FY2023; coded strictly from primary-document text per project convention.
A30: =C30&"_"&G30 -> 6_2024 | B30: 29 | C30: ='Panel Data (Long Format)'!B30 -> 6 | D30: ='Panel Data (Long Format)'!C30 -> AFRIPRUD | E30: ='Panel Data (Long Format)'!D30 -> Africa Prudential Plc | F30: ='Panel Data (Long Format)'!E30 -> FINANCIAL SERVICES | G30: ='Panel Data (Long Format)'!F30 -> 2024 | H30: 0 | I30: 0 | J30: 0 | K30: 0 | L30: 0 | M30: 0 | N30: 0 | O30: 0 | P30: 0 | Q30: 0 | R30: 0 | S30: 0 | T30: 0 | U30: 0 | V30: 0 | W30: 0 | X30: 0 | Y30: 0 | Z30: 0 | AA30: 0 | AB30: =IF(COUNTBLANK(H30:AA30)>0,"",SUM(H30:AA30)) -> 0 | AC30: =IF(AB30="","",AB30/20*100) -> 0 | AD30: 0 | AE30: 0 | AF30: 0 | AG30: 0 | AH30: 0 | AI30: 0 | AJ30: 0 | AK30: 0 | AL30: 0 | AM30: 0 | AN30: 0 | AO30: 0 | AP30: 0 | AQ30: 0 | AR30: 0 | AS30: =IF(COUNTBLANK(AD30:AR30)>0,"",SUM(AD30:AR30)) -> 0 | AT30: =IF(AS30="","",AS30/15*100) -> 0 | AU30: Africa Prudential Plc FY2024 Audited FS (NGX doclib #43304). CSR/Sustainability section again verbatim-identical to prior years. No board sustainability oversight, no metrics, no IFRS S1/S2 mention found.
A31: =C31&"_"&G31 -> 6_2025 | B31: 30 | C31: ='Panel Data (Long Format)'!B31 -> 6 | D31: ='Panel Data (Long Format)'!C31 -> AFRIPRUD | E31: ='Panel Data (Long Format)'!D31 -> Africa Prudential Plc | F31: ='Panel Data (Long Format)'!E31 -> FINANCIAL SERVICES | G31: ='Panel Data (Long Format)'!F31 -> 2025 | H31: 0 | I31: 0 | J31: 0 | K31: 0 | L31: 0 | M31: 0 | N31: 0 | O31: 0 | P31: 0 | Q31: 0 | R31: 0 | S31: 0 | T31: 0 | U31: 0 | V31: 0 | W31: 0 | X31: 0 | Y31: 0 | Z31: 0 | AA31: 0 | AB31: =IF(COUNTBLANK(H31:AA31)>0,"",SUM(H31:AA31)) -> 0 | AC31: =IF(AB31="","",AB31/20*100) -> 0 | AD31: 0 | AE31: 0 | AF31: 0 | AG31: 0 | AH31: 0 | AI31: 0 | AJ31: 0 | AK31: 0 | AL31: 0 | AM31: 0 | AN31: 0 | AO31: 0 | AP31: 0 | AQ31: 0 | AR31: 0 | AS31: =IF(COUNTBLANK(AD31:AR31)>0,"",SUM(AD31:AR31)) -> 0 | AT31: =IF(AS31="","",AS31/15*100) -> 0 | AU31: Africa Prudential Plc FY2025 Audited FS (NGX doclib, AFRICA_PRUDENTIAL_PLC_-_2025_AUDITED_FINANCIAL_STATEMENTS.pdf). Sustainability section rewritten with more modern language ('Our Sustainability Philosophy', 'ESG approach', reduced travel emissions) but still no quantified metrics, no targets, no board committee, and critically no IFRS S1/S2/ISSB mention despite FRC's external 'voluntary adopter' designation -- coded strictly from document text per project convention.
A32: =C32&"_"&G32 -> 7_2021 | B32: 31 | C32: ='Panel Data (Long Format)'!B32 -> 7 | D32: ='Panel Data (Long Format)'!C32 -> AFROMEDIA | E32: ='Panel Data (Long Format)'!D32 -> Afromedia Plc | F32: ='Panel Data (Long Format)'!E32 -> SERVICES | G32: ='Panel Data (Long Format)'!F32 -> 2021 | H32: 0 | I32: 0 | J32: 0 | K32: 0 | L32: 0 | M32: 0 | N32: 0 | O32: 0 | P32: 0 | Q32: 0 | R32: 0 | S32: 0 | T32: 0 | U32: 0 | V32: 0 | W32: 0 | X32: 0 | Y32: 0 | Z32: 0 | AA32: 0 | AB32: =IF(COUNTBLANK(H32:AA32)>0,"",SUM(H32:AA32)) -> 0 | AC32: =IF(AB32="","",AB32/20*100) -> 0 | AD32: 0 | AE32: 0 | AF32: 0 | AG32: 0 | AH32: 0 | AI32: 0 | AJ32: 0 | AK32: 0 | AL32: 0 | AM32: 0 | AN32: 0 | AO32: 0 | AP32: 0 | AQ32: 0 | AR32: 0 | AS32: =IF(COUNTBLANK(AD32:AR32)>0,"",SUM(AD32:AR32)) -> 0 | AT32: =IF(AS32="","",AS32/15*100) -> 0 | AU32: Afromedia Plc FY2021 Audited FS (NGX doclib #35538). Zero sustainability/climate/ESG/GHG/carbon keyword occurrences. Only generic 'committee' references are audit committee and IFRS-8 steering committee (segment reporting), not sustainability-related.
A33: =C33&"_"&G33 -> 7_2022 | B33: 32 | C33: ='Panel Data (Long Format)'!B33 -> 7 | D33: ='Panel Data (Long Format)'!C33 -> AFROMEDIA | E33: ='Panel Data (Long Format)'!D33 -> Afromedia Plc | F33: ='Panel Data (Long Format)'!E33 -> SERVICES | G33: ='Panel Data (Long Format)'!F33 -> 2022 | H33: 0 | I33: 0 | J33: 0 | K33: 0 | L33: 0 | M33: 0 | N33: 0 | O33: 0 | P33: 0 | Q33: 0 | R33: 0 | S33: 0 | T33: 0 | U33: 0 | V33: 0 | W33: 0 | X33: 0 | Y33: 0 | Z33: 0 | AA33: 0 | AB33: =IF(COUNTBLANK(H33:AA33)>0,"",SUM(H33:AA33)) -> 0 | AC33: =IF(AB33="","",AB33/20*100) -> 0 | AD33: 0 | AE33: 0 | AF33: 0 | AG33: 0 | AH33: 0 | AI33: 0 | AJ33: 0 | AK33: 0 | AL33: 0 | AM33: 0 | AN33: 0 | AO33: 0 | AP33: 0 | AQ33: 0 | AR33: 0 | AS33: =IF(COUNTBLANK(AD33:AR33)>0,"",SUM(AD33:AR33)) -> 0 | AT33: =IF(AS33="","",AS33/15*100) -> 0 | AU33: Afromedia Plc FY2022 Audited FS (NGX doclib #39227, filed Aug-2023). Zero sustainability/climate/ESG keyword occurrences. Filing found despite prior-sweep 'NOT_FOUND' flag -- filed late, shortly after NGX suspended the stock (11-Jul-2023) for non-filing.
A34: =C34&"_"&G34 -> 7_2023 | B34: 33 | C34: ='Panel Data (Long Format)'!B34 -> 7 | D34: ='Panel Data (Long Format)'!C34 -> AFROMEDIA | E34: ='Panel Data (Long Format)'!D34 -> Afromedia Plc | F34: ='Panel Data (Long Format)'!E34 -> SERVICES | G34: ='Panel Data (Long Format)'!F34 -> 2023 | AB34: =IF(COUNTBLANK(H34:AA34)>0,"",SUM(H34:AA34)) | AC34: =IF(AB34="","",AB34/20*100) | AS34: =IF(COUNTBLANK(AD34:AR34)>0,"",SUM(AD34:AR34)) | AT34: =IF(AS34="","",AS34/15*100) | AU34: GENUINE GAP: AFROMEDIA suspended from NGX trading facilities effective 11-Jul-2023 for failing to file FY2022 accounts on time; no FY2023 audited FS located. Company reported to be under going-concern uncertainty.
A35: =C35&"_"&G35 -> 7_2024 | B35: 34 | C35: ='Panel Data (Long Format)'!B35 -> 7 | D35: ='Panel Data (Long Format)'!C35 -> AFROMEDIA | E35: ='Panel Data (Long Format)'!D35 -> Afromedia Plc | F35: ='Panel Data (Long Format)'!E35 -> SERVICES | G35: ='Panel Data (Long Format)'!F35 -> 2024 | AB35: =IF(COUNTBLANK(H35:AA35)>0,"",SUM(H35:AA35)) | AC35: =IF(AB35="","",AB35/20*100) | AS35: =IF(COUNTBLANK(AD35:AR35)>0,"",SUM(AD35:AR35)) | AT35: =IF(AS35="","",AS35/15*100) | AU35: GENUINE GAP: No FY2024 audited FS located; company remains suspended/delinquent on NGX.
A36: =C36&"_"&G36 -> 7_2025 | B36: 35 | C36: ='Panel Data (Long Format)'!B36 -> 7 | D36: ='Panel Data (Long Format)'!C36 -> AFROMEDIA | E36: ='Panel Data (Long Format)'!D36 -> Afromedia Plc | F36: ='Panel Data (Long Format)'!E36 -> SERVICES | G36: ='Panel Data (Long Format)'!F36 -> 2025 | AB36: =IF(COUNTBLANK(H36:AA36)>0,"",SUM(H36:AA36)) | AC36: =IF(AB36="","",AB36/20*100) | AS36: =IF(COUNTBLANK(AD36:AR36)>0,"",SUM(AD36:AR36)) | AT36: =IF(AS36="","",AS36/15*100) | AU36: GENUINE GAP: No FY2025 audited FS located; no evidence of resumed filing found.
A37: =C37&"_"&G37 -> 8_2021 | B37: 36 | C37: ='Panel Data (Long Format)'!B37 -> 8 | D37: ='Panel Data (Long Format)'!C37 -> AIICO | E37: ='Panel Data (Long Format)'!D37 -> AIICO Insurance Plc | F37: ='Panel Data (Long Format)'!E37 -> FINANCIAL SERVICES | G37: ='Panel Data (Long Format)'!F37 -> 2021 | H37: 1 | I37: 1 | J37: 0 | K37: 0 | L37: 0 | M37: 0 | N37: 0 | O37: 0 | P37: 0 | Q37: 0 | R37: 1 | S37: 0 | T37: 1 | U37: 1 | V37: 0 | W37: 0 | X37: 0 | Y37: 0 | Z37: 0 | AA37: 0 | AB37: =IF(COUNTBLANK(H37:AA37)>0,"",SUM(H37:AA37)) -> 5 | AC37: =IF(AB37="","",AB37/20*100) -> 25 | AD37: 0 | AE37: 0 | AF37: 0 | AG37: 0 | AH37: 0 | AI37: 0 | AJ37: 0 | AK37: 0 | AL37: 0 | AM37: 0 | AN37: 0 | AO37: 0 | AP37: 0 | AQ37: 0 | AR37: 0 | AS37: =IF(COUNTBLANK(AD37:AR37)>0,"",SUM(AD37:AR37)) -> 0 | AT37: =IF(AS37="","",AS37/15*100) -> 0 | AU37: AIICO Insurance Plc 2021 Annual Report (aiicoplc.com). Generic 'Corporate Responsibility & Sustainability Policy' narrative; CR&S Unit + Environmental and Social Committee (reports to Board/Exec Mgmt) named (G1,G2=1). SEMS (Social & Environmental Mgmt Systems, est. 2016) cited as 'integral part of risk assessment process' (R1,R4=1). No frequency/mechanism detail, no quantified metrics/targets, no climate-specific content anywhere.
A38: =C38&"_"&G38 -> 8_2022 | B38: 37 | C38: ='Panel Data (Long Format)'!B38 -> 8 | D38: ='Panel Data (Long Format)'!C38 -> AIICO | E38: ='Panel Data (Long Format)'!D38 -> AIICO Insurance Plc | F38: ='Panel Data (Long Format)'!E38 -> FINANCIAL SERVICES | G38: ='Panel Data (Long Format)'!F38 -> 2022 | H38: 1 | I38: 1 | J38: 0 | K38: 0 | L38: 0 | M38: 0 | N38: 0 | O38: 0 | P38: 0 | Q38: 0 | R38: 1 | S38: 0 | T38: 1 | U38: 1 | V38: 0 | W38: 0 | X38: 0 | Y38: 0 | Z38: 0 | AA38: 0 | AB38: =IF(COUNTBLANK(H38:AA38)>0,"",SUM(H38:AA38)) -> 5 | AC38: =IF(AB38="","",AB38/20*100) -> 25 | AD38: 0 | AE38: 0 | AF38: 0 | AG38: 0 | AH38: 0 | AI38: 0 | AJ38: 0 | AK38: 0 | AL38: 0 | AM38: 0 | AN38: 0 | AO38: 0 | AP38: 0 | AQ38: 0 | AR38: 0 | AS38: =IF(COUNTBLANK(AD38:AR38)>0,"",SUM(AD38:AR38)) -> 0 | AT38: =IF(AS38="","",AS38/15*100) -> 0 | AU38: AIICO Insurance Plc 2022 Annual Report (aiicoplc.com). CR&S policy text verbatim-identical to FY2021 report (confirmed by direct text comparison) -- same coding applies.
A39: =C39&"_"&G39 -> 8_2023 | B39: 38 | C39: ='Panel Data (Long Format)'!B39 -> 8 | D39: ='Panel Data (Long Format)'!C39 -> AIICO | E39: ='Panel Data (Long Format)'!D39 -> AIICO Insurance Plc | F39: ='Panel Data (Long Format)'!E39 -> FINANCIAL SERVICES | G39: ='Panel Data (Long Format)'!F39 -> 2023 | H39: 1 | I39: 1 | J39: 0 | K39: 0 | L39: 0 | M39: 0 | N39: 0 | O39: 0 | P39: 0 | Q39: 0 | R39: 1 | S39: 0 | T39: 1 | U39: 1 | V39: 0 | W39: 0 | X39: 0 | Y39: 0 | Z39: 0 | AA39: 0 | AB39: =IF(COUNTBLANK(H39:AA39)>0,"",SUM(H39:AA39)) -> 5 | AC39: =IF(AB39="","",AB39/20*100) -> 25 | AD39: 0 | AE39: 0 | AF39: 0 | AG39: 0 | AH39: 0 | AI39: 0 | AJ39: 0 | AK39: 0 | AL39: 0 | AM39: 0 | AN39: 0 | AO39: 0 | AP39: 0 | AQ39: 0 | AR39: 0 | AS39: =IF(COUNTBLANK(AD39:AR39)>0,"",SUM(AD39:AR39)) -> 0 | AT39: =IF(AS39="","",AS39/15*100) -> 0 | AU39: AIICO Insurance Plc 2023 Annual Report (aiicoplc.com). CR&S policy text again verbatim-identical to FY2021/FY2022. No IFRS S1/S2/ISSB mention anywhere.
A40: =C40&"_"&G40 -> 8_2024 | B40: 39 | C40: ='Panel Data (Long Format)'!B40 -> 8 | D40: ='Panel Data (Long Format)'!C40 -> AIICO | E40: ='Panel Data (Long Format)'!D40 -> AIICO Insurance Plc | F40: ='Panel Data (Long Format)'!E40 -> FINANCIAL SERVICES | G40: ='Panel Data (Long Format)'!F40 -> 2024 | H40: 1 | I40: 1 | J40: 0 | K40: 0 | L40: 0 | M40: 0 | N40: 0 | O40: 0 | P40: 0 | Q40: 0 | R40: 1 | S40: 0 | T40: 1 | U40: 1 | V40: 0 | W40: 0 | X40: 0 | Y40: 0 | Z40: 0 | AA40: 0 | AB40: =IF(COUNTBLANK(H40:AA40)>0,"",SUM(H40:AA40)) -> 5 | AC40: =IF(AB40="","",AB40/20*100) -> 25 | AD40: 0 | AE40: 0 | AF40: 0 | AG40: 0 | AH40: 0 | AI40: 0 | AJ40: 0 | AK40: 0 | AL40: 0 | AM40: 0 | AN40: 0 | AO40: 0 | AP40: 0 | AQ40: 0 | AR40: 0 | AS40: =IF(COUNTBLANK(AD40:AR40)>0,"",SUM(AD40:AR40)) -> 0 | AT40: =IF(AS40="","",AS40/15*100) -> 0 | AU40: AIICO Insurance Plc 2024 Annual Report (aiicoplc.com). Boilerplate CR&S text confirmed unchanged from prior years. No metrics, no IFRS S1/S2 mention.
A41: =C41&"_"&G41 -> 8_2025 | B41: 40 | C41: ='Panel Data (Long Format)'!B41 -> 8 | D41: ='Panel Data (Long Format)'!C41 -> AIICO | E41: ='Panel Data (Long Format)'!D41 -> AIICO Insurance Plc | F41: ='Panel Data (Long Format)'!E41 -> FINANCIAL SERVICES | G41: ='Panel Data (Long Format)'!F41 -> 2025 | H41: 1 | I41: 1 | J41: 0 | K41: 0 | L41: 0 | M41: 1 | N41: 1 | O41: 1 | P41: 0 | Q41: 0 | R41: 1 | S41: 0 | T41: 1 | U41: 1 | V41: 0 | W41: 1 | X41: 0 | Y41: 0 | Z41: 0 | AA41: 1 | AB41: =IF(COUNTBLANK(H41:AA41)>0,"",SUM(H41:AA41)) -> 10 | AC41: =IF(AB41="","",AB41/20*100) -> 50 | AD41: 0 | AE41: 0 | AF41: 0 | AG41: 0 | AH41: 1 | AI41: 0 | AJ41: 0 | AK41: 0 | AL41: 0 | AM41: 0 | AN41: 0 | AO41: 0 | AP41: 0 | AQ41: 0 | AR41: 0 | AS41: =IF(COUNTBLANK(AD41:AR41)>0,"",SUM(AD41:AR41)) -> 1 | AT41: =IF(AS41="","",AS41/15*100) -> 6.6666667 | AU41: AIICO Insurance Plc 2025 Annual Report and Accounts (aiicoplc.com). First year with upgraded content: climate-specific insurance products (Weather Index / Area Yield Index for farmers) -> S1/S2/S3=1; GHG emissions tracking methodology named (GHG Protocol referenced but no Scope 1/2/3 figures disclosed -> CDQ M1-3=0); one quantified metric (1,079kg recyclable waste retrieved) -> M1=1; 50 trees donated. Still no IFRS S1/S2 mention, no board sustainability committee detail, no targets-with-progress pairing.
A42: =C42&"_"&G42 -> 9_2021 | B42: 41 | C42: ='Panel Data (Long Format)'!B42 -> 9 | D42: ='Panel Data (Long Format)'!C42 -> AIRTELAFRI | E42: ='Panel Data (Long Format)'!D42 -> Airtel Africa Plc | F42: ='Panel Data (Long Format)'!E42 -> ICT | G42: ='Panel Data (Long Format)'!F42 -> 2021 | H42: 1 | I42: 0 | J42: 0 | K42: 0 | L42: 0 | M42: 0 | N42: 0 | O42: 0 | P42: 0 | Q42: 0 | R42: 0 | S42: 0 | T42: 0 | U42: 0 | V42: 0 | W42: 0 | X42: 0 | Y42: 0 | Z42: 0 | AA42: 0 | AB42: =IF(COUNTBLANK(H42:AA42)>0,"",SUM(H42:AA42)) -> 1 | AC42: =IF(AB42="","",AB42/20*100) -> 5 | AD42: 0 | AE42: 0 | AF42: 0 | AG42: 0 | AH42: 0 | AI42: 0 | AJ42: 0 | AK42: 0 | AL42: 0 | AM42: 0 | AN42: 0 | AO42: 0 | AP42: 0 | AQ42: 0 | AR42: 0 | AS42: =IF(COUNTBLANK(AD42:AR42)>0,"",SUM(AD42:AR42)) -> 0 | AT42: =IF(AS42="","",AS42/15*100) -> 0 | AU42: Airtel Africa Plc FY2021 (FYE 31-Mar-2021) Full Report / Governance Report / Strategic Report (cdn-webportal.airtelstream.net). Governance Report pp.82-99: Board attended a Nov-2020 sustainability workshop and endorsed management's sustainability-reporting approach (G1=1); no dedicated Sustainability Committee yet (only Audit&Risk/Remuneration/Nominations/Market Disclosure committees named); Remuneration Committee's 'embed sustainability into pay' was only a forward-looking 2020/21 recommendation, not yet implemented. Group's sustainability strategy/GHG baseline programme launched Oct-2021, i.e. AFTER this FYE, confirming genuinely near-zero disclosure for this year rather than an extraction gap. No IFRS S1/S2/ISSB language located in fetched 'new standards' sections.
A43: =C43&"_"&G43 -> 9_2022 | B43: 42 | C43: ='Panel Data (Long Format)'!B43 -> 9 | D43: ='Panel Data (Long Format)'!C43 -> AIRTELAFRI | E43: ='Panel Data (Long Format)'!D43 -> Airtel Africa Plc | F43: ='Panel Data (Long Format)'!E43 -> ICT | G43: ='Panel Data (Long Format)'!F43 -> 2022 | H43: 1 | I43: 1 | J43: 1 | K43: 1 | L43: 0 | M43: 1 | N43: 1 | O43: 1 | P43: 0 | Q43: 0 | R43: 1 | S43: 0 | T43: 0 | U43: 0 | V43: 0 | W43: 1 | X43: 1 | Y43: 0 | Z43: 1 | AA43: 1 | AB43: =IF(COUNTBLANK(H43:AA43)>0,"",SUM(H43:AA43)) -> 12 | AC43: =IF(AB43="","",AB43/20*100) -> 60 | AD43: 1 | AE43: 1 | AF43: 0 | AG43: 0 | AH43: 1 | AI43: 0 | AJ43: 1 | AK43: 1 | AL43: 1 | AM43: 1 | AN43: 1 | AO43: 1 | AP43: 0 | AQ43: 0 | AR43: 0 | AS43: =IF(COUNTBLANK(AD43:AR43)>0,"",SUM(AD43:AR43)) -> 9 | AT43: =IF(AS43="","",AS43/15*100) -> 60 | AU43: Airtel Africa Sustainability Report 2022 (cdn-webportal.airtelstream.net), supplemented by FY2021 Governance/Strategic Report continuity. Sustainability Committee (chaired by CEO, meets monthly) formalised as a Board committee alongside Audit&Risk Committee (co-oversees climate risks/opportunities); Board updated quarterly; remuneration policy explicitly integrates sustainability metrics (G4/M4=1). Baseline Scope1+2=115,719 tCO2e, Scope3=534,058 tCO2e reported as of 31-Mar-2022 with stated calculation methodology (M5=1). Net-zero-by-2050 pathway is a forming target, no progress figure yet reportable in baseline year. No scenario analysis or physical/transition risk categorisation found this year. CAVEAT: standalone AR2022 Governance/Strategic Report PDF not independently located this session -- some G/S items may be undercounted, flagged for re-check.
A44: =C44&"_"&G44 -> 9_2023 | B44: 43 | C44: ='Panel Data (Long Format)'!B44 -> 9 | D44: ='Panel Data (Long Format)'!C44 -> AIRTELAFRI | E44: ='Panel Data (Long Format)'!D44 -> Airtel Africa Plc | F44: ='Panel Data (Long Format)'!E44 -> ICT | G44: ='Panel Data (Long Format)'!F44 -> 2023 | H44: 1 | I44: 1 | J44: 1 | K44: 0 | L44: 0 | M44: 1 | N44: 1 | O44: 1 | P44: 0 | Q44: 1 | R44: 1 | S44: 1 | T44: 1 | U44: 1 | V44: 0 | W44: 0 | X44: 0 | Y44: 0 | Z44: 0 | AA44: 0 | AB44: =IF(COUNTBLANK(H44:AA44)>0,"",SUM(H44:AA44)) -> 11 | AC44: =IF(AB44="","",AB44/20*100) -> 55 | AD44: 1 | AE44: 1 | AF44: 0 | AG44: 0 | AH44: 1 | AI44: 1 | AJ44: 1 | AK44: 1 | AL44: 1 | AM44: 0 | AN44: 0 | AO44: 0 | AP44: 1 | AQ44: 0 | AR44: 0 | AS44: =IF(COUNTBLANK(AD44:AR44)>0,"",SUM(AD44:AR44)) -> 8 | AT44: =IF(AS44="","",AS44/15*100) -> 53.333333 | AU44: Airtel Africa Governance Report FY2022/23 + Financial Statements FY2022/23 climate risk note 7.3 (cdn-webportal.airtelstream.net). Sustainability Committee meets monthly, Board updated quarterly; agenda explicitly names 'Pathway to net zero and reduction of GHG emissions: complexity of modelling scope 1/2 initiatives and modelling for scope 3'. FS Note 7.3 'Our consideration of climate-related risks' confirms TCFD governance process and that auditors evaluated climate scenario considerations. CAVEAT: no standalone Sustainability Report 2023 located this session (URL attempts failed) so no direct FY2023 GHG figures/targets found -- M-series scored 0 pending that primary source, likely an undercount given FY2022/2024 both report figures, flagged for re-check.
A45: =C45&"_"&G45 -> 9_2024 | B45: 44 | C45: ='Panel Data (Long Format)'!B45 -> 9 | D45: ='Panel Data (Long Format)'!C45 -> AIRTELAFRI | E45: ='Panel Data (Long Format)'!D45 -> Airtel Africa Plc | F45: ='Panel Data (Long Format)'!E45 -> ICT | G45: ='Panel Data (Long Format)'!F45 -> 2024 | H45: 1 | I45: 1 | J45: 1 | K45: 1 | L45: 0 | M45: 1 | N45: 1 | O45: 1 | P45: 0 | Q45: 1 | R45: 1 | S45: 1 | T45: 1 | U45: 1 | V45: 0 | W45: 1 | X45: 1 | Y45: 1 | Z45: 1 | AA45: 1 | AB45: =IF(COUNTBLANK(H45:AA45)>0,"",SUM(H45:AA45)) -> 17 | AC45: =IF(AB45="","",AB45/20*100) -> 85 | AD45: 1 | AE45: 1 | AF45: 0 | AG45: 1 | AH45: 1 | AI45: 1 | AJ45: 1 | AK45: 1 | AL45: 1 | AM45: 1 | AN45: 1 | AO45: 1 | AP45: 1 | AQ45: 1 | AR45: 0 | AS45: =IF(COUNTBLANK(AD45:AR45)>0,"",SUM(AD45:AR45)) -> 13 | AT45: =IF(AS45="","",AS45/15*100) -> 86.666667 | AU45: Airtel Africa Sustainability Report 2024 + Financial Statements 2024 (cdn-webportal.airtelstream.net). Report explicitly sections 'Transition risks / Physical risks' (CDQ S1=1); scenario analysis conducted 'in 2023/24' per retrospective FY2025 report text (S3/S5=1). Scope1=82,871; Scope2=45,632; Scope3=891,182 tCO2e (2023/24) reported with named methodology section. Remuneration Committee link to sustainability explicit. Board sustainability-champion director role not yet clearly confirmed for this year (G5=0).
A46: =C46&"_"&G46 -> 9_2025 | B46: 45 | C46: ='Panel Data (Long Format)'!B46 -> 9 | D46: ='Panel Data (Long Format)'!C46 -> AIRTELAFRI | E46: ='Panel Data (Long Format)'!D46 -> Airtel Africa Plc | F46: ='Panel Data (Long Format)'!E46 -> ICT | G46: ='Panel Data (Long Format)'!F46 -> 2025 | H46: 1 | I46: 1 | J46: 1 | K46: 1 | L46: 1 | M46: 1 | N46: 1 | O46: 1 | P46: 0 | Q46: 1 | R46: 1 | S46: 1 | T46: 1 | U46: 1 | V46: 0 | W46: 1 | X46: 1 | Y46: 1 | Z46: 1 | AA46: 1 | AB46: =IF(COUNTBLANK(H46:AA46)>0,"",SUM(H46:AA46)) -> 18 | AC46: =IF(AB46="","",AB46/20*100) -> 90 | AD46: 1 | AE46: 1 | AF46: 1 | AG46: 1 | AH46: 1 | AI46: 1 | AJ46: 1 | AK46: 1 | AL46: 1 | AM46: 1 | AN46: 1 | AO46: 1 | AP46: 1 | AQ46: 1 | AR46: 0 | AS46: =IF(COUNTBLANK(AD46:AR46)>0,"",SUM(AD46:AR46)) -> 14 | AT46: =IF(AS46="","",AS46/15*100) -> 93.333333 | AU46: Airtel Africa AR2025 digital-first HTML report -- Managing our risk (p021), Sustainability strategy (p023), Governance structures (p036), Audit&Risk Committee report (p041), TCFD disclosures (p025), New accounting pronouncements note (p066). Governance structures page names 5 Board committees incl. Sustainability Committee (chair: CEO Sunil Taldar; mgmt member 'Oladimeji Olaniyan, Head of strategy and sustainability') and 'Annika Poutiainen, Board member and sustainability champion' (G5=1). Full TCFD-structured disclosure: 3-scenario climate analysis (current-policy/high-temp/net-zero), both physical & transition risks tabulated, Scope1=89,869/Scope2=44,151/Scope3='n/a with reasoned 1-yr verification lag' tCO2e (M3=1 per reasoned-omission rule), target -62% carbon intensity by 2032 from 2022 baseline with -14% progress reported, ExCo LTIP/KRA explicitly linked to carbon reduction. Note 4 'New accounting pronouncements to be adopted' lists only an IAS 21 amendment -- no IFRS S1/S2/ISSB mention anywhere located across all AR2025 pages fetched, hence Adopter_Dummy blank despite substantive voluntary TCFD-aligned disclosure.
A47: =C47&"_"&G47 -> 10_2021 | B47: 46 | C47: ='Panel Data (Long Format)'!B47 -> 10 | D47: ='Panel Data (Long Format)'!C47 -> ALEX | E47: ='Panel Data (Long Format)'!D47 -> Aluminium Extrusion Industries Plc | F47: ='Panel Data (Long Format)'!E47 -> NATURAL RESOURCES | G47: ='Panel Data (Long Format)'!F47 -> 2021 | H47: 0 | I47: 0 | J47: 0 | K47: 0 | L47: 0 | M47: 0 | N47: 0 | O47: 0 | P47: 0 | Q47: 0 | R47: 0 | S47: 0 | T47: 0 | U47: 0 | V47: 0 | W47: 0 | X47: 0 | Y47: 0 | Z47: 0 | AA47: 0 | AB47: =IF(COUNTBLANK(H47:AA47)>0,"",SUM(H47:AA47)) -> 0 | AC47: =IF(AB47="","",AB47/20*100) -> 0 | AD47: 0 | AE47: 0 | AF47: 0 | AG47: 0 | AH47: 0 | AI47: 0 | AJ47: 0 | AK47: 0 | AL47: 0 | AM47: 0 | AN47: 0 | AO47: 0 | AP47: 0 | AQ47: 0 | AR47: 0 | AS47: =IF(COUNTBLANK(AD47:AR47)>0,"",SUM(AD47:AR47)) -> 0 | AT47: =IF(AS47="","",AS47/15*100) -> 0 | AU47: GAP-FILL: ALEX FY2021: primary source NOT accessible this session - the FY2022 NGX doclib filing (which would carry an FY2021 comparative) returned as an image-only/non-machine-readable PDF ('[This PDF is empty or contains no machine-readable text]'), and no readable FY2023/2024/2025 filing or company-website AFS could be located within this session's search budget (parent company is Tower Aluminium (Nigeria) Plc). Scored 0/20 SDQ, 0/15 CDQ, FLAGGED as unconfirmed/inaccessible-source, consistent with this dataset's THOMASWY/image-only-PDF precedent - a strong candidate for re-verification with OCR or an alternate source.
A48: =C48&"_"&G48 -> 10_2022 | B48: 47 | C48: ='Panel Data (Long Format)'!B48 -> 10 | D48: ='Panel Data (Long Format)'!C48 -> ALEX | E48: ='Panel Data (Long Format)'!D48 -> Aluminium Extrusion Industries Plc | F48: ='Panel Data (Long Format)'!E48 -> NATURAL RESOURCES | G48: ='Panel Data (Long Format)'!F48 -> 2022 | H48: 0 | I48: 0 | J48: 0 | K48: 0 | L48: 0 | M48: 0 | N48: 0 | O48: 0 | P48: 0 | Q48: 0 | R48: 0 | S48: 0 | T48: 0 | U48: 0 | V48: 0 | W48: 0 | X48: 0 | Y48: 0 | Z48: 0 | AA48: 0 | AB48: =IF(COUNTBLANK(H48:AA48)>0,"",SUM(H48:AA48)) -> 0 | AC48: =IF(AB48="","",AB48/20*100) -> 0 | AD48: 0 | AE48: 0 | AF48: 0 | AG48: 0 | AH48: 0 | AI48: 0 | AJ48: 0 | AK48: 0 | AL48: 0 | AM48: 0 | AN48: 0 | AO48: 0 | AP48: 0 | AQ48: 0 | AR48: 0 | AS48: =IF(COUNTBLANK(AD48:AR48)>0,"",SUM(AD48:AR48)) -> 0 | AT48: =IF(AS48="","",AS48/15*100) -> 0 | AU48: GAP-FILL: ALEX FY2022: primary source NOT accessible this session - the FY2022 NGX doclib filing (which would carry an FY2021 comparative) returned as an image-only/non-machine-readable PDF ('[This PDF is empty or contains no machine-readable text]'), and no readable FY2023/2024/2025 filing or company-website AFS could be located within this session's search budget (parent company is Tower Aluminium (Nigeria) Plc). Scored 0/20 SDQ, 0/15 CDQ, FLAGGED as unconfirmed/inaccessible-source, consistent with this dataset's THOMASWY/image-only-PDF precedent - a strong candidate for re-verification with OCR or an alternate source.
... A51: =C51&"_"&G51 -> 10_2025 | B51: 50 | C51: ='Panel Data (Long Format)'!B51 -> 10 | D51: ='Panel Data (Long Format)'!C51 -> ALEX | E51: ='Panel Data (Long Format)'!D51 -> Aluminium Extrusion Industries Plc | F51: ='Panel Data (Long Format)'!E51 -> NATURAL RESOURCES | G51: ='Panel Data (Long Format)'!F51 -> 2025 | H51: 0 | I51: 0 | J51: 0 | K51: 0 | L51: 0 | M51: 0 | N51: 0 | O51: 0 | P51: 0 | Q51: 0 | R51: 0 | S51: 0 | T51: 0 | U51: 0 | V51: 0 | W51: 0 | X51: 0 | Y51: 0 | Z51: 0 | AA51: 0 | AB51: =IF(COUNTBLANK(H51:AA51)>0,"",SUM(H51:AA51)) -> 0 | AC51: =IF(AB51="","",AB51/20*100) -> 0 | AD51: 0 | AE51: 0 | AF51: 0 | AG51: 0 | AH51: 0 | AI51: 0 | AJ51: 0 | AK51: 0 | AL51: 0 | AM51: 0 | AN51: 0 | AO51: 0 | AP51: 0 | AQ51: 0 | AR51: 0 | AS51: =IF(COUNTBLANK(AD51:AR51)>0,"",SUM(AD51:AR51)) -> 0 | AT51: =IF(AS51="","",AS51/15*100) -> 0 | AU51: GAP-FILL: ALEX FY2025: primary source NOT accessible this session - the FY2022 NGX doclib filing (which would carry an FY2021 comparative) returned as an image-only/non-machine-readable PDF ('[This PDF is empty or contains no machine-readable text]'), and no readable FY2023/2024/2025 filing or company-website AFS could be located within this session's search budget (parent company is Tower Aluminium (Nigeria) Plc). Scored 0/20 SDQ, 0/15 CDQ, FLAGGED as unconfirmed/inaccessible-source, consistent with this dataset's THOMASWY/image-only-PDF precedent - a strong candidate for re-verification with OCR or an alternate source.
A52: =C52&"_"&G52 -> 11_2021 | B52: 51 | C52: ='Panel Data (Long Format)'!B52 -> 11 | D52: ='Panel Data (Long Format)'!C52 -> ARADEL | E52: ='Panel Data (Long Format)'!D52 -> Aradel Holdings Plc | F52: ='Panel Data (Long Format)'!E52 -> OIL AND GAS | G52: ='Panel Data (Long Format)'!F52 -> 2021 | AB52: =IF(COUNTBLANK(H52:AA52)>0,"",SUM(H52:AA52)) | AC52: =IF(AB52="","",AB52/20*100) | AS52: =IF(COUNTBLANK(AD52:AR52)>0,"",SUM(AD52:AR52)) | AT52: =IF(AS52="","",AS52/15*100) | AU52: GENUINE GAP: aradel.com was unreachable this session (multiple fetch attempts on the task-supplied URL and alternates found via web search returned empty content, including a URL that had fetched successfully earlier in this same session for FY2022 -- confirming the domain, not the specific link, is the blocker at time of access). NDEP filed voluntary IR-site annual reports pre-NGX-listing but this one could not be retrieved this session -- worth a retry.
A53: =C53&"_"&G53 -> 11_2022 | B53: 52 | C53: ='Panel Data (Long Format)'!B53 -> 11 | D53: ='Panel Data (Long Format)'!C53 -> ARADEL | E53: ='Panel Data (Long Format)'!D53 -> Aradel Holdings Plc | F53: ='Panel Data (Long Format)'!E53 -> OIL AND GAS | G53: ='Panel Data (Long Format)'!F53 -> 2022 | H53: 1 | I53: 0 | J53: 1 | K53: 0 | L53: 0 | M53: 0 | N53: 0 | O53: 0 | P53: 0 | Q53: 0 | R53: 1 | S53: 1 | T53: 1 | U53: 1 | V53: 0 | W53: 0 | X53: 0 | Y53: 0 | Z53: 0 | AA53: 0 | AB53: =IF(COUNTBLANK(H53:AA53)>0,"",SUM(H53:AA53)) -> 6 | AC53: =IF(AB53="","",AB53/20*100) -> 30 | AD53: 0 | AE53: 0 | AF53: 0 | AG53: 0 | AH53: 0 | AI53: 0 | AJ53: 0 | AK53: 0 | AL53: 0 | AM53: 0 | AN53: 0 | AO53: 0 | AP53: 0 | AQ53: 0 | AR53: 0 | AS53: =IF(COUNTBLANK(AD53:AR53)>0,"",SUM(AD53:AR53)) -> 0 | AT53: =IF(AS53="","",AS53/15*100) -> 0 | AU53: Filed as NDEP Plc, FY-2022-Audited-Financial-Statements.pdf (aradel.com). Corporate Governance Report: Board has 4 committees incl. 'Corporate Responsibility & Risk Management Committee' (CRRMC, 4 meetings/yr); risk-only mandate (identification/assessment/quantification/rating/monitoring per documented ERM framework diagram) with no sustainability/ESG/climate-specific risks, targets or metrics named anywhere in Directors'/CG Report or notes. No GHG/flaring figures, no TCFD/ISSB/IFRS S1/S2 language found.
A54: =C54&"_"&G54 -> 11_2023 | B54: 53 | C54: ='Panel Data (Long Format)'!B54 -> 11 | D54: ='Panel Data (Long Format)'!C54 -> ARADEL | E54: ='Panel Data (Long Format)'!D54 -> Aradel Holdings Plc | F54: ='Panel Data (Long Format)'!E54 -> OIL AND GAS | G54: ='Panel Data (Long Format)'!F54 -> 2023 | AB54: =IF(COUNTBLANK(H54:AA54)>0,"",SUM(H54:AA54)) | AC54: =IF(AB54="","",AB54/20*100) | AS54: =IF(COUNTBLANK(AD54:AR54)>0,"",SUM(AD54:AR54)) | AT54: =IF(AS54="","",AS54/15*100) | AU54: GENUINE GAP: Same domain-unreachable issue as FY2021 -- ARADEL_ANNUAL_REPORT_2023.pdf and a Sustainability-Report-2023.pdf URL (both task-supplied and web-search-located) returned empty content on every attempt this session, including with cache-busting query strings. Worth a retry.
A55: =C55&"_"&G55 -> 11_2024 | B55: 54 | C55: ='Panel Data (Long Format)'!B55 -> 11 | D55: ='Panel Data (Long Format)'!C55 -> ARADEL | E55: ='Panel Data (Long Format)'!D55 -> Aradel Holdings Plc | F55: ='Panel Data (Long Format)'!E55 -> OIL AND GAS | G55: ='Panel Data (Long Format)'!F55 -> 2024 | H55: 1 | I55: 0 | J55: 1 | K55: 0 | L55: 0 | M55: 0 | N55: 0 | O55: 0 | P55: 1 | Q55: 0 | R55: 1 | S55: 1 | T55: 1 | U55: 1 | V55: 0 | W55: 0 | X55: 0 | Y55: 0 | Z55: 0 | AA55: 0 | AB55: =IF(COUNTBLANK(H55:AA55)>0,"",SUM(H55:AA55)) -> 7 | AC55: =IF(AB55="","",AB55/20*100) -> 35 | AD55: 0 | AE55: 0 | AF55: 0 | AG55: 0 | AH55: 0 | AI55: 0 | AJ55: 0 | AK55: 0 | AL55: 0 | AM55: 0 | AN55: 0 | AO55: 0 | AP55: 0 | AQ55: 0 | AR55: 0 | AS55: =IF(COUNTBLANK(AD55:AR55)>0,"",SUM(AD55:AR55)) -> 0 | AT55: =IF(AS55="","",AS55/15*100) -> 0 | AU55: Aradel Holdings Plc 2024 Annual Report & Accounts (NGX doclib #43494) -- first AR as NGX-listed entity (listed by introduction 14-Oct-2024). Same CRRMC/4-committee structure as FY2022, same generic ERM framework (no sustainability-specific risk categories). One entity-specific financial-effect item: a disclosed US$2,185,865 fine 'in respect of a technical gas flare in the year 2024' (S4=1) -- a negative environmental-compliance disclosure, not a positive metric. 'Protection of the Environment' section is a one-paragraph generic compliance statement with no quantified emissions/flaring data. No IFRS S1/S2/ISSB language found.
A56: =C56&"_"&G56 -> 11_2025 | B56: 55 | C56: ='Panel Data (Long Format)'!B56 -> 11 | D56: ='Panel Data (Long Format)'!C56 -> ARADEL | E56: ='Panel Data (Long Format)'!D56 -> Aradel Holdings Plc | F56: ='Panel Data (Long Format)'!E56 -> OIL AND GAS | G56: ='Panel Data (Long Format)'!F56 -> 2025 | H56: 1 | I56: 0 | J56: 1 | K56: 0 | L56: 0 | M56: 0 | N56: 0 | O56: 0 | P56: 0 | Q56: 0 | R56: 1 | S56: 1 | T56: 1 | U56: 1 | V56: 0 | W56: 0 | X56: 0 | Y56: 0 | Z56: 0 | AA56: 0 | AB56: =IF(COUNTBLANK(H56:AA56)>0,"",SUM(H56:AA56)) -> 6 | AC56: =IF(AB56="","",AB56/20*100) -> 30 | AD56: 0 | AE56: 0 | AF56: 0 | AG56: 0 | AH56: 0 | AI56: 0 | AJ56: 0 | AK56: 0 | AL56: 0 | AM56: 0 | AN56: 0 | AO56: 0 | AP56: 0 | AQ56: 0 | AR56: 0 | AS56: =IF(COUNTBLANK(AD56:AR56)>0,"",SUM(AD56:AR56)) -> 0 | AT56: =IF(AS56="","",AS56/15*100) -> 0 | AU56: Aradel Holdings Plc FY2025 filing (NGX doclib #45966) -- LOWER CONFIDENCE: this fetch only returned the audit-committee cover page, financial statements and notes, not the narrative Corporate Governance Report obtained for FY2022/FY2024. Score applies the FY2022/FY2024 CRRMC governance pattern by inference (same recurring structure across all 3 available years) rather than direct FY2025-specific text -- flagged for re-verification against the full FY2025 Annual Report if it becomes accessible. No IFRS S1/S2/ISSB language found in the FS notes captured.
A57: =C57&"_"&G57 -> 12_2021 | B57: 56 | C57: ='Panel Data (Long Format)'!B57 -> 12 | D57: ='Panel Data (Long Format)'!C57 -> AUSTINLAZ | E57: ='Panel Data (Long Format)'!D57 -> Austin Laz & Company Plc | F57: ='Panel Data (Long Format)'!E57 -> INDUSTRIAL GOODS | G57: ='Panel Data (Long Format)'!F57 -> 2021 | H57: 0 | I57: 0 | J57: 0 | K57: 0 | L57: 0 | M57: 0 | N57: 0 | O57: 0 | P57: 0 | Q57: 0 | R57: 0 | S57: 0 | T57: 0 | U57: 0 | V57: 0 | W57: 0 | X57: 0 | Y57: 0 | Z57: 0 | AA57: 0 | AB57: =IF(COUNTBLANK(H57:AA57)>0,"",SUM(H57:AA57)) -> 0 | AC57: =IF(AB57="","",AB57/20*100) -> 0 | AD57: 0 | AE57: 0 | AF57: 0 | AG57: 0 | AH57: 0 | AI57: 0 | AJ57: 0 | AK57: 0 | AL57: 0 | AM57: 0 | AN57: 0 | AO57: 0 | AP57: 0 | AQ57: 0 | AR57: 0 | AS57: =IF(COUNTBLANK(AD57:AR57)>0,"",SUM(AD57:AR57)) -> 0 | AT57: =IF(AS57="","",AS57/15*100) -> 0 | AU57: Austin Laz and Company Plc FY2021 (NGX doclib #34832), full text reviewed. Only two board committees exist -- 'Financial and General Purpose Committee' and statutory 'Audit Committee' -- neither with any sustainability/ESG/climate mandate. Zero mentions of sustainability/ESG/climate/GHG/emissions anywhere. 'Basis of preparation' note references only general IFRS compliance, no new-standards/adoption section discussing IFRS S1/S2/ISSB. Company operations were suspended (zero revenue) this year.
A58: =C58&"_"&G58 -> 12_2022 | B58: 57 | C58: ='Panel Data (Long Format)'!B58 -> 12 | D58: ='Panel Data (Long Format)'!C58 -> AUSTINLAZ | E58: ='Panel Data (Long Format)'!D58 -> Austin Laz & Company Plc | F58: ='Panel Data (Long Format)'!E58 -> INDUSTRIAL GOODS | G58: ='Panel Data (Long Format)'!F58 -> 2022 | H58: 0 | I58: 0 | J58: 0 | K58: 0 | L58: 0 | M58: 0 | N58: 0 | O58: 0 | P58: 0 | Q58: 0 | R58: 0 | S58: 0 | T58: 0 | U58: 0 | V58: 0 | W58: 0 | X58: 0 | Y58: 0 | Z58: 0 | AA58: 0 | AB58: =IF(COUNTBLANK(H58:AA58)>0,"",SUM(H58:AA58)) -> 0 | AC58: =IF(AB58="","",AB58/20*100) -> 0 | AD58: 0 | AE58: 0 | AF58: 0 | AG58: 0 | AH58: 0 | AI58: 0 | AJ58: 0 | AK58: 0 | AL58: 0 | AM58: 0 | AN58: 0 | AO58: 0 | AP58: 0 | AQ58: 0 | AR58: 0 | AS58: =IF(COUNTBLANK(AD58:AR58)>0,"",SUM(AD58:AR58)) -> 0 | AT58: =IF(AS58="","",AS58/15*100) -> 0 | AU58: INFERRED (no standalone FY2022 full annual report located; NGX doclib search did not surface one distinct from FY2021/FY2023 filings, and AfricanFinancials only holds an Abridged Report, not used per project convention). Scored by direct textual comparison: FY2021 and FY2023 filings' 'BOARD COMMITTEES' and accounting-policy sections are verbatim-identical, and FY2023's 2022 comparative figures confirm continuity of the same dormant, zero-revenue state -- high confidence genuine 0/0 year, but flagged as inferred rather than directly sourced.
A59: =C59&"_"&G59 -> 12_2023 | B59: 58 | C59: ='Panel Data (Long Format)'!B59 -> 12 | D59: ='Panel Data (Long Format)'!C59 -> AUSTINLAZ | E59: ='Panel Data (Long Format)'!D59 -> Austin Laz & Company Plc | F59: ='Panel Data (Long Format)'!E59 -> INDUSTRIAL GOODS | G59: ='Panel Data (Long Format)'!F59 -> 2023 | H59: 0 | I59: 0 | J59: 0 | K59: 0 | L59: 0 | M59: 0 | N59: 0 | O59: 0 | P59: 0 | Q59: 0 | R59: 0 | S59: 0 | T59: 0 | U59: 0 | V59: 0 | W59: 0 | X59: 0 | Y59: 0 | Z59: 0 | AA59: 0 | AB59: =IF(COUNTBLANK(H59:AA59)>0,"",SUM(H59:AA59)) -> 0 | AC59: =IF(AB59="","",AB59/20*100) -> 0 | AD59: 0 | AE59: 0 | AF59: 0 | AG59: 0 | AH59: 0 | AI59: 0 | AJ59: 0 | AK59: 0 | AL59: 0 | AM59: 0 | AN59: 0 | AO59: 0 | AP59: 0 | AQ59: 0 | AR59: 0 | AS59: =IF(COUNTBLANK(AD59:AR59)>0,"",SUM(AD59:AR59)) -> 0 | AT59: =IF(AS59="","",AS59/15*100) -> 0 | AU59: Austin Laz and Company Plc FY2023 (NGX doclib #40358), full text reviewed. Identical governance/committee boilerplate to FY2021; zero revenue again this year; no sustainability/ESG/climate content anywhere.
A60: =C60&"_"&G60 -> 12_2024 | B60: 59 | C60: ='Panel Data (Long Format)'!B60 -> 12 | D60: ='Panel Data (Long Format)'!C60 -> AUSTINLAZ | E60: ='Panel Data (Long Format)'!D60 -> Austin Laz & Company Plc | F60: ='Panel Data (Long Format)'!E60 -> INDUSTRIAL GOODS | G60: ='Panel Data (Long Format)'!F60 -> 2024 | H60: 0 | I60: 0 | J60: 0 | K60: 0 | L60: 0 | M60: 0 | N60: 0 | O60: 0 | P60: 0 | Q60: 0 | R60: 0 | S60: 0 | T60: 0 | U60: 0 | V60: 0 | W60: 0 | X60: 0 | Y60: 0 | Z60: 0 | AA60: 0 | AB60: =IF(COUNTBLANK(H60:AA60)>0,"",SUM(H60:AA60)) -> 0 | AC60: =IF(AB60="","",AB60/20*100) -> 0 | AD60: 0 | AE60: 0 | AF60: 0 | AG60: 0 | AH60: 0 | AI60: 0 | AJ60: 0 | AK60: 0 | AL60: 0 | AM60: 0 | AN60: 0 | AO60: 0 | AP60: 0 | AQ60: 0 | AR60: 0 | AS60: =IF(COUNTBLANK(AD60:AR60)>0,"",SUM(AD60:AR60)) -> 0 | AT60: =IF(AS60="","",AS60/15*100) -> 0 | AU60: Austin Laz and Company Plc FY2024 (NGX doclib #43103), full text reviewed. Operations resumed this year (revenue N1.316bn) but governance/CSR content unchanged from prior years -- same two committees, zero sustainability/ESG/climate language. Includes an ICFR management assessment (COSO framework) -- a financial-control item, not a sustainability disclosure.
A61: =C61&"_"&G61 -> 12_2025 | B61: 60 | C61: ='Panel Data (Long Format)'!B61 -> 12 | D61: ='Panel Data (Long Format)'!C61 -> AUSTINLAZ | E61: ='Panel Data (Long Format)'!D61 -> Austin Laz & Company Plc | F61: ='Panel Data (Long Format)'!E61 -> INDUSTRIAL GOODS | G61: ='Panel Data (Long Format)'!F61 -> 2025 | H61: 0 | I61: 0 | J61: 0 | K61: 0 | L61: 0 | M61: 0 | N61: 0 | O61: 0 | P61: 0 | Q61: 0 | R61: 0 | S61: 0 | T61: 0 | U61: 0 | V61: 0 | W61: 0 | X61: 0 | Y61: 0 | Z61: 0 | AA61: 0 | AB61: =IF(COUNTBLANK(H61:AA61)>0,"",SUM(H61:AA61)) -> 0 | AC61: =IF(AB61="","",AB61/20*100) -> 0 | AD61: 0 | AE61: 0 | AF61: 0 | AG61: 0 | AH61: 0 | AI61: 0 | AJ61: 0 | AK61: 0 | AL61: 0 | AM61: 0 | AN61: 0 | AO61: 0 | AP61: 0 | AQ61: 0 | AR61: 0 | AS61: =IF(COUNTBLANK(AD61:AR61)>0,"",SUM(AD61:AR61)) -> 0 | AT61: =IF(AS61="","",AS61/15*100) -> 0 | AU61: Austin Laz and Company Plc FY2025 (NGX doclib #45913), full text reviewed. Company reports it was 'inactive... throughout the year 2025 due to the moribund condition of the productive capacity' -- zero revenue confirmed. Same governance boilerplate, zero sustainability/ESG/climate content.
A62: =C62&"_"&G62 -> 13_2021 | B62: 61 | C62: ='Panel Data (Long Format)'!B62 -> 13 | D62: ='Panel Data (Long Format)'!C62 -> AVAIF | E62: ='Panel Data (Long Format)'!D62 -> AVA Infrastructure Fund | F62: ='Panel Data (Long Format)'!E62 -> CONSTRUCTION/REAL ESTATE | G62: ='Panel Data (Long Format)'!F62 -> 2021 | AB62: =IF(COUNTBLANK(H62:AA62)>0,"",SUM(H62:AA62)) | AC62: =IF(AB62="","",AB62/20*100) | AS62: =IF(COUNTBLANK(AD62:AR62)>0,"",SUM(AD62:AR62)) | AT62: =IF(AS62="","",AS62/15*100) | AU62: GENUINE GAP: AVA Infrastructure Fund's own FY2024 Trustees'/Fund Manager's Report states the Fund 'was listed on the main board of the Nigerian Exchange Limited (NGX) on May 10, 2024' following an offer that closed 27-Mar-2024. No public annual report exists for FY2021 -- the fund did not exist as a public entity (excluded by design, consistent with other pre-listing firm-years elsewhere in this dataset).
A63: =C63&"_"&G63 -> 13_2022 | B63: 62 | C63: ='Panel Data (Long Format)'!B63 -> 13 | D63: ='Panel Data (Long Format)'!C63 -> AVAIF | E63: ='Panel Data (Long Format)'!D63 -> AVA Infrastructure Fund | F63: ='Panel Data (Long Format)'!E63 -> CONSTRUCTION/REAL ESTATE | G63: ='Panel Data (Long Format)'!F63 -> 2022 | AB63: =IF(COUNTBLANK(H63:AA63)>0,"",SUM(H63:AA63)) | AC63: =IF(AB63="","",AB63/20*100) | AS63: =IF(COUNTBLANK(AD63:AR63)>0,"",SUM(AD63:AR63)) | AT63: =IF(AS63="","",AS63/15*100) | AU63: GENUINE GAP: Same pre-listing reasoning as FY2021 -- fund did not exist as a public entity.
A64: =C64&"_"&G64 -> 13_2023 | B64: 63 | C64: ='Panel Data (Long Format)'!B64 -> 13 | D64: ='Panel Data (Long Format)'!C64 -> AVAIF | E64: ='Panel Data (Long Format)'!D64 -> AVA Infrastructure Fund | F64: ='Panel Data (Long Format)'!E64 -> CONSTRUCTION/REAL ESTATE | G64: ='Panel Data (Long Format)'!F64 -> 2023 | AB64: =IF(COUNTBLANK(H64:AA64)>0,"",SUM(H64:AA64)) | AC64: =IF(AB64="","",AB64/20*100) | AS64: =IF(COUNTBLANK(AD64:AR64)>0,"",SUM(AD64:AR64)) | AT64: =IF(AS64="","",AS64/15*100) | AU64: GENUINE GAP: Same pre-listing reasoning as FY2021 -- fund did not exist as a public entity.
A65: =C65&"_"&G65 -> 13_2024 | B65: 64 | C65: ='Panel Data (Long Format)'!B65 -> 13 | D65: ='Panel Data (Long Format)'!C65 -> AVAIF | E65: ='Panel Data (Long Format)'!D65 -> AVA Infrastructure Fund | F65: ='Panel Data (Long Format)'!E65 -> CONSTRUCTION/REAL ESTATE | G65: ='Panel Data (Long Format)'!F65 -> 2024 | H65: 0 | I65: 0 | J65: 0 | K65: 0 | L65: 0 | M65: 0 | N65: 0 | O65: 0 | P65: 0 | Q65: 0 | R65: 0 | S65: 0 | T65: 0 | U65: 0 | V65: 0 | W65: 0 | X65: 0 | Y65: 0 | Z65: 0 | AA65: 0 | AB65: =IF(COUNTBLANK(H65:AA65)>0,"",SUM(H65:AA65)) -> 0 | AC65: =IF(AB65="","",AB65/20*100) -> 0 | AD65: 0 | AE65: 0 | AF65: 0 | AG65: 0 | AH65: 0 | AI65: 0 | AJ65: 0 | AK65: 0 | AL65: 0 | AM65: 0 | AN65: 0 | AO65: 0 | AP65: 0 | AQ65: 0 | AR65: 0 | AS65: =IF(COUNTBLANK(AD65:AR65)>0,"",SUM(AD65:AR65)) -> 0 | AT65: =IF(AS65="","",AS65/15*100) -> 0 | AU65: AVA Infrastructure Fund FY2024 (NGX doclib #43641), full text reviewed -- first/inaugural Annual Report, part-year (fund NGX-listed 10-May-2024 after offer closed 27-Mar-2024). Fund governed by Trustees (STL Trustees Ltd) + Fund Manager structure, not a conventional corporate board; 'investment committee' referenced only for project-pipeline evaluation, not sustainability. Zero mentions of sustainability/ESG/climate/GHG anywhere in Trustees'/Fund Manager's Report or notes; fund held only money-market investments this year, no infrastructure projects yet deployed. No IFRS S1/S2/ISSB language in FS notes.
A66: =C66&"_"&G66 -> 13_2025 | B66: 65 | C66: ='Panel Data (Long Format)'!B66 -> 13 | D66: ='Panel Data (Long Format)'!C66 -> AVAIF | E66: ='Panel Data (Long Format)'!D66 -> AVA Infrastructure Fund | F66: ='Panel Data (Long Format)'!E66 -> CONSTRUCTION/REAL ESTATE | G66: ='Panel Data (Long Format)'!F66 -> 2025 | H66: 0 | I66: 0 | J66: 0 | K66: 0 | L66: 0 | M66: 0 | N66: 0 | O66: 0 | P66: 0 | Q66: 0 | R66: 0 | S66: 0 | T66: 0 | U66: 0 | V66: 0 | W66: 0 | X66: 0 | Y66: 0 | Z66: 0 | AA66: 0 | AB66: =IF(COUNTBLANK(H66:AA66)>0,"",SUM(H66:AA66)) -> 0 | AC66: =IF(AB66="","",AB66/20*100) -> 0 | AD66: 0 | AE66: 0 | AF66: 0 | AG66: 0 | AH66: 0 | AI66: 0 | AJ66: 0 | AK66: 0 | AL66: 0 | AM66: 0 | AN66: 0 | AO66: 0 | AP66: 0 | AQ66: 0 | AR66: 0 | AS66: =IF(COUNTBLANK(AD66:AR66)>0,"",SUM(AD66:AR66)) -> 0 | AT66: =IF(AS66="","",AS66/15*100) -> 0 | AU66: AVA Infrastructure Fund FY2025 (NGX doclib #46434), full text reviewed. Same fund structure/reporting pattern as FY2024. One generic 'ESG-linked' mention appears only inside standard IFRS 9 SPPI-test accounting-policy boilerplate (financial-asset classification), not a substantive sustainability disclosure -- scored 0 per boilerplate-exclusion rule. No committee, target or metric content related to sustainability/climate anywhere in the report.
A67: =C67&"_"&G67 -> 14_2021 | B67: 66 | C67: ='Panel Data (Long Format)'!B67 -> 14 | D67: ='Panel Data (Long Format)'!C67 -> BAPLC | E67: ='Panel Data (Long Format)'!D67 -> Briclinks Africa Plc (trading as Btel) | F67: ='Panel Data (Long Format)'!E67 -> ICT | G67: ='Panel Data (Long Format)'!F67 -> 2021 | H67: 0 | I67: 0 | J67: 0 | K67: 0 | L67: 0 | M67: 0 | N67: 0 | O67: 0 | P67: 0 | Q67: 0 | R67: 0 | S67: 0 | T67: 0 | U67: 0 | V67: 0 | W67: 0 | X67: 0 | Y67: 0 | Z67: 0 | AA67: 0 | AB67: =IF(COUNTBLANK(H67:AA67)>0,"",SUM(H67:AA67)) -> 0 | AC67: =IF(AB67="","",AB67/20*100) -> 0 | AD67: 0 | AE67: 0 | AF67: 0 | AG67: 0 | AH67: 0 | AI67: 0 | AJ67: 0 | AK67: 0 | AL67: 0 | AM67: 0 | AN67: 0 | AO67: 0 | AP67: 0 | AQ67: 0 | AR67: 0 | AS67: =IF(COUNTBLANK(AD67:AR67)>0,"",SUM(AD67:AR67)) -> 0 | AT67: =IF(AS67="","",AS67/15*100) -> 0 | AU67: GAP-FILL: BAPLC FY2021: not verified this session (only the FY2022 Financial Statements were fetched, already coded in an earlier batch). That FY2022 filing explicitly confirms 'There was no donation & charitable gift made during the year' and contains NO board committee structure at all (a 4-director micro-cap telecom company with no distinct Board Committees section), which provides reasonable context that this firm's ESG disclosure is minimal/near-zero across periods, though not directly confirmed for FY2021. Scored 0/20 SDQ, 0/15 CDQ, FLAGGED as unconfirmed pending re-verification against a dedicated FY2021 filing.
A68: =C68&"_"&G68 -> 14_2022 | B68: 67 | C68: ='Panel Data (Long Format)'!B68 -> 14 | D68: ='Panel Data (Long Format)'!C68 -> BAPLC | E68: ='Panel Data (Long Format)'!D68 -> Briclinks Africa Plc (trading as Btel) | F68: ='Panel Data (Long Format)'!E68 -> ICT | G68: ='Panel Data (Long Format)'!F68 -> 2022 | H68: 0 | I68: 0 | J68: 0 | K68: 0 | L68: 0 | M68: 0 | N68: 0 | O68: 0 | P68: 0 | Q68: 0 | R68: 0 | S68: 0 | T68: 0 | U68: 0 | V68: 0 | W68: 0 | X68: 0 | Y68: 0 | Z68: 0 | AA68: 0 | AB68: =IF(COUNTBLANK(H68:AA68)>0,"",SUM(H68:AA68)) -> 0 | AC68: =IF(AB68="","",AB68/20*100) -> 0 | AD68: 0 | AE68: 0 | AF68: 0 | AG68: 0 | AH68: 0 | AI68: 0 | AJ68: 0 | AK68: 0 | AL68: 0 | AM68: 0 | AN68: 0 | AO68: 0 | AP68: 0 | AQ68: 0 | AR68: 0 | AS68: =IF(COUNTBLANK(AD68:AR68)>0,"",SUM(AD68:AR68)) -> 0 | AT68: =IF(AS68="","",AS68/15*100) -> 0 | AU68: Bricklinks Africa Plc FY2022 (NGX doclib #38151). Small telecom-adjacent subsidiary; filing has only Directors' Report/financials, no MD&A, no board committee, no CSR/sustainability/risk narrative of any kind. Standards note silent on IFRS S1/S2.
A69: =C69&"_"&G69 -> 14_2023 | B69: 68 | C69: ='Panel Data (Long Format)'!B69 -> 14 | D69: ='Panel Data (Long Format)'!C69 -> BAPLC | E69: ='Panel Data (Long Format)'!D69 -> Briclinks Africa Plc (trading as Btel) | F69: ='Panel Data (Long Format)'!E69 -> ICT | G69: ='Panel Data (Long Format)'!F69 -> 2023 | H69: 0 | I69: 0 | J69: 0 | K69: 0 | L69: 0 | M69: 0 | N69: 0 | O69: 0 | P69: 0 | Q69: 0 | R69: 0 | S69: 0 | T69: 0 | U69: 0 | V69: 0 | W69: 0 | X69: 0 | Y69: 0 | Z69: 0 | AA69: 0 | AB69: =IF(COUNTBLANK(H69:AA69)>0,"",SUM(H69:AA69)) -> 0 | AC69: =IF(AB69="","",AB69/20*100) -> 0 | AD69: 0 | AE69: 0 | AF69: 0 | AG69: 0 | AH69: 0 | AI69: 0 | AJ69: 0 | AK69: 0 | AL69: 0 | AM69: 0 | AN69: 0 | AO69: 0 | AP69: 0 | AQ69: 0 | AR69: 0 | AS69: =IF(COUNTBLANK(AD69:AR69)>0,"",SUM(AD69:AR69)) -> 0 | AT69: =IF(AS69="","",AS69/15*100) -> 0 | AU69: Bricklinks Africa Plc FY2023 Year-End FS (NGX doclib #40130). Same minimal format as FY2022; no governance/sustainability narrative; standards note silent on IFRS S1/S2.
A70: =C70&"_"&G70 -> 14_2024 | B70: 69 | C70: ='Panel Data (Long Format)'!B70 -> 14 | D70: ='Panel Data (Long Format)'!C70 -> BAPLC | E70: ='Panel Data (Long Format)'!D70 -> Briclinks Africa Plc (trading as Btel) | F70: ='Panel Data (Long Format)'!E70 -> ICT | G70: ='Panel Data (Long Format)'!F70 -> 2024 | H70: 0 | I70: 0 | J70: 0 | K70: 0 | L70: 0 | M70: 0 | N70: 0 | O70: 0 | P70: 0 | Q70: 0 | R70: 0 | S70: 0 | T70: 0 | U70: 0 | V70: 0 | W70: 0 | X70: 0 | Y70: 0 | Z70: 0 | AA70: 0 | AB70: =IF(COUNTBLANK(H70:AA70)>0,"",SUM(H70:AA70)) -> 0 | AC70: =IF(AB70="","",AB70/20*100) -> 0 | AD70: 0 | AE70: 0 | AF70: 0 | AG70: 0 | AH70: 0 | AI70: 0 | AJ70: 0 | AK70: 0 | AL70: 0 | AM70: 0 | AN70: 0 | AO70: 0 | AP70: 0 | AQ70: 0 | AR70: 0 | AS70: =IF(COUNTBLANK(AD70:AR70)>0,"",SUM(AD70:AR70)) -> 0 | AT70: =IF(AS70="","",AS70/15*100) -> 0 | AU70: GAP-FILL: BAPLC FY2024: not verified this session (only the FY2022 Financial Statements were fetched, already coded in an earlier batch). That FY2022 filing explicitly confirms 'There was no donation & charitable gift made during the year' and contains NO board committee structure at all (a 4-director micro-cap telecom company with no distinct Board Committees section), which provides reasonable context that this firm's ESG disclosure is minimal/near-zero across periods, though not directly confirmed for FY2024. Scored 0/20 SDQ, 0/15 CDQ, FLAGGED as unconfirmed pending re-verification against a dedicated FY2024 filing.
A71: =C71&"_"&G71 -> 14_2025 | B71: 70 | C71: ='Panel Data (Long Format)'!B71 -> 14 | D71: ='Panel Data (Long Format)'!C71 -> BAPLC | E71: ='Panel Data (Long Format)'!D71 -> Briclinks Africa Plc (trading as Btel) | F71: ='Panel Data (Long Format)'!E71 -> ICT | G71: ='Panel Data (Long Format)'!F71 -> 2025 | H71: 0 | I71: 0 | J71: 0 | K71: 0 | L71: 0 | M71: 0 | N71: 0 | O71: 0 | P71: 0 | Q71: 0 | R71: 0 | S71: 0 | T71: 0 | U71: 0 | V71: 0 | W71: 0 | X71: 0 | Y71: 0 | Z71: 0 | AA71: 0 | AB71: =IF(COUNTBLANK(H71:AA71)>0,"",SUM(H71:AA71)) -> 0 | AC71: =IF(AB71="","",AB71/20*100) -> 0 | AD71: 0 | AE71: 0 | AF71: 0 | AG71: 0 | AH71: 0 | AI71: 0 | AJ71: 0 | AK71: 0 | AL71: 0 | AM71: 0 | AN71: 0 | AO71: 0 | AP71: 0 | AQ71: 0 | AR71: 0 | AS71: =IF(COUNTBLANK(AD71:AR71)>0,"",SUM(AD71:AR71)) -> 0 | AT71: =IF(AS71="","",AS71/15*100) -> 0 | AU71: GAP-FILL: BAPLC FY2025: not verified this session (only the FY2022 Financial Statements were fetched, already coded in an earlier batch). That FY2022 filing explicitly confirms 'There was no donation & charitable gift made during the year' and contains NO board committee structure at all (a 4-director micro-cap telecom company with no distinct Board Committees section), which provides reasonable context that this firm's ESG disclosure is minimal/near-zero across periods, though not directly confirmed for FY2025. Scored 0/20 SDQ, 0/15 CDQ, FLAGGED as unconfirmed pending re-verification against a dedicated FY2025 filing.
A72: =C72&"_"&G72 -> 15_2021 | B72: 71 | C72: ='Panel Data (Long Format)'!B72 -> 15 | D72: ='Panel Data (Long Format)'!C72 -> BERGER | E72: ='Panel Data (Long Format)'!D72 -> Berger Paints Nigeria Plc | F72: ='Panel Data (Long Format)'!E72 -> INDUSTRIAL GOODS | G72: ='Panel Data (Long Format)'!F72 -> 2021 | H72: 1 | I72: 0 | J72: 1 | K72: 0 | L72: 0 | M72: 0 | N72: 0 | O72: 0 | P72: 0 | Q72: 0 | R72: 0 | S72: 0 | T72: 0 | U72: 1 | V72: 0 | W72: 0 | X72: 0 | Y72: 0 | Z72: 0 | AA72: 0 | AB72: =IF(COUNTBLANK(H72:AA72)>0,"",SUM(H72:AA72)) -> 3 | AC72: =IF(AB72="","",AB72/20*100) -> 15 | AD72: 0 | AE72: 0 | AF72: 0 | AG72: 0 | AH72: 0 | AI72: 0 | AJ72: 0 | AK72: 0 | AL72: 0 | AM72: 0 | AN72: 0 | AO72: 0 | AP72: 0 | AQ72: 0 | AR72: 0 | AS72: =IF(COUNTBLANK(AD72:AR72)>0,"",SUM(AD72:AR72)) -> 0 | AT72: =IF(AS72="","",AS72/15*100) -> 0 | AU72: Berger Paints Nigeria Plc FY2021 (NGX doclib #35551). Board Audit, Strategy & Risk Management Committee named with ERM oversight + CSR-policy duty (G1); meeting frequency disclosed (G3); ERM framework explicit (R4). No metrics, no climate content. Standards note silent on IFRS S1/S2 (predates ISSB issuance).
A73: =C73&"_"&G73 -> 15_2022 | B73: 72 | C73: ='Panel Data (Long Format)'!B73 -> 15 | D73: ='Panel Data (Long Format)'!C73 -> BERGER | E73: ='Panel Data (Long Format)'!D73 -> Berger Paints Nigeria Plc | F73: ='Panel Data (Long Format)'!E73 -> INDUSTRIAL GOODS | G73: ='Panel Data (Long Format)'!F73 -> 2022 | H73: 1 | I73: 0 | J73: 1 | K73: 0 | L73: 0 | M73: 0 | N73: 0 | O73: 0 | P73: 0 | Q73: 0 | R73: 0 | S73: 0 | T73: 0 | U73: 1 | V73: 0 | W73: 0 | X73: 0 | Y73: 0 | Z73: 0 | AA73: 0 | AB73: =IF(COUNTBLANK(H73:AA73)>0,"",SUM(H73:AA73)) -> 3 | AC73: =IF(AB73="","",AB73/20*100) -> 15 | AD73: 0 | AE73: 0 | AF73: 0 | AG73: 0 | AH73: 0 | AI73: 0 | AJ73: 0 | AK73: 0 | AL73: 0 | AM73: 0 | AN73: 0 | AO73: 0 | AP73: 0 | AQ73: 0 | AR73: 0 | AS73: =IF(COUNTBLANK(AD73:AR73)>0,"",SUM(AD73:AR73)) -> 0 | AT73: =IF(AS73="","",AS73/15*100) -> 0 | AU73: Berger Paints Nigeria Plc FY2022 (NGX doclib #38102). Identical governance structure to FY2021. 'Standards issued but not yet effective' note lists only IAS 12/IAS 1 amendments -- no IFRS S1/S2 (predates ISSB issuance).
A74: =C74&"_"&G74 -> 15_2023 | B74: 73 | C74: ='Panel Data (Long Format)'!B74 -> 15 | D74: ='Panel Data (Long Format)'!C74 -> BERGER | E74: ='Panel Data (Long Format)'!D74 -> Berger Paints Nigeria Plc | F74: ='Panel Data (Long Format)'!E74 -> INDUSTRIAL GOODS | G74: ='Panel Data (Long Format)'!F74 -> 2023 | H74: 1 | I74: 0 | J74: 1 | K74: 0 | L74: 0 | M74: 0 | N74: 0 | O74: 0 | P74: 0 | Q74: 0 | R74: 0 | S74: 0 | T74: 0 | U74: 1 | V74: 0 | W74: 0 | X74: 0 | Y74: 0 | Z74: 0 | AA74: 0 | AB74: =IF(COUNTBLANK(H74:AA74)>0,"",SUM(H74:AA74)) -> 3 | AC74: =IF(AB74="","",AB74/20*100) -> 15 | AD74: 0 | AE74: 0 | AF74: 0 | AG74: 0 | AH74: 0 | AI74: 0 | AJ74: 0 | AK74: 0 | AL74: 0 | AM74: 0 | AN74: 0 | AO74: 0 | AP74: 0 | AQ74: 0 | AR74: 0 | AS74: =IF(COUNTBLANK(AD74:AR74)>0,"",SUM(AD74:AR74)) -> 0 | AT74: =IF(AS74="","",AS74/15*100) -> 0 | AU74: Berger Paints Nigeria Plc FY2023 (NGX doclib #40780). Same governance pattern as FY2021/2022; no IFRS S1/S2 mention anywhere in document.
A75: =C75&"_"&G75 -> 15_2024 | B75: 74 | C75: ='Panel Data (Long Format)'!B75 -> 15 | D75: ='Panel Data (Long Format)'!C75 -> BERGER | E75: ='Panel Data (Long Format)'!D75 -> Berger Paints Nigeria Plc | F75: ='Panel Data (Long Format)'!E75 -> INDUSTRIAL GOODS | G75: ='Panel Data (Long Format)'!F75 -> 2024 | H75: 1 | I75: 0 | J75: 1 | K75: 0 | L75: 1 | M75: 0 | N75: 0 | O75: 0 | P75: 0 | Q75: 0 | R75: 0 | S75: 0 | T75: 0 | U75: 1 | V75: 0 | W75: 0 | X75: 0 | Y75: 0 | Z75: 0 | AA75: 0 | AB75: =IF(COUNTBLANK(H75:AA75)>0,"",SUM(H75:AA75)) -> 4 | AC75: =IF(AB75="","",AB75/20*100) -> 20 | AD75: 0 | AE75: 0 | AF75: 1 | AG75: 0 | AH75: 0 | AI75: 0 | AJ75: 0 | AK75: 0 | AL75: 0 | AM75: 0 | AN75: 0 | AO75: 0 | AP75: 0 | AQ75: 0 | AR75: 0 | AS75: =IF(COUNTBLANK(AD75:AR75)>0,"",SUM(AD75:AR75)) -> 1 | AT75: =IF(AS75="","",AS75/15*100) -> 6.6666667 | AU75: Berger Paints Nigeria Plc FY2024 (NGX doclib #43523). Directors' Report notes SPIN-facilitated director training 'Understanding the New ISSB (IFRS S1 & S2) Sustainability Disclosure Standards' -- scored SDQ-G5 and CDQ-G3 (climate-specific expertise via training). Standards-adoption note itself is silent on IFRS S1/S2 status, so Adopter_Dummy stays blank despite the training evidence.
A76: =C76&"_"&G76 -> 15_2025 | B76: 75 | C76: ='Panel Data (Long Format)'!B76 -> 15 | D76: ='Panel Data (Long Format)'!C76 -> BERGER | E76: ='Panel Data (Long Format)'!D76 -> Berger Paints Nigeria Plc | F76: ='Panel Data (Long Format)'!E76 -> INDUSTRIAL GOODS | G76: ='Panel Data (Long Format)'!F76 -> 2025 | H76: 0 | I76: 0 | J76: 0 | K76: 0 | L76: 0 | M76: 0 | N76: 0 | O76: 0 | P76: 0 | Q76: 0 | R76: 1 | S76: 0 | T76: 1 | U76: 0 | V76: 0 | W76: 1 | X76: 0 | Y76: 0 | Z76: 0 | AA76: 0 | AB76: =IF(COUNTBLANK(H76:AA76)>0,"",SUM(H76:AA76)) -> 3 | AC76: =IF(AB76="","",AB76/20*100) -> 15 | AD76: 0 | AE76: 0 | AF76: 0 | AG76: 0 | AH76: 0 | AI76: 0 | AJ76: 0 | AK76: 0 | AL76: 0 | AM76: 0 | AN76: 0 | AO76: 0 | AP76: 0 | AQ76: 0 | AR76: 0 | AS76: =IF(COUNTBLANK(AD76:AR76)>0,"",SUM(AD76:AR76)) -> 0 | AT76: =IF(AS76="","",AS76/15*100) -> 0 | AU76: GAP-FILL: BERGER FY2025 (Audited Consolidated and Separate Financial Statements, NGX doclib, fetched directly): SDQ=3/20. Credited: SDQ_M1 (Note 9 'Donations and gifts' - fully itemised table, Opebi Primary Health Centre Maternity Ward painting N256,439, Heritage Homes orphanage painting N535,228, Federal Nigerian Society for the Blind facility painting N1,504,928, total N2,296,595); SDQ_R1 (a named 'Safety and environment policy' explicitly includes 'The assessment of the adverse impact of our raw materials or new products on both humans and the environment' - a specific environmental-risk-identification practice); SDQ_R3 (the same policy states the Company conducts 'a periodic environmental audit to monitor the significant environmental aspects of our operations' - a named ongoing-monitoring process). NOT credited: SDQ_G1 (no sustainability-specific board committee among Finance & General-Purpose, Establishment/Remuneration/Governance, and Audit/Strategy/Risk Management Committees); SDQ_R2 (no distinct risk-assessment/prioritisation process described separately from R1/R3); SDQ_M3 (no quantified environmental metric beyond the donations figure). CDQ=0/15 - the 'Sustainability' sub-section references 'use of modern technology and expertise to reduce environmental pollution' and 'proper disposal or recycle of waste' but is generic pollution/waste-management language, not climate/GHG-specific, and no emissions figures were found anywhere in the document.
... A126: =C126&"_"&G126 -> 25_2025 | B126: 125 | C126: ='Panel Data (Long Format)'!B126 -> 25 | D126: ='Panel Data (Long Format)'!C126 -> CILEASING | E126: ='Panel Data (Long Format)'!D126 -> C & I Leasing Plc | F126: ='Panel Data (Long Format)'!E126 -> SERVICES | G126: ='Panel Data (Long Format)'!F126 -> 2025 | H126: 0 | I126: 0 | J126: 0 | K126: 0 | L126: 0 | M126: 0 | N126: 0 | O126: 0 | P126: 0 | Q126: 0 | R126: 0 | S126: 0 | T126: 0 | U126: 0 | V126: 0 | W126: 0 | X126: 0 | Y126: 0 | Z126: 0 | AA126: 0 | AB126: =IF(COUNTBLANK(H126:AA126)>0,"",SUM(H126:AA126)) -> 0 | AC126: =IF(AB126="","",AB126/20*100) -> 0 | AD126: 0 | AE126: 0 | AF126: 0 | AG126: 0 | AH126: 0 | AI126: 0 | AJ126: 0 | AK126: 0 | AL126: 0 | AM126: 0 | AN126: 0 | AO126: 0 | AP126: 0 | AQ126: 0 | AR126: 0 | AS126: =IF(COUNTBLANK(AD126:AR126)>0,"",SUM(AD126:AR126)) -> 0 | AT126: =IF(AS126="","",AS126/15*100) -> 0 | AU126: C&I Leasing Plc FY2025 (NGX doclib ID 45907). Filing contains only FS + notes, no Directors'/Governance/CSR sections at all.
A127: =C127&"_"&G127 -> 26_2021 | B127: 126 | C127: ='Panel Data (Long Format)'!B127 -> 26 | D127: ='Panel Data (Long Format)'!C127 -> CMFC | E127: ='Panel Data (Long Format)'!D127 -> Critical Minerals Financing Corp Plc (formerly Deap Capital Management & Trust Plc) | F127: ='Panel Data (Long Format)'!E127 -> FINANCIAL SERVICES | G127: ='Panel Data (Long Format)'!F127 -> 2021 | AB127: =IF(COUNTBLANK(H127:AA127)>0,"",SUM(H127:AA127)) | AC127: =IF(AB127="","",AB127/20*100) | AS127: =IF(COUNTBLANK(AD127:AR127)>0,"",SUM(AD127:AR127)) | AT127: =IF(AS127="","",AS127/15*100) | AU127: GENUINE GAP: Only an abridged report exists on AfricanFinancials for FY2021; NGX doclib search ('DEAP CAPITAL') surfaced no separate full audited FS. Abridged report page contains no governance/CSR/note-level content beyond company profile boilerplate.
A128: =C128&"_"&G128 -> 26_2022 | B128: 127 | C128: ='Panel Data (Long Format)'!B128 -> 26 | D128: ='Panel Data (Long Format)'!C128 -> CMFC | E128: ='Panel Data (Long Format)'!D128 -> Critical Minerals Financing Corp Plc (formerly Deap Capital Management & Trust Plc) | F128: ='Panel Data (Long Format)'!E128 -> FINANCIAL SERVICES | G128: ='Panel Data (Long Format)'!F128 -> 2022 | AB128: =IF(COUNTBLANK(H128:AA128)>0,"",SUM(H128:AA128)) | AC128: =IF(AB128="","",AB128/20*100) | AS128: =IF(COUNTBLANK(AD128:AR128)>0,"",SUM(AD128:AR128)) | AT128: =IF(AS128="","",AS128/15*100) | AU128: GENUINE GAP: Confirmed abridged-only filing (AfricanFinancials ng-deapca-2022-ab-00); no FY2022 full audited FS located on NGX doclib despite targeted search.
A129: =C129&"_"&G129 -> 26_2023 | B129: 128 | C129: ='Panel Data (Long Format)'!B129 -> 26 | D129: ='Panel Data (Long Format)'!C129 -> CMFC | E129: ='Panel Data (Long Format)'!D129 -> Critical Minerals Financing Corp Plc (formerly Deap Capital Management & Trust Plc) | F129: ='Panel Data (Long Format)'!E129 -> FINANCIAL SERVICES | G129: ='Panel Data (Long Format)'!F129 -> 2023 | AB129: =IF(COUNTBLANK(H129:AA129)>0,"",SUM(H129:AA129)) | AC129: =IF(AB129="","",AB129/20*100) | AS129: =IF(COUNTBLANK(AD129:AR129)>0,"",SUM(AD129:AR129)) | AT129: =IF(AS129="","",AS129/15*100) | AU129: GENUINE GAP: Abridged-only filing confirmed; company appears to be a late-filer (results for several years released in a catch-up cycle); no full audited FS with governance notes located.
A130: =C130&"_"&G130 -> 26_2024 | B130: 129 | C130: ='Panel Data (Long Format)'!B130 -> 26 | D130: ='Panel Data (Long Format)'!C130 -> CMFC | E130: ='Panel Data (Long Format)'!D130 -> Critical Minerals Financing Corp Plc (formerly Deap Capital Management & Trust Plc) | F130: ='Panel Data (Long Format)'!E130 -> FINANCIAL SERVICES | G130: ='Panel Data (Long Format)'!F130 -> 2024 | AB130: =IF(COUNTBLANK(H130:AA130)>0,"",SUM(H130:AA130)) | AC130: =IF(AB130="","",AB130/20*100) | AS130: =IF(COUNTBLANK(AD130:AR130)>0,"",SUM(AD130:AR130)) | AT130: =IF(AS130="","",AS130/15*100) | AU130: GENUINE GAP: NGX doclib PDF is a confirmed scanned/image document with zero extractable text (no OCR capability available this session). AfricanFinancials Google Drive embed for the same filing also returns empty.
A131: =C131&"_"&G131 -> 26_2025 | B131: 130 | C131: ='Panel Data (Long Format)'!B131 -> 26 | D131: ='Panel Data (Long Format)'!C131 -> CMFC | E131: ='Panel Data (Long Format)'!D131 -> Critical Minerals Financing Corp Plc (formerly Deap Capital Management & Trust Plc) | F131: ='Panel Data (Long Format)'!E131 -> FINANCIAL SERVICES | G131: ='Panel Data (Long Format)'!F131 -> 2025 | AB131: =IF(COUNTBLANK(H131:AA131)>0,"",SUM(H131:AA131)) | AC131: =IF(AB131="","",AB131/20*100) | AS131: =IF(COUNTBLANK(AD131:AR131)>0,"",SUM(AD131:AR131)) | AT131: =IF(AS131="","",AS131/15*100) | AU131: GENUINE GAP: NGX doclib PDF (FYE shifted to 30-Sep-2025) is a confirmed scanned/image document with zero extractable text -- no OCR capability available this session. NOTE: AfricanFinancials carries a self-labelled AI-generated summary of this filing, but per this project's standing rule, AI-generated summaries are never used as a primary coding source (circularity risk) -- so this firm-year is documented as a genuine access gap rather than coded from that secondary source. Flagged for re-check if OCR tooling or an alternate primary source becomes available.
A132: =C132&"_"&G132 -> 27_2021 | B132: 131 | C132: ='Panel Data (Long Format)'!B132 -> 27 | D132: ='Panel Data (Long Format)'!C132 -> CNIF | E132: ='Panel Data (Long Format)'!D132 -> Coronation Infrastructure Fund | F132: ='Panel Data (Long Format)'!E132 -> INDUSTRIAL GOODS | G132: ='Panel Data (Long Format)'!F132 -> 2021 | AB132: =IF(COUNTBLANK(H132:AA132)>0,"",SUM(H132:AA132)) | AC132: =IF(AB132="","",AB132/20*100) | AS132: =IF(COUNTBLANK(AD132:AR132)>0,"",SUM(AD132:AR132)) | AT132: =IF(AS132="","",AS132/15*100) | AU132: GENUINE GAP: Coronation Infrastructure Fund listed on NGX in August 2025; did not exist as a public reporting entity in FY2021 -- excluded by design, consistent with other pre-listing firm-years elsewhere in this dataset.
A133: =C133&"_"&G133 -> 27_2022 | B133: 132 | C133: ='Panel Data (Long Format)'!B133 -> 27 | D133: ='Panel Data (Long Format)'!C133 -> CNIF | E133: ='Panel Data (Long Format)'!D133 -> Coronation Infrastructure Fund | F133: ='Panel Data (Long Format)'!E133 -> INDUSTRIAL GOODS | G133: ='Panel Data (Long Format)'!F133 -> 2022 | AB133: =IF(COUNTBLANK(H133:AA133)>0,"",SUM(H133:AA133)) | AC133: =IF(AB133="","",AB133/20*100) | AS133: =IF(COUNTBLANK(AD133:AR133)>0,"",SUM(AD133:AR133)) | AT133: =IF(AS133="","",AS133/15*100) | AU133: GENUINE GAP: Same pre-listing reasoning as FY2021 -- fund did not exist as a public entity.
A134: =C134&"_"&G134 -> 27_2023 | B134: 133 | C134: ='Panel Data (Long Format)'!B134 -> 27 | D134: ='Panel Data (Long Format)'!C134 -> CNIF | E134: ='Panel Data (Long Format)'!D134 -> Coronation Infrastructure Fund | F134: ='Panel Data (Long Format)'!E134 -> INDUSTRIAL GOODS | G134: ='Panel Data (Long Format)'!F134 -> 2023 | AB134: =IF(COUNTBLANK(H134:AA134)>0,"",SUM(H134:AA134)) | AC134: =IF(AB134="","",AB134/20*100) | AS134: =IF(COUNTBLANK(AD134:AR134)>0,"",SUM(AD134:AR134)) | AT134: =IF(AS134="","",AS134/15*100) | AU134: GENUINE GAP: Same pre-listing reasoning as FY2021 -- fund did not exist as a public entity.
A135: =C135&"_"&G135 -> 27_2024 | B135: 134 | C135: ='Panel Data (Long Format)'!B135 -> 27 | D135: ='Panel Data (Long Format)'!C135 -> CNIF | E135: ='Panel Data (Long Format)'!D135 -> Coronation Infrastructure Fund | F135: ='Panel Data (Long Format)'!E135 -> INDUSTRIAL GOODS | G135: ='Panel Data (Long Format)'!F135 -> 2024 | AB135: =IF(COUNTBLANK(H135:AA135)>0,"",SUM(H135:AA135)) | AC135: =IF(AB135="","",AB135/20*100) | AS135: =IF(COUNTBLANK(AD135:AR135)>0,"",SUM(AD135:AR135)) | AT135: =IF(AS135="","",AS135/15*100) | AU135: GENUINE GAP: Same pre-listing reasoning as FY2021 -- fund did not exist as a public entity.
A136: =C136&"_"&G136 -> 27_2025 | B136: 135 | C136: ='Panel Data (Long Format)'!B136 -> 27 | D136: ='Panel Data (Long Format)'!C136 -> CNIF | E136: ='Panel Data (Long Format)'!D136 -> Coronation Infrastructure Fund | F136: ='Panel Data (Long Format)'!E136 -> INDUSTRIAL GOODS | G136: ='Panel Data (Long Format)'!F136 -> 2025 | H136: 0 | I136: 0 | J136: 0 | K136: 0 | L136: 0 | M136: 0 | N136: 0 | O136: 1 | P136: 0 | Q136: 0 | R136: 0 | S136: 0 | T136: 0 | U136: 0 | V136: 0 | W136: 1 | X136: 1 | Y136: 1 | Z136: 0 | AA136: 0 | AB136: =IF(COUNTBLANK(H136:AA136)>0,"",SUM(H136:AA136)) -> 4 | AC136: =IF(AB136="","",AB136/20*100) -> 20 | AD136: 0 | AE136: 0 | AF136: 0 | AG136: 0 | AH136: 0 | AI136: 0 | AJ136: 0 | AK136: 0 | AL136: 0 | AM136: 0 | AN136: 0 | AO136: 0 | AP136: 0 | AQ136: 0 | AR136: 0 | AS136: =IF(COUNTBLANK(AD136:AR136)>0,"",SUM(AD136:AR136)) -> 0 | AT136: =IF(AS136="","",AS136/15*100) -> 0 | AU136: Coronation Infrastructure Fund 2025 Annual Report (NGX doclib #46999, full text extracted). S3=1: 'Sustainability' strategy section (pp.6-7) states integration of SDG considerations into project selection, capital allocation, governance oversight and performance monitoring. M1/M3=1: entity-specific ESG/impact metrics per portfolio project (pp.17-18) -- e.g. 30,000 diesel generators displaced, 14% women in managerial roles, jobs created. M2=1: target-vs-actual shown for the Independent Power Project (p.17): Target 31 customers/30MW/33kv feeder route vs. actual 25 customers connected/6MW connected/5 feeders radiated. No Board of Directors section exists in this document -- governance structure described is Investment Committee + Fund Manager + Trustee (p.9), only generic 'Risk Management' bullets (p.9) not framed around sustainability, hence all G and R items=0. No GHG figures, scenario analysis or transition plan tied to the Fund's own operations -- all CDQ=0. This is the Fund's strategy/impact annual report; a separate audited financial statement FY2025 is referenced (p.14) but not linked/located this session -- the Basis of Preparation/IFRS S1-S2 adoption note likely sits there, so Adopter_Dummy is blank rather than inferred, flagged for re-check if that document becomes accessible.
A137: =C137&"_"&G137 -> 28_2021 | B137: 136 | C137: ='Panel Data (Long Format)'!B137 -> 28 | D137: ='Panel Data (Long Format)'!C137 -> CONHALLPLC | E137: ='Panel Data (Long Format)'!D137 -> Consolidated Hallmark Holdings Plc (formerly Consolidated Hallmark Insurance Plc) | F137: ='Panel Data (Long Format)'!E137 -> FINANCIAL SERVICES | G137: ='Panel Data (Long Format)'!F137 -> 2021 | H137: 0 | I137: 0 | J137: 0 | K137: 0 | L137: 0 | M137: 0 | N137: 0 | O137: 0 | P137: 0 | Q137: 0 | R137: 1 | S137: 0 | T137: 0 | U137: 1 | V137: 0 | W137: 1 | X137: 0 | Y137: 0 | Z137: 0 | AA137: 0 | AB137: =IF(COUNTBLANK(H137:AA137)>0,"",SUM(H137:AA137)) -> 3 | AC137: =IF(AB137="","",AB137/20*100) -> 15 | AD137: 0 | AE137: 0 | AF137: 0 | AG137: 0 | AH137: 0 | AI137: 0 | AJ137: 0 | AK137: 0 | AL137: 0 | AM137: 0 | AN137: 0 | AO137: 0 | AP137: 0 | AQ137: 0 | AR137: 0 | AS137: =IF(COUNTBLANK(AD137:AR137)>0,"",SUM(AD137:AR137)) -> 0 | AT137: =IF(AS137="","",AS137/15*100) -> 0 | AU137: Consolidated Hallmark Insurance Plc FY2021 (ch-insure.com, full Annual Report & Accounts). 'Sustainability Reporting' section: ERM framework covers environmental risks (R1, R4). Sponsorship/donations table (N12.48m) = M1. Board committees generic, not sustainability-framed.
A138: =C138&"_"&G138 -> 28_2022 | B138: 137 | C138: ='Panel Data (Long Format)'!B138 -> 28 | D138: ='Panel Data (Long Format)'!C138 -> CONHALLPLC | E138: ='Panel Data (Long Format)'!D138 -> Consolidated Hallmark Holdings Plc (formerly Consolidated Hallmark Insurance Plc) | F138: ='Panel Data (Long Format)'!E138 -> FINANCIAL SERVICES | G138: ='Panel Data (Long Format)'!F138 -> 2022 | H138: 0 | I138: 0 | J138: 0 | K138: 0 | L138: 0 | M138: 0 | N138: 0 | O138: 0 | P138: 0 | Q138: 0 | R138: 1 | S138: 0 | T138: 0 | U138: 1 | V138: 0 | W138: 1 | X138: 0 | Y138: 0 | Z138: 0 | AA138: 0 | AB138: =IF(COUNTBLANK(H138:AA138)>0,"",SUM(H138:AA138)) -> 3 | AC138: =IF(AB138="","",AB138/20*100) -> 15 | AD138: 0 | AE138: 0 | AF138: 0 | AG138: 0 | AH138: 0 | AI138: 0 | AJ138: 0 | AK138: 0 | AL138: 0 | AM138: 0 | AN138: 0 | AO138: 0 | AP138: 0 | AQ138: 0 | AR138: 0 | AS138: =IF(COUNTBLANK(AD138:AR138)>0,"",SUM(AD138:AR138)) -> 0 | AT138: =IF(AS138="","",AS138/15*100) -> 0 | AU138: Consolidated Hallmark Insurance Plc FY2022 (NGX doclib ID 38065). Same 'Sustainability Reporting' boilerplate (pp.16-17); donations total N7.71m = M1. Standards note covers only IFRS 17/IAS 1/IFRS 8, no ISSB.
A139: =C139&"_"&G139 -> 28_2023 | B139: 138 | C139: ='Panel Data (Long Format)'!B139 -> 28 | D139: ='Panel Data (Long Format)'!C139 -> CONHALLPLC | E139: ='Panel Data (Long Format)'!D139 -> Consolidated Hallmark Holdings Plc (formerly Consolidated Hallmark Insurance Plc) | F139: ='Panel Data (Long Format)'!E139 -> FINANCIAL SERVICES | G139: ='Panel Data (Long Format)'!F139 -> 2023 | H139: 0 | I139: 0 | J139: 0 | K139: 0 | L139: 0 | M139: 0 | N139: 0 | O139: 0 | P139: 0 | Q139: 0 | R139: 0 | S139: 0 | T139: 0 | U139: 0 | V139: 0 | W139: 0 | X139: 0 | Y139: 0 | Z139: 0 | AA139: 0 | AB139: =IF(COUNTBLANK(H139:AA139)>0,"",SUM(H139:AA139)) -> 0 | AC139: =IF(AB139="","",AB139/20*100) -> 0 | AD139: 0 | AE139: 0 | AF139: 0 | AG139: 0 | AH139: 0 | AI139: 0 | AJ139: 0 | AK139: 0 | AL139: 0 | AM139: 0 | AN139: 0 | AO139: 0 | AP139: 0 | AQ139: 0 | AR139: 0 | AS139: =IF(COUNTBLANK(AD139:AR139)>0,"",SUM(AD139:AR139)) -> 0 | AT139: =IF(AS139="","",AS139/15*100) -> 0 | AU139: Consolidated Hallmark Insurance Plc FY2023 (NGX doclib ID 40250, interim-style FS for period ended 31-Dec-2023). Abbreviated filing -- no Directors'/Governance/Sustainability sections. Genuine content gap in the filed document itself.
A140: =C140&"_"&G140 -> 28_2024 | B140: 139 | C140: ='Panel Data (Long Format)'!B140 -> 28 | D140: ='Panel Data (Long Format)'!C140 -> CONHALLPLC | E140: ='Panel Data (Long Format)'!D140 -> Consolidated Hallmark Holdings Plc (formerly Consolidated Hallmark Insurance Plc) | F140: ='Panel Data (Long Format)'!E140 -> FINANCIAL SERVICES | G140: ='Panel Data (Long Format)'!F140 -> 2024 | H140: 0 | I140: 0 | J140: 0 | K140: 0 | L140: 0 | M140: 0 | N140: 0 | O140: 0 | P140: 0 | Q140: 0 | R140: 0 | S140: 0 | T140: 0 | U140: 0 | V140: 0 | W140: 0 | X140: 0 | Y140: 0 | Z140: 0 | AA140: 0 | AB140: =IF(COUNTBLANK(H140:AA140)>0,"",SUM(H140:AA140)) -> 0 | AC140: =IF(AB140="","",AB140/20*100) -> 0 | AD140: 0 | AE140: 0 | AF140: 0 | AG140: 0 | AH140: 0 | AI140: 0 | AJ140: 0 | AK140: 0 | AL140: 0 | AM140: 0 | AN140: 0 | AO140: 0 | AP140: 0 | AQ140: 0 | AR140: 0 | AS140: =IF(COUNTBLANK(AD140:AR140)>0,"",SUM(AD140:AR140)) -> 0 | AT140: =IF(AS140="","",AS140/15*100) -> 0 | AU140: Consolidated Hallmark Holdings Plc FY2024 (NGX doclib ID 43061). First filing as new HoldCo (CHH Plc); same abbreviated interim-style format, no governance/sustainability narrative.
A141: =C141&"_"&G141 -> 28_2025 | B141: 140 | C141: ='Panel Data (Long Format)'!B141 -> 28 | D141: ='Panel Data (Long Format)'!C141 -> CONHALLPLC | E141: ='Panel Data (Long Format)'!D141 -> Consolidated Hallmark Holdings Plc (formerly Consolidated Hallmark Insurance Plc) | F141: ='Panel Data (Long Format)'!E141 -> FINANCIAL SERVICES | G141: ='Panel Data (Long Format)'!F141 -> 2025 | H141: 0 | I141: 0 | J141: 0 | K141: 0 | L141: 0 | M141: 0 | N141: 0 | O141: 0 | P141: 0 | Q141: 0 | R141: 0 | S141: 0 | T141: 0 | U141: 0 | V141: 0 | W141: 0 | X141: 0 | Y141: 0 | Z141: 0 | AA141: 0 | AB141: =IF(COUNTBLANK(H141:AA141)>0,"",SUM(H141:AA141)) -> 0 | AC141: =IF(AB141="","",AB141/20*100) -> 0 | AD141: 0 | AE141: 0 | AF141: 0 | AG141: 0 | AH141: 0 | AI141: 0 | AJ141: 0 | AK141: 0 | AL141: 0 | AM141: 0 | AN141: 0 | AO141: 0 | AP141: 0 | AQ141: 0 | AR141: 0 | AS141: =IF(COUNTBLANK(AD141:AR141)>0,"",SUM(AD141:AR141)) -> 0 | AT141: =IF(AS141="","",AS141/15*100) -> 0 | AU141: GAP-FILL: CONHALLPLC (Consolidated Hallmark Holdings Plc) FY2025: not verified this session - only interim Q1-Q3 2025 and Q1 2026 unaudited financial statements were located via search; no Year-End/audited FY2025 Annual Report was located within this session's search budget (interim filings typically omit the Directors' Report CSR/ESG sections that carry this dataset's scorable content). Scored 0/20 SDQ, 0/15 CDQ, FLAGGED as unconfirmed pending re-verification against the full audited FY2025 Annual Report once filed. Note: this firm's FY2021-2024 were already coded in an earlier batch (Batch 27's predecessor sessions), so this is purely a most-recent-year gap.
A142: =C142&"_"&G142 -> 29_2021 | B142: 141 | C142: ='Panel Data (Long Format)'!B142 -> 29 | D142: ='Panel Data (Long Format)'!C142 -> CONOIL | E142: ='Panel Data (Long Format)'!D142 -> Conoil Plc | F142: ='Panel Data (Long Format)'!E142 -> OIL AND GAS | G142: ='Panel Data (Long Format)'!F142 -> 2021 | H142: 0 | I142: 0 | J142: 0 | K142: 0 | L142: 0 | M142: 0 | N142: 0 | O142: 0 | P142: 0 | Q142: 0 | R142: 0 | S142: 0 | T142: 0 | U142: 0 | V142: 0 | W142: 1 | X142: 0 | Y142: 0 | Z142: 0 | AA142: 0 | AB142: =IF(COUNTBLANK(H142:AA142)>0,"",SUM(H142:AA142)) -> 1 | AC142: =IF(AB142="","",AB142/20*100) -> 5 | AD142: 0 | AE142: 0 | AF142: 0 | AG142: 0 | AH142: 0 | AI142: 0 | AJ142: 0 | AK142: 0 | AL142: 0 | AM142: 0 | AN142: 0 | AO142: 0 | AP142: 0 | AQ142: 0 | AR142: 0 | AS142: =IF(COUNTBLANK(AD142:AR142)>0,"",SUM(AD142:AR142)) -> 0 | AT142: =IF(AS142="","",AS142/15*100) -> 0 | AU142: Conoil Plc FY2021 (conoilplc.com, official Annual Report). Diversity/gender headcount table (p.27) = M1 only. Risk Committee/board expertise generic, no sustainability mandate.
A143: =C143&"_"&G143 -> 29_2022 | B143: 142 | C143: ='Panel Data (Long Format)'!B143 -> 29 | D143: ='Panel Data (Long Format)'!C143 -> CONOIL | E143: ='Panel Data (Long Format)'!D143 -> Conoil Plc | F143: ='Panel Data (Long Format)'!E143 -> OIL AND GAS | G143: ='Panel Data (Long Format)'!F143 -> 2022 | H143: 0 | I143: 0 | J143: 0 | K143: 0 | L143: 0 | M143: 0 | N143: 0 | O143: 0 | P143: 0 | Q143: 0 | R143: 0 | S143: 0 | T143: 0 | U143: 0 | V143: 0 | W143: 1 | X143: 0 | Y143: 0 | Z143: 0 | AA143: 0 | AB143: =IF(COUNTBLANK(H143:AA143)>0,"",SUM(H143:AA143)) -> 1 | AC143: =IF(AB143="","",AB143/20*100) -> 5 | AD143: 0 | AE143: 0 | AF143: 0 | AG143: 0 | AH143: 0 | AI143: 0 | AJ143: 0 | AK143: 0 | AL143: 0 | AM143: 0 | AN143: 0 | AO143: 0 | AP143: 0 | AQ143: 0 | AR143: 0 | AS143: =IF(COUNTBLANK(AD143:AR143)>0,"",SUM(AD143:AR143)) -> 0 | AT143: =IF(AS143="","",AS143/15*100) -> 0 | AU143: Conoil Plc FY2022 (conoilplc.com Annual Report). 'Climate Change Issues and Policy Options' section (pp.19-20) is generic Nigeria-level macro commentary, not entity-specific -- scores 0 on CDQ. Gender table = M1.
A144: =C144&"_"&G144 -> 29_2023 | B144: 143 | C144: ='Panel Data (Long Format)'!B144 -> 29 | D144: ='Panel Data (Long Format)'!C144 -> CONOIL | E144: ='Panel Data (Long Format)'!D144 -> Conoil Plc | F144: ='Panel Data (Long Format)'!E144 -> OIL AND GAS | G144: ='Panel Data (Long Format)'!F144 -> 2023 | H144: 0 | I144: 0 | J144: 0 | K144: 0 | L144: 0 | M144: 0 | N144: 0 | O144: 0 | P144: 0 | Q144: 0 | R144: 0 | S144: 0 | T144: 0 | U144: 0 | V144: 0 | W144: 1 | X144: 0 | Y144: 0 | Z144: 0 | AA144: 0 | AB144: =IF(COUNTBLANK(H144:AA144)>0,"",SUM(H144:AA144)) -> 1 | AC144: =IF(AB144="","",AB144/20*100) -> 5 | AD144: 0 | AE144: 0 | AF144: 0 | AG144: 0 | AH144: 0 | AI144: 0 | AJ144: 0 | AK144: 0 | AL144: 0 | AM144: 0 | AN144: 0 | AO144: 0 | AP144: 0 | AQ144: 0 | AR144: 0 | AS144: =IF(COUNTBLANK(AD144:AR144)>0,"",SUM(AD144:AR144)) -> 0 | AT144: =IF(AS144="","",AS144/15*100) -> 0 | AU144: Conoil Plc FY2023 (conoilplc.com, Full-Year Annual Report). CSR contributions figure (N32m) + gender table = M1. Zero climate-related keyword hits anywhere.
A145: =C145&"_"&G145 -> 29_2024 | B145: 144 | C145: ='Panel Data (Long Format)'!B145 -> 29 | D145: ='Panel Data (Long Format)'!C145 -> CONOIL | E145: ='Panel Data (Long Format)'!D145 -> Conoil Plc | F145: ='Panel Data (Long Format)'!E145 -> OIL AND GAS | G145: ='Panel Data (Long Format)'!F145 -> 2024 | H145: 0 | I145: 0 | J145: 0 | K145: 0 | L145: 0 | M145: 0 | N145: 0 | O145: 0 | P145: 0 | Q145: 0 | R145: 0 | S145: 0 | T145: 0 | U145: 0 | V145: 0 | W145: 1 | X145: 0 | Y145: 0 | Z145: 0 | AA145: 0 | AB145: =IF(COUNTBLANK(H145:AA145)>0,"",SUM(H145:AA145)) -> 1 | AC145: =IF(AB145="","",AB145/20*100) -> 5 | AD145: 0 | AE145: 0 | AF145: 0 | AG145: 0 | AH145: 0 | AI145: 0 | AJ145: 0 | AK145: 0 | AL145: 0 | AM145: 0 | AN145: 0 | AO145: 0 | AP145: 0 | AQ145: 0 | AR145: 0 | AS145: =IF(COUNTBLANK(AD145:AR145)>0,"",SUM(AD145:AR145)) -> 0 | AT145: =IF(AS145="","",AS145/15*100) -> 0 | AU145: Conoil Plc FY2024 (NGX doclib ID 44295). Note 2.2 explicitly lists 'Sustainability Reporting Standards (ESG-related Standards)' as issued-but-not-yet-effective and states company elected NOT to early adopt -> Adopter_Dummy=0. Gender table = M1.
A146: =C146&"_"&G146 -> 29_2025 | B146: 145 | C146: ='Panel Data (Long Format)'!B146 -> 29 | D146: ='Panel Data (Long Format)'!C146 -> CONOIL | E146: ='Panel Data (Long Format)'!D146 -> Conoil Plc | F146: ='Panel Data (Long Format)'!E146 -> OIL AND GAS | G146: ='Panel Data (Long Format)'!F146 -> 2025 | H146: 0 | I146: 0 | J146: 0 | K146: 0 | L146: 0 | M146: 0 | N146: 0 | O146: 0 | P146: 0 | Q146: 0 | R146: 0 | S146: 0 | T146: 0 | U146: 0 | V146: 0 | W146: 1 | X146: 0 | Y146: 0 | Z146: 0 | AA146: 0 | AB146: =IF(COUNTBLANK(H146:AA146)>0,"",SUM(H146:AA146)) -> 1 | AC146: =IF(AB146="","",AB146/20*100) -> 5 | AD146: 0 | AE146: 0 | AF146: 0 | AG146: 0 | AH146: 0 | AI146: 0 | AJ146: 0 | AK146: 0 | AL146: 0 | AM146: 0 | AN146: 0 | AO146: 0 | AP146: 0 | AQ146: 0 | AR146: 0 | AS146: =IF(COUNTBLANK(AD146:AR146)>0,"",SUM(AD146:AR146)) -> 0 | AT146: =IF(AS146="","",AS146/15*100) -> 0 | AU146: Conoil Plc FY2025 (NGX doclib ID 47162, final audited FS). Same Note 2.2 language, elected not to early-adopt -> Adopter_Dummy=0. Gender table = M1. CSR 'under consideration and development.'
A147: =C147&"_"&G147 -> 30_2021 | B147: 146 | C147: ='Panel Data (Long Format)'!B147 -> 30 | D147: ='Panel Data (Long Format)'!C147 -> CORNERST | E147: ='Panel Data (Long Format)'!D147 -> Cornerstone Insurance Plc | F147: ='Panel Data (Long Format)'!E147 -> FINANCIAL SERVICES | G147: ='Panel Data (Long Format)'!F147 -> 2021 | H147: 1 | I147: 1 | J147: 1 | K147: 0 | L147: 0 | M147: 0 | N147: 0 | O147: 0 | P147: 0 | Q147: 0 | R147: 1 | S147: 1 | T147: 1 | U147: 1 | V147: 1 | W147: 1 | X147: 0 | Y147: 1 | Z147: 0 | AA147: 0 | AB147: =IF(COUNTBLANK(H147:AA147)>0,"",SUM(H147:AA147)) -> 10 | AC147: =IF(AB147="","",AB147/20*100) -> 50 | AD147: 0 | AE147: 0 | AF147: 0 | AG147: 0 | AH147: 0 | AI147: 0 | AJ147: 0 | AK147: 0 | AL147: 0 | AM147: 0 | AN147: 0 | AO147: 0 | AP147: 0 | AQ147: 0 | AR147: 0 | AS147: =IF(COUNTBLANK(AD147:AR147)>0,"",SUM(AD147:AR147)) -> 0 | AT147: =IF(AS147="","",AS147/15*100) -> 0 | AU147: Cornerstone Insurance Plc FY2021 (cornerstone.com.ng Annual Report). ERM & Governance Committee, Head of ERM, quarterly board reporting; RCSA/RAG/Risk Appetite Dashboard named; Category-C E&S classification (M3); training metric (M1). No climate content. CAVEAT: standards-adoption note is beyond this session's PDF extraction limit (~100K chars) so Adopter_Dummy is blank due to inaccessibility, not confirmed non-adoption -- flagged for re-check.
... A181: =C181&"_"&G181 -> 36_2025 | B181: 180 | C181: ='Panel Data (Long Format)'!B181 -> 36 | D181: ='Panel Data (Long Format)'!C181 -> DANGSUGAR | E181: ='Panel Data (Long Format)'!D181 -> Dangote Sugar Refinery Plc | F181: ='Panel Data (Long Format)'!E181 -> CONSUMER GOODS | G181: ='Panel Data (Long Format)'!F181 -> 2025 | H181: 0 | I181: 0 | J181: 0 | K181: 0 | L181: 0 | M181: 0 | N181: 0 | O181: 0 | P181: 0 | Q181: 0 | R181: 0 | S181: 0 | T181: 0 | U181: 0 | V181: 0 | W181: 1 | X181: 0 | Y181: 0 | Z181: 0 | AA181: 0 | AB181: =IF(COUNTBLANK(H181:AA181)>0,"",SUM(H181:AA181)) -> 1 | AC181: =IF(AB181="","",AB181/20*100) -> 5 | AD181: 0 | AE181: 0 | AF181: 0 | AG181: 0 | AH181: 0 | AI181: 0 | AJ181: 0 | AK181: 0 | AL181: 0 | AM181: 0 | AN181: 0 | AO181: 0 | AP181: 0 | AQ181: 0 | AR181: 0 | AS181: =IF(COUNTBLANK(AD181:AR181)>0,"",SUM(AD181:AR181)) -> 0 | AT181: =IF(AS181="","",AS181/15*100) -> 0 | AU181: GAP-FILL: DANGSUGAR FY2025 (Annual Report and Financial Statements, NGX doclib, fetched directly): SDQ_M1=1 - Directors' Report Note 18 'Donations and Charitable Gifts' itemises 37 line items totalling N112,118,053 (community scholarships, school furniture, cultural festival sponsorships, police/security station support, NSE conference support). CDQ NOT scored from this document (the AFS itself contains no GHG/climate content; the dedicated FY2025 Sustainability Report, which secondary sources indicate covers a new 'comprehensive Decarbonization Plan for achieving Net Zero' and CDP score improvements, was not fetched this session). Scored CDQ=0/15, FLAGGED as a HIGH-PRIORITY re-verification candidate - given the confirmed FY2023 profile (6/20 SDQ, 4/15 CDQ) and secondary-source evidence of continued/expanded climate ambition, FY2025's true profile is very likely materially higher than scored here.
A182: =C182&"_"&G182 -> 37_2021 | B182: 181 | C182: ='Panel Data (Long Format)'!B182 -> 37 | D182: ='Panel Data (Long Format)'!C182 -> EKOCORP | E182: ='Panel Data (Long Format)'!D182 -> Ekocorp Plc | F182: ='Panel Data (Long Format)'!E182 -> HEALTHCARE | G182: ='Panel Data (Long Format)'!F182 -> 2021 | AB182: =IF(COUNTBLANK(H182:AA182)>0,"",SUM(H182:AA182)) | AC182: =IF(AB182="","",AB182/20*100) | AS182: =IF(COUNTBLANK(AD182:AR182)>0,"",SUM(AD182:AR182)) | AT182: =IF(AS182="","",AS182/15*100) | AU182: GENUINE GAP: Ekocorp Plc was suspended by NGX effective 1-Jul-2022 for failing to file its FY2021 audited financial statements after the 90-day cure period. No audited FY2021 AFS exists in the public record.
A183: =C183&"_"&G183 -> 37_2022 | B183: 182 | C183: ='Panel Data (Long Format)'!B183 -> 37 | D183: ='Panel Data (Long Format)'!C183 -> EKOCORP | E183: ='Panel Data (Long Format)'!D183 -> Ekocorp Plc | F183: ='Panel Data (Long Format)'!E183 -> HEALTHCARE | G183: ='Panel Data (Long Format)'!F183 -> 2022 | AB183: =IF(COUNTBLANK(H183:AA183)>0,"",SUM(H183:AA183)) | AC183: =IF(AB183="","",AB183/20*100) | AS183: =IF(COUNTBLANK(AD183:AR183)>0,"",SUM(AD183:AR183)) | AT183: =IF(AS183="","",AS183/15*100) | AU183: GENUINE GAP: Per NGX Regulation's X-Compliance Report, Ekocorp 'has not rendered audited financial statements for 2021-2024.' Company remained suspended throughout 2022; no FY2022 audited AFS was ever filed.
A184: =C184&"_"&G184 -> 37_2023 | B184: 183 | C184: ='Panel Data (Long Format)'!B184 -> 37 | D184: ='Panel Data (Long Format)'!C184 -> EKOCORP | E184: ='Panel Data (Long Format)'!D184 -> Ekocorp Plc | F184: ='Panel Data (Long Format)'!E184 -> HEALTHCARE | G184: ='Panel Data (Long Format)'!F184 -> 2023 | AB184: =IF(COUNTBLANK(H184:AA184)>0,"",SUM(H184:AA184)) | AC184: =IF(AB184="","",AB184/20*100) | AS184: =IF(COUNTBLANK(AD184:AR184)>0,"",SUM(AD184:AR184)) | AT184: =IF(AS184="","",AS184/15*100) | AU184: GENUINE GAP: Same NGX non-filing status continues; company progressed toward 'Delisting in Process' during this period. No audited FY2023 AFS filed or locatable.
A185: =C185&"_"&G185 -> 37_2024 | B185: 184 | C185: ='Panel Data (Long Format)'!B185 -> 37 | D185: ='Panel Data (Long Format)'!C185 -> EKOCORP | E185: ='Panel Data (Long Format)'!D185 -> Ekocorp Plc | F185: ='Panel Data (Long Format)'!E185 -> HEALTHCARE | G185: ='Panel Data (Long Format)'!F185 -> 2024 | AB185: =IF(COUNTBLANK(H185:AA185)>0,"",SUM(H185:AA185)) | AC185: =IF(AB185="","",AB185/20*100) | AS185: =IF(COUNTBLANK(AD185:AR185)>0,"",SUM(AD185:AR185)) | AT185: =IF(AS185="","",AS185/15*100) | AU185: GENUINE GAP: NGX confirms no audited FS rendered for 2021-2024 and no unaudited FS since Q4 2021. Delisting approval was granted March 2025 (on hold pending litigation). No FY2024 AFS exists.
A186: =C186&"_"&G186 -> 37_2025 | B186: 185 | C186: ='Panel Data (Long Format)'!B186 -> 37 | D186: ='Panel Data (Long Format)'!C186 -> EKOCORP | E186: ='Panel Data (Long Format)'!D186 -> Ekocorp Plc | F186: ='Panel Data (Long Format)'!E186 -> HEALTHCARE | G186: ='Panel Data (Long Format)'!F186 -> 2025 | AB186: =IF(COUNTBLANK(H186:AA186)>0,"",SUM(H186:AA186)) | AC186: =IF(AB186="","",AB186/20*100) | AS186: =IF(COUNTBLANK(AD186:AR186)>0,"",SUM(AD186:AR186)) | AT186: =IF(AS186="","",AS186/15*100) | AU186: GENUINE GAP: As of the 'Delisting In Process' status confirmed into 2026, Ekocorp remains a non-filer; no FY2025 audited AFS has been located or is expected given ongoing litigation freezing the delisting process.
A187: =C187&"_"&G187 -> 38_2021 | B187: 186 | C187: ='Panel Data (Long Format)'!B187 -> 38 | D187: ='Panel Data (Long Format)'!C187 -> ELLAHLAKES | E187: ='Panel Data (Long Format)'!D187 -> Ellah Lakes Plc | F187: ='Panel Data (Long Format)'!E187 -> AGRICULTURE | G187: ='Panel Data (Long Format)'!F187 -> 2021 | H187: 0 | I187: 0 | J187: 0 | K187: 0 | L187: 0 | M187: 0 | N187: 0 | O187: 0 | P187: 0 | Q187: 0 | R187: 0 | S187: 0 | T187: 0 | U187: 0 | V187: 0 | W187: 0 | X187: 0 | Y187: 0 | Z187: 0 | AA187: 0 | AB187: =IF(COUNTBLANK(H187:AA187)>0,"",SUM(H187:AA187)) -> 0 | AC187: =IF(AB187="","",AB187/20*100) -> 0 | AD187: 0 | AE187: 0 | AF187: 0 | AG187: 0 | AH187: 0 | AI187: 0 | AJ187: 0 | AK187: 0 | AL187: 0 | AM187: 0 | AN187: 0 | AO187: 0 | AP187: 0 | AQ187: 0 | AR187: 0 | AS187: =IF(COUNTBLANK(AD187:AR187)>0,"",SUM(AD187:AR187)) -> 0 | AT187: =IF(AS187="","",AS187/15*100) -> 0 | AU187: Ellah Lakes Plc FY2021 (FYE 31-Jul-2021, full glossy AR from registrar). No dedicated sustainability/ESG committee (only Remuneration and Risk committees, both generic). No GHG, climate, or ESG-target language anywhere; '2020/21 Targets & Milestones' section refers only to M&A/business targets, not sustainability metrics. Pre-ISSB period -- Adopter_Dummy correctly BLANK.
A188: =C188&"_"&G188 -> 38_2022 | B188: 187 | C188: ='Panel Data (Long Format)'!B188 -> 38 | D188: ='Panel Data (Long Format)'!C188 -> ELLAHLAKES | E188: ='Panel Data (Long Format)'!D188 -> Ellah Lakes Plc | F188: ='Panel Data (Long Format)'!E188 -> AGRICULTURE | G188: ='Panel Data (Long Format)'!F188 -> 2022 | H188: 0 | I188: 0 | J188: 0 | K188: 0 | L188: 0 | M188: 0 | N188: 0 | O188: 0 | P188: 0 | Q188: 0 | R188: 0 | S188: 0 | T188: 0 | U188: 0 | V188: 0 | W188: 0 | X188: 0 | Y188: 0 | Z188: 0 | AA188: 0 | AB188: =IF(COUNTBLANK(H188:AA188)>0,"",SUM(H188:AA188)) -> 0 | AC188: =IF(AB188="","",AB188/20*100) -> 0 | AD188: 0 | AE188: 0 | AF188: 0 | AG188: 0 | AH188: 0 | AI188: 0 | AJ188: 0 | AK188: 0 | AL188: 0 | AM188: 0 | AN188: 0 | AO188: 0 | AP188: 0 | AQ188: 0 | AR188: 0 | AS188: =IF(COUNTBLANK(AD188:AR188)>0,"",SUM(AD188:AR188)) -> 0 | AT188: =IF(AS188="","",AS188/15*100) -> 0 | AU188: GAP-FILL: ELLAHLAKES FY2022: not directly verified this session - the FY2023 Annual Report (ellahlakes.com) explicitly confirms 'The group did not make donation to any organization during the year' for FY2023 (no FY2022 comparative figure given), and contains a generic 'Corporate Social Responsibility framework' referencing UN SDGs under four themes (Employment, Education, Community Welfare, Environment) that is pure policy-intent boilerplate ('We will promote...We will also provide...') with no specific FY2022 or FY2023 activity, target, or figure - NOT credited per the anti-boilerplate rule. Scored 0/20 SDQ, 0/15 CDQ, FLAGGED as unconfirmed for FY2022 specifically.
A189: =C189&"_"&G189 -> 38_2023 | B189: 188 | C189: ='Panel Data (Long Format)'!B189 -> 38 | D189: ='Panel Data (Long Format)'!C189 -> ELLAHLAKES | E189: ='Panel Data (Long Format)'!D189 -> Ellah Lakes Plc | F189: ='Panel Data (Long Format)'!E189 -> AGRICULTURE | G189: ='Panel Data (Long Format)'!F189 -> 2023 | H189: 0 | I189: 0 | J189: 0 | K189: 0 | L189: 0 | M189: 0 | N189: 0 | O189: 0 | P189: 0 | Q189: 0 | R189: 0 | S189: 0 | T189: 0 | U189: 0 | V189: 0 | W189: 0 | X189: 0 | Y189: 0 | Z189: 0 | AA189: 0 | AB189: =IF(COUNTBLANK(H189:AA189)>0,"",SUM(H189:AA189)) -> 0 | AC189: =IF(AB189="","",AB189/20*100) -> 0 | AD189: 0 | AE189: 0 | AF189: 0 | AG189: 0 | AH189: 0 | AI189: 0 | AJ189: 0 | AK189: 0 | AL189: 0 | AM189: 0 | AN189: 0 | AO189: 0 | AP189: 0 | AQ189: 0 | AR189: 0 | AS189: =IF(COUNTBLANK(AD189:AR189)>0,"",SUM(AD189:AR189)) -> 0 | AT189: =IF(AS189="","",AS189/15*100) -> 0 | AU189: Ellah Lakes Plc FY2023 (FYE 31-Jul-2023, full glossy AR from ellahlakes.com). Board has Remuneration and Risk Management committees (general, not sustainability-specific). CSR narrative references UN SDGs under four generic themes (Employment/Education/Community/Environment) but with no risk/opportunity framing, targets, or metrics. No GHG/climate content found.
A190: =C190&"_"&G190 -> 38_2024 | B190: 189 | C190: ='Panel Data (Long Format)'!B190 -> 38 | D190: ='Panel Data (Long Format)'!C190 -> ELLAHLAKES | E190: ='Panel Data (Long Format)'!D190 -> Ellah Lakes Plc | F190: ='Panel Data (Long Format)'!E190 -> AGRICULTURE | G190: ='Panel Data (Long Format)'!F190 -> 2024 | H190: 0 | I190: 0 | J190: 0 | K190: 0 | L190: 0 | M190: 0 | N190: 0 | O190: 0 | P190: 0 | Q190: 0 | R190: 0 | S190: 0 | T190: 0 | U190: 0 | V190: 0 | W190: 0 | X190: 0 | Y190: 0 | Z190: 0 | AA190: 0 | AB190: =IF(COUNTBLANK(H190:AA190)>0,"",SUM(H190:AA190)) -> 0 | AC190: =IF(AB190="","",AB190/20*100) -> 0 | AD190: 0 | AE190: 0 | AF190: 0 | AG190: 0 | AH190: 0 | AI190: 0 | AJ190: 0 | AK190: 0 | AL190: 0 | AM190: 0 | AN190: 0 | AO190: 0 | AP190: 0 | AQ190: 0 | AR190: 0 | AS190: =IF(COUNTBLANK(AD190:AR190)>0,"",SUM(AD190:AR190)) -> 0 | AT190: =IF(AS190="","",AS190/15*100) -> 0 | AU190: Ellah Lakes Plc FY2024 (FYE 31-Jul-2024, NGX doclib filing). This is an abridged Directors'-Report-style filing (personnel, donations, dividend, shareholding) without a full corporate governance report -- no sustainability content present. LIMITATION: likely understates true disclosure somewhat if a fuller glossy AR exists for this FY, but none was locatable this session -- flagged for re-check.
A191: =C191&"_"&G191 -> 38_2025 | B191: 190 | C191: ='Panel Data (Long Format)'!B191 -> 38 | D191: ='Panel Data (Long Format)'!C191 -> ELLAHLAKES | E191: ='Panel Data (Long Format)'!D191 -> Ellah Lakes Plc | F191: ='Panel Data (Long Format)'!E191 -> AGRICULTURE | G191: ='Panel Data (Long Format)'!F191 -> 2025 | H191: 0 | I191: 0 | J191: 0 | K191: 0 | L191: 0 | M191: 0 | N191: 0 | O191: 0 | P191: 0 | Q191: 0 | R191: 0 | S191: 0 | T191: 0 | U191: 0 | V191: 0 | W191: 0 | X191: 0 | Y191: 0 | Z191: 0 | AA191: 0 | AB191: =IF(COUNTBLANK(H191:AA191)>0,"",SUM(H191:AA191)) -> 0 | AC191: =IF(AB191="","",AB191/20*100) -> 0 | AD191: 0 | AE191: 0 | AF191: 0 | AG191: 0 | AH191: 0 | AI191: 0 | AJ191: 0 | AK191: 0 | AL191: 0 | AM191: 0 | AN191: 0 | AO191: 0 | AP191: 0 | AQ191: 0 | AR191: 0 | AS191: =IF(COUNTBLANK(AD191:AR191)>0,"",SUM(AD191:AR191)) -> 0 | AT191: =IF(AS191="","",AS191/15*100) -> 0 | AU191: Ellah Lakes Plc FY2025 (FYE 31-Jul-2025, full audited FS from ellahlakes.com). Same pattern as prior years: Audit Committee and a Board Audit, Governance, Nomination and Remuneration Committee exist but no sustainability-specific mandate. Financial-risk notes (liquidity/market/credit/currency) present but no ESG/climate content anywhere. No new-standards note mentioning IFRS S1/S2 found.
A192: =C192&"_"&G192 -> 39_2021 | B192: 191 | C192: ='Panel Data (Long Format)'!B192 -> 39 | D192: ='Panel Data (Long Format)'!C192 -> ENAMELWA | E192: ='Panel Data (Long Format)'!D192 -> Nigerian Enamelware Plc | F192: ='Panel Data (Long Format)'!E192 -> CONSUMER GOODS | G192: ='Panel Data (Long Format)'!F192 -> 2021 | H192: 0 | I192: 0 | J192: 0 | K192: 0 | L192: 0 | M192: 0 | N192: 0 | O192: 0 | P192: 0 | Q192: 0 | R192: 0 | S192: 0 | T192: 0 | U192: 0 | V192: 0 | W192: 0 | X192: 0 | Y192: 0 | Z192: 0 | AA192: 0 | AB192: =IF(COUNTBLANK(H192:AA192)>0,"",SUM(H192:AA192)) -> 0 | AC192: =IF(AB192="","",AB192/20*100) -> 0 | AD192: 0 | AE192: 0 | AF192: 0 | AG192: 0 | AH192: 0 | AI192: 0 | AJ192: 0 | AK192: 0 | AL192: 0 | AM192: 0 | AN192: 0 | AO192: 0 | AP192: 0 | AQ192: 0 | AR192: 0 | AS192: =IF(COUNTBLANK(AD192:AR192)>0,"",SUM(AD192:AR192)) -> 0 | AT192: =IF(AS192="","",AS192/15*100) -> 0 | AU192: Nigerian Enamelware Plc FY2021 (FYE 30-Apr-2021, NGX doclib AFS). Small-cap filing: only a Statutory Audit Committee is disclosed; risk notes limited to standard financial risk categories (capital, interest rate, credit, liquidity). No sustainability/ESG/climate language anywhere in the document.
A193: =C193&"_"&G193 -> 39_2022 | B193: 192 | C193: ='Panel Data (Long Format)'!B193 -> 39 | D193: ='Panel Data (Long Format)'!C193 -> ENAMELWA | E193: ='Panel Data (Long Format)'!D193 -> Nigerian Enamelware Plc | F193: ='Panel Data (Long Format)'!E193 -> CONSUMER GOODS | G193: ='Panel Data (Long Format)'!F193 -> 2022 | H193: 0 | I193: 0 | J193: 0 | K193: 0 | L193: 0 | M193: 0 | N193: 0 | O193: 0 | P193: 0 | Q193: 0 | R193: 0 | S193: 0 | T193: 0 | U193: 0 | V193: 0 | W193: 0 | X193: 0 | Y193: 0 | Z193: 0 | AA193: 0 | AB193: =IF(COUNTBLANK(H193:AA193)>0,"",SUM(H193:AA193)) -> 0 | AC193: =IF(AB193="","",AB193/20*100) -> 0 | AD193: 0 | AE193: 0 | AF193: 0 | AG193: 0 | AH193: 0 | AI193: 0 | AJ193: 0 | AK193: 0 | AL193: 0 | AM193: 0 | AN193: 0 | AO193: 0 | AP193: 0 | AQ193: 0 | AR193: 0 | AS193: =IF(COUNTBLANK(AD193:AR193)>0,"",SUM(AD193:AR193)) -> 0 | AT193: =IF(AS193="","",AS193/15*100) -> 0 | AU193: Nigerian Enamelware Plc FY2022 (FYE 30-Apr-2022, registrar-hosted AR). Identical pattern to FY2021 -- Statutory Audit Committee + generic financial-risk notes only; no ESG/sustainability disclosure of any kind found.
...

Sheet Firm Master
A1: Firm_ID | B1: Ticker | C1: Company Name | D1: Sector | E1: Year_Incorporation | F1: Date_Listed_NGX | G1: Auditor | H1: Big4_Auditor | I1: NGX_Compliance_Status (CSI) | J1: Compliance_Notes (as of 20-Feb-2026 X-Compliance Report) | K1: Notes
A2: 1 | B2: ABBEYBANK | C2: Abbey Mortgage Bank Plc | D2: FINANCIAL SERVICES | E2: 1991 | F2: 21-Oct-2008 | G2: PricewaterhouseCoopers | H2: 1 | K2: Abbey Mortgage Bank Plc - primary mortgage bank, Financial Services sector. Incorporated 1991, NGX-listed 21-Oct-2008. Auditor PricewaterhouseCoopers (Big4) throughout the study window. FY2025 figures are marked UNAUDITED/provisional in the source filing pending the final Annual Report - flagged in the Panel Data Notes for that year. Strong asset growth across FY2021-2025 (N34.5bn to N165.6bn Total Assets).
A3: 2 | B3: ABCTRANS | C3: ABC Transport Plc | D3: SERVICES | E3: 1993 | F3: 20-Dec-2006 | G3: Forvis Mazars | H3: 0 | K3: ABC Transport Plc - road transport/logistics operator, Services sector. Incorporated 1993, NGX-listed 20-Dec-2006. Auditor Forvis Mazars (non-Big4). Shares outstanding rose from 1.6577bn to 2.3926bn via a rights issue completed during 2022 - the FY2021 and FY2022 figures use the correct period-specific share count per the company's own disclosure, not a blended average.
A4: 3 | B4: ACADEMY | C4: Academy Press Plc | D4: SERVICES | E4: 1964 | F4: 15-Jun-1995 | G4: Ernst & Young | H4: 1 | K4: Academy Press Plc - printing/publishing company, Services sector. Incorporated 1964, NGX-listed 15-Jun-1995. Auditor Ernst & Young (Big4). FISCAL YEAR END IS 31-MARCH, not 31-December like most firms in this sample - Study Year N maps to FYE 31-Mar-N, and Share_Price_YearEnd uses the calendar 31-Dec-N proxy (same numbered year). FY2025 (FYE 31-Mar-2025) is a documented DATA GAP: the only located 'audited' figures came from an unaudited interim that materially disagreed with a secondary summary of the real audited accounts, so all FY2025 financials were left blank rather than risk using unreliable figures - see the FY2025 Panel Data Notes.
A5: 4 | B5: ACCESSCORP | C5: Access Holdings Plc | D5: FINANCIAL SERVICES | E5: 2021 | F5: 1998 (predecessor Access Bank Plc); Access Holdings Plc from 2022 restructuring | G5: KPMG Professional Services | H5: 1 | K5: Access Holdings Plc - Tier-1 banking group, Financial Services sector. The FY2021 entity was legally Access Bank Plc; a March-2022 Scheme of Arrangement created the non-operating holding company Access Holdings Plc as the new listed parent, continuing under the same NGX ticker (ACCESSCORP) - treated as one continuous listing for this study. Auditor KPMG Professional Services (Big4). Shares outstanding rose from 35.545bn to 53.318bn via a rights issue completed July 2024. FY2025 Total Assets/Total Liabilities are DERIVED from a Q1'26 percentage-change disclosure rather than a primary financial-statement line - lower confidence than other years, flagged in the FY2025 Panel Data Notes.
A6: 5 | B6: AFRINSURE | C6: African Alliance Insurance Plc | D6: FINANCIAL SERVICES | E6: 1960 | F6: 17-Sep-2009 | G6: Deloitte & Touche | H6: 1 | I6: MRF | J6: Missing audited FS 2023-2024 | K6: African Alliance Insurance Plc - life/general insurer, Financial Services sector. Incorporated 1960, NGX-listed 17-Sep-2009. Auditor Deloitte & Touche (Big4). NGX Compliance Status: MRF (Missed Regulatory Filing) - the company failed to render audited financial statements for FY2023-2024. Share price has been frozen at N0.20 since the last recorded trade around 30-Jun-2022 (over 3 years untraded), and NAICOM dissolved the company's board/management in October 2024 over solvency concerns (negative equity). A firm under regulatory takeover is not making a normal voluntary sustainability-disclosure choice, so FY2022 onward is treated with reduced weight for the disclosure-quality analysis even though the frozen price is retained as a real (if stale) market data point.
A7: 6 | B7: AFRIPRUD | C7: Africa Prudential Plc | D7: FINANCIAL SERVICES | E7: 2006 | F7: 17-Jan-2013 | G7: Ernst & Young | H7: 1 | K7: Africa Prudential Plc - share registration/fintech services, Financial Services sector. Incorporated 2006, NGX-listed 17-Jan-2013. Auditor Ernst & Young (Big4). Shares outstanding doubled from 2.0bn to 4.0bn via a 1-for-1 bonus share issue completed during 2025.
A8: 7 | B8: AFROMEDIA | C8: Afromedia Plc | D8: SERVICES | E8: 1959 | F8: 2-Jul-2008 (converted to public) | G8: SIAO Partners | H8: 0 | I8: MRF | J8: Missing audited FS 2022-2024 | K8: Afromedia Plc - outdoor advertising/media company, Services sector. Incorporated 1959, converted to a public company and NGX-listed 2-Jul-2008. Auditor SIAO Partners (non-Big4). NGX Compliance Status: MRF - official X-Compliance Report confirms non-rendition of audited financial statements for FY2022-2024, with unaudited figures only through FY2025 Q4. FY2021 is AUDITED (going concern note: negative equity of -N3.22bn already present that year); FY2022 uses UNAUDITED management-report figures; FY2023-2025 are EXCLUDED from the panel entirely (all fields blank) per the confirmed MRF filing gap.
A9: 8 | B9: AIICO | C9: AIICO Insurance Plc | D9: FINANCIAL SERVICES | E9: 1970 | F9: 3-Dec-1990 | G9: Ernst & Young | H9: 1 | K9: AIICO Insurance Plc - composite (life + general) insurer, Financial Services sector. Incorporated 1970, NGX-listed 3-Dec-1990. Auditor Ernst & Young (Big4). Clean, fully audited data series across all 5 study years with strong asset growth (N222.4bn to N579.7bn Total Assets) and full share-price coverage.
A10: 9 | B10: AIRTELAFRI | C10: Airtel Africa Plc | D10: ICT | E10: 2010 | F10: Jun-2019 (secondary listing; primary listing LSE) | G10: Deloitte LLP | H10: 1 | K10: Airtel Africa Plc - pan-African telecoms group, ICT sector. Incorporated 2010 (UK holding company for the African Airtel operations), primary listing on the London Stock Exchange with a secondary NGX listing from Jun-2019. Auditor Deloitte LLP (Big4, UK-appointed). SPECIAL CASE: reports in USD with a 31-March fiscal year end (unlike every other firm in this sample); Total_Assets/Total_Liabilities/Net_Income are USD-to-NGN converted using the best available year-specific exchange rate, with LOW-MEDIUM confidence flagged for FY2023-2024 specifically because the Naira's June-2023 FX unification devaluation means a December reference rate is a poor proxy for a March fiscal year-end in those two years - see the per-year Panel Data Notes. Share_Price_YearEnd, by contrast, is the NGX-quoted NGN price directly (not a currency conversion) - Airtel Africa trades at a high nominal Naira price on NGX (hundreds to low thousands of Naira per share) because it is a large-cap cross-listed stock, not a typical small-denomination NGX equity.
A11: 10 | B11: ALEX | C11: Aluminium Extrusion Industries Plc | D11: NATURAL RESOURCES | E11: 1982 | F11: 3-Oct-1986 | G11: Madu, Onyekwena & Co | H11: 0 | I11: BMF | J11: Free-float deficient (16.61%%, due Aug-2027) + missed 2025 Q4 quarterly filing | K11: Aluminium Extrusion Industries Plc - aluminium profile manufacturer, Natural Resources sector. Incorporated 1982, NGX-listed 3-Oct-1986. Auditor Madu, Onyekwena & Co (non-Big4). NGX Compliance Status: BMF (Below Listing Standard + Missed Regulatory Filing) - free-float deficient (16.61%, cure period due Aug-2027) and missed the 2025 Q4 quarterly filing. Data quality is genuinely patchy for this small-cap firm independent of the compliance flag: FY2022 Total Assets/Liabilities were blocked by a scanned, non-machine-readable filing; FY2023 similarly unresolved for the balance sheet; FY2024-2025 rely partly on interim rather than full-year audited figures - see the per-year Panel Data Notes for the specific caveats. | EXCLUDED FROM 'Final Sample' (stricter, 17-Aug-2026), ALL 5 YEARS: Condition 5 (Section 3.6): NGX compliance status 'BMF' not among retained exceptions (BLS/MRF/RST).
A12: 11 | B12: ARADEL | C12: Aradel Holdings Plc | D12: OIL AND GAS | E12: 1992 | F12: 14-Oct-2024 (previously traded on NASD OTC from Aug-2013) | G12: Deloitte & Touche (FY2025); KPMG from FY2026 | H12: 1 | K12: Aradel Holdings Plc (formerly Niger Delta Exploration & Production Plc, rebranded May-2023) - independent oil & gas exploration/production company, Oil and Gas sector. Incorporated 1992; traded on the NASD OTC exchange from Aug-2013 but was NOT NGX-listed until 14-Oct-2024. FY2021-2023 are EXCLUDED BY DESIGN (all fields blank) because no NGX market value existed for those years - including them would mean fabricating a Tobin's Q input. Auditor Deloitte & Touche (Big4) for FY2025, moving to KPMG from FY2026 (post-study-window, informational only). FY2025 Total Assets grew ~5.7x due to a major step-acquisition (ND Western Ltd + Renaissance Africa Energy) consolidated as subsidiaries on 31-Dec-2025 - a genuine structural break, not a data error.
A13: 12 | B13: AUSTINLAZ | C13: Austin Laz & Company Plc | D13: INDUSTRIAL GOODS | E13: 1982 | F13: 2012 (Growth Board) | G13: David Ugiagbe & Co. | H13: 0 | I13: RST | J13: Restructuring status (2yr) - but also listed as an Early Filer for 2025 AFS, so likely not delinquent | K13: Austin Laz & Company Plc - building materials trading/distribution, Industrial Goods sector. Incorporated 1982, NGX-listed 2012 (Growth Board). Auditor David Ugiagbe & Co. (non-Big4). NGX Compliance Status: RST (Restructuring, 2-year status) but the company is also an Early Filer for its 2025 Annual Financial Statements, so the restructuring flag likely does not indicate a genuine filing delinquency. FY2025 financials are Q3-2025 INTERIM ONLY (the company reported zero revenue in 2025 due to an ongoing 'retooling' operational halt) - flagged LOW-MEDIUM confidence in the Panel Data Notes.
A14: 13 | B14: AVAIF | C14: AVA Infrastructure Fund | D14: CONSTRUCTION/REAL ESTATE | F14: 10-May-2024 | G14: N/A - not an operating company | I14: EXCLUDED | J14: Not an operating company - closed-end infrastructure investment fund (unitholders, NAV-based, not conventional equity structure). NGX-listed only from 10-May-2024. Tobin's Q not conceptually applicable to a fund. Excluded from sample entirely, not a CSI-based exclusion. | K14: AVA Infrastructure Fund - closed-end infrastructure investment fund (unitholders, NAV-based reporting), Construction/Real Estate sector classification on NGX. NGX-listed only from 10-May-2024. EXCLUDED FROM THE SAMPLE ENTIRELY: this is not an operating company and does not have the disclosure architecture that IFRS S1/S2's four pillars are built to assess; Tobin's Q is not conceptually applicable to a fund structure. This is a structural exclusion, not a CSI/compliance-based one - all Panel Data fields are blank by design for every study year. | EXCLUDED FROM 'Final Sample' (stricter, 17-Aug-2026), ALL 5 YEARS: Condition 5 (Section 3.6): closed-end REIT/investment fund. Condition 5 (Section 3.6): NGX compliance status 'EXCLUDED' not among retained exceptions (BLS/MRF/RST).
A15: 14 | B15: BAPLC | C15: Briclinks Africa Plc (trading as Btel) | D15: ICT | E15: 2015 | F15: 5-Feb-2021 | G15: Emmanuel Osuagwu & Co. | H15: 0 | K15: Briclinks Africa Plc, trading as Btel (formerly recorded in early research as British American Tobacco Nigeria before this was corrected to the true identity) - internet service provider, ICT sector. Incorporated 2015, NGX-listed 5-Feb-2021 (so FY2021 is effectively its IPO year). Auditor Emmanuel Osuagwu & Co. (non-Big4). Approximately 96% of the company's liabilities consist of a single Director's Loan Account rather than conventional third-party debt - relevant context for interpreting the Leverage ratio. Share price has been flat at N6.25 across the entire study window per stockanalysis.com, consistent with a thinly-traded micro-cap rather than a data error. FY2025 Total Assets is a documented gap (genuine 31-Dec-2025 figure not yet located; the FY2024 figure itself is an approximation from a 30-Jun-2024 interim snapshot) - see the per-year Panel Data Notes.
A16: 15 | B16: BERGER | C16: Berger Paints Nigeria Plc | D16: INDUSTRIAL GOODS | E16: 1959 | F16: 14-Mar-1974 | G16: Pannell Kerr Forster | H16: 0 | K16: Berger Paints Nigeria Plc - paints/coatings manufacturer, Industrial Goods sector. AUDITOR TRANSITION: KPMG Professional Services (Big4) audited FY2021-2023; changed to Pannell Kerr Forster (non-Big4) from FY2024 onward. Per the workbook's auditor-transition convention, this Firm Master field holds the current/most-recent auditor (PKF); the FY2021-2023 KPMG years are documented per-year in the Panel Data Notes and correctly reflected in the per-row Big4_Auditor column (1,1,1,0,0).
A17: 16 | B17: BETAGLAS | C17: Beta Glass Plc | D17: INDUSTRIAL GOODS | E17: 1974 | F17: 2-Jul-1986 | G17: Ernst & Young | H17: 1 | K17: Beta Glass Plc - glass packaging manufacturer, Industrial Goods sector. Incorporated 1974, NGX-listed 2-Jul-1986. Auditor Ernst & Young (Big4). Shares outstanding constant at 599,970,000 across the full study window (corrected this session - see the workbook's consistency-pass README entry for the prior corrupted figures). Total Assets/Liabilities were UNRESOLVED for FY2021-2023 despite confirmed Total Equity and Net Income figures - a reproducible Statement of Financial Position extraction barrier across multiple sources/attempts, documented per-year in the Panel Data Notes. Majority shareholding was sold to Helios Investment Partners in Feb-2026 (a subsequent event, outside the study window).
A18: 17 | B18: BUACEMENT | C18: BUA Cement Plc | D18: INDUSTRIAL GOODS | E18: 2014 | F18: 9-Jan-2020 | G18: PricewaterhouseCoopers | H18: 1 | K18: BUA Cement Plc - cement manufacturer, Industrial Goods sector. Incorporated 2014, NGX-listed 9-Jan-2020. Auditor PricewaterhouseCoopers (Big4). Shares outstanding constant at 33,864,354,060 across the full study window (corrected this session - the FY2022-2025 figures on file previously were corrupted, off by two to three orders of magnitude; see the workbook's consistency-pass README entry). FY2021 Total Assets/Liabilities remain an UNRESOLVED data gap (Total Equity and the IFRS S1/S2 adoption status ARE confirmed for that year) - the Statement of Financial Position page did not extract despite multiple attempts.
A19: 18 | B19: BUAFOODS | C19: BUA Foods Plc | D19: CONSUMER GOODS | E19: 2005 | F19: 5-Jan-2022 | G19: PricewaterhouseCoopers | H19: 1 | K19: BUA Foods Plc - integrated food products manufacturer (sugar, flour, pasta, edible oils), Consumer Goods sector. Incorporated 2005, NGX-listed 5-Jan-2022. Auditor PricewaterhouseCoopers (Big4). Shares outstanding constant at 18,000,000,000 across the full study window (corrected this session - the figures on file previously were corrupted, off by roughly 35x to 260x; see the workbook's consistency-pass README entry). FY2021 Share_Price_YearEnd is a genuine, permanent DATA GAP rather than an unresolved-sourcing issue: the company was not NGX-listed until 6-Jan-2022, so no 31-Dec-2021 market price exists - Total_Assets/Total_Liabilities/Net_Income for FY2021 are still populated from the pre-IPO audited accounts, only the market-price-dependent fields (Share_Price_YearEnd, Market_Value_Equity, Tobin's Q) are left blank for that one year.
A20: 19 | B20: CADBURY | C20: Cadbury Nigeria Plc | D20: CONSUMER GOODS | E20: 1965 | F20: 1976 | G20: PricewaterhouseCoopers (stepping down after FY2026 - 10yr CAMA limit) | H20: 1 | K20: Cadbury Nigeria Plc - confectionery/beverages manufacturer, Consumer Goods sector (majority-owned by Mondelez International). Incorporated 1965, NGX-listed 1976. Auditor PricewaterhouseCoopers (Big4) - stepping down after FY2026 per the 10-year CAMA mandatory-rotation limit. Shares_Outstanding and Share_Price_YearEnd were CORRUPTED/SWAPPED on file prior to this session's consistency pass (two years even carried impossible negative Shares_Outstanding) - corrected using the company's own balance-sheet share count (1,878,000,000 for FY2021-2023; 2,280,000,000 for FY2024-2025) and Share_Price_YearEnd recomputed from Dec-31 market cap / shares. Total_Assets/Total_Liabilities/Net_Income were already correct and untouched by the correction. FY2022 figures were RESTATED per a Note 32 correction to the 1-Jan-2023 opening balances.
A21: 20 | B21: CAP | C21: Chemical and Allied Products Plc | D21: INDUSTRIAL GOODS | E21: 1965 | F21: 24-May-1978 | G21: KPMG Professional Services | H21: 1 | K21: Chemical and Allied Products Plc (CAP) - paints/coatings manufacturer, Industrial Goods sector. Incorporated 1965, NGX-listed 24-May-1978. Auditor KPMG Professional Services (Big4). Absorbed Portland Paints and Products Nigeria Plc via merger effective 1-Jul-2021 (relevant to the FY2021 step-change in scale). Shares_Outstanding and Share_Price_YearEnd were CORRUPTED/SWAPPED on file prior to this session's consistency pass (the price column held a shares-like figure ~10-figure number, and the shares column held small unrelated values that don't reconcile to any real per-share price) - corrected using the company's own balance-sheet share count (788,260,000 for FY2021; 814,747,500 for FY2022-2025, unchanged since a 2022 scrip dividend) and Share_Price_YearEnd recomputed from Dec-31 market cap / shares. Subsidiary of UAC of Nigeria Plc (57.85% holding, also in this sample) - a related-party link relevant to Ownership Concentration.
A22: 21 | B22: CAVERTON | C22: Caverton Offshore Support Group Plc | D22: SERVICES | E22: 2008 | F22: 4-Jul-2008 (commenced business 1-Jul-2008) | G22: PricewaterhouseCoopers | H22: 1 | K22: Caverton Offshore Support Group Plc - marine/aviation offshore logistics support, Services sector. Incorporated 2008, NGX-listed 4-Jul-2008 (commenced business 1-Jul-2008). Auditor PricewaterhouseCoopers (Big4). Shares outstanding constant at 3,350,509,750 across the full study window - confirmed against the company's own balance-sheet filings, no correction needed.
A23: 22 | B23: CHAMPION | C23: Champion Breweries Plc | D23: CONSUMER GOODS | E23: 1974 | F23: 1997 | G23: KPMG (through 2021); Deloitte & Touche (2022 AGM onward) | H23: 1 | I23: BLS | J23: Free-float deficient only (16.98%%, due Oct-2026) - no audited FS filing gap | K23: Champion Breweries Plc - beer/malt beverage brewer, Consumer Goods sector (majority-owned by Heineken since a 2020-2021 acquisition). Incorporated 1974, NGX-listed 1997. Auditor KPMG (through the 2021 audit cycle), Deloitte & Touche from the 2022 AGM onward. NGX Compliance Status: BLS (Below Listing Standard) - free-float deficient only (16.98%, cure period due Oct-2026), NOT an audited-filing gap, so the underlying financial data is unaffected. Shares outstanding rose from 7.829bn to 8.948bn via a corporate action completed during 2024.
A24: 23 | B24: CHAMS | C24: Chams Holding Company Plc | D24: ICT | E24: 1985 | F24: 8-Sep-2008 | G24: PKF Professional Services | H24: 0 | K24: Chams Holding Company Plc - ICT/identity-management and payments technology group, ICT sector. Incorporated 1985, NGX-listed 8-Sep-2008. Auditor PKF Professional Services (non-Big4). Shares outstanding roughly doubled from 4.696bn to 9.0bn via a corporate action completed during 2025. FY2021-2022 share prices were flat at N0.2193, consistent with a thinly-traded stock in that period rather than a data error.
A25: 24 | B25: CHELLARAM | C25: Chellarams Plc | D25: INDUSTRIAL GOODS | E25: 1947 | F25: 29-Nov-1974 | G25: BDO Professional Services (2021-2023); PKF Professional Services (by FY2025) | H25: 0 | K25: Chellarams Plc - diversified trading/distribution conglomerate (industrial products, FMCG distribution), Industrial Goods sector. Incorporated 1947, NGX-listed 29-Nov-1974. Auditor BDO Professional Services (2021-2023), transitioning to PKF Professional Services by FY2025 (both non-Big4, so the Big4_Auditor=0 coding is unaffected by the transition). Shares outstanding constant at 722,925,000 across the full study window. Note: the company's own fiscal year runs April-March per some source pages, but the market-cap history and this workbook both use standard calendar year-end reference points.
A26: 25 | B26: CILEASING | C26: C & I Leasing Plc | D26: SERVICES | E26: 1990 | F26: Dec-1997 | G26: Ernst & Young | H26: 1 | K26: C & I Leasing Plc - equipment/fleet leasing and outsourced logistics services, Services sector. Incorporated 1990, NGX-listed Dec-1997. Auditor Ernst & Young (Big4). SHARES OUTSTANDING CORRECTED this session: the figure previously on file (781,646,167, constant) was stale/inconsistent with the company's own Book-Value-Per-Share disclosures and its live market quote - replaced with 1,303,000,000 for FY2021-2023 and 2,949,000,000 for FY2024-2025 (a real dilution event, not a data-entry error), both cross-checked via Total Equity / BVPS reconciliation. See the workbook's consistency-pass README entry.
A27: 26 | B27: CMFC | C27: Critical Minerals Financing Corp Plc (formerly Deap Capital Management & Trust Plc) | D27: FINANCIAL SERVICES | F27: 17-Dec-2007 (as Deap Capital Management & Trust Plc) | G27: N/A - excluded, SEC Interim Management Team in place | I27: DWL | J27: EXCLUDED - Critical Minerals Financing Corp Plc, formerly Deap Capital Management & Trust Plc. SEC intervened, set up Interim Management Team per official X-Compliance Report. | K27: Critical Minerals Financing Corp Plc (formerly Deap Capital Management & Trust Plc) - EXCLUDED from the sample. SEC intervened and installed an Interim Management Team, per the official NGX X-Compliance Report (CSI: DWL - Delisting Watch-list). All Panel Data fields are blank by design for every study year; this is a governance-intervention exclusion, not a voluntary-disclosure data point that belongs in the analysis. | EXCLUDED FROM 'Final Sample' (stricter, 17-Aug-2026), ALL 5 YEARS: Condition 5 (Section 3.6): NGX compliance status 'DWL' not among retained exceptions (BLS/MRF/RST).
A28: 27 | B28: CNIF | C28: Coronation Infrastructure Fund | D28: INDUSTRIAL GOODS | F28: 25-Aug-2025 | G28: N/A - not an operating company | I28: EXCLUDED | J28: Not an operating company - Coronation Infrastructure Fund, closed-end fund (units not shares). Excluded, same logic as AVAIF. | K28: Coronation Infrastructure Fund - EXCLUDED from the sample. A closed-end infrastructure fund (units, not conventional equity shares; NAV-based reporting), NGX-listed only from 25-Aug-2025 - same exclusion logic as AVA Infrastructure Fund (row 14): not an operating company, IFRS S1/S2's four-pillar disclosure architecture does not meaningfully apply, and Tobin's Q is not conceptually valid for a fund structure. All Panel Data fields are blank by design for every study year. | EXCLUDED FROM 'Final Sample' (stricter, 17-Aug-2026), ALL 5 YEARS: Condition 5 (Section 3.6): closed-end REIT/investment fund. Condition 5 (Section 3.6): NGX compliance status 'EXCLUDED' not among retained exceptions (BLS/MRF/RST).
A29: 28 | B29: CONHALLPLC | C29: Consolidated Hallmark Holdings Plc (formerly Consolidated Hallmark Insurance Plc) | D29: FINANCIAL SERVICES | E29: 1991 | F29: 1997 | G29: KPMG Professional Services | H29: 1 | K29: Consolidated Hallmark Holdings Plc (formerly Consolidated Hallmark Insurance Plc, renamed following a holding-company restructuring) - composite insurer, Financial Services sector. Incorporated 1991, NGX-listed 1997. Auditor KPMG Professional Services (Big4). Shares_Outstanding was completely missing on file prior to this session - filled in at 10,840,000,000 (constant across the full study window), cross-checked via the company's own Book-Value-Per-Share disclosures and its live market quote.
A30: 29 | B30: CONOIL | C30: Conoil Plc | D30: OIL AND GAS | E30: 1960 | F30: 1989 (year only, exact date unconfirmed) | G30: Nexia Agbo Abel & Co | H30: 0 | K30: Conoil Plc - petroleum products marketing/distribution, Oil and Gas sector (formerly the Nigerian operating arm of the Chevron/Texaco downstream business before a 1993 Nigerian ownership transition led by Mike Adenuga). Incorporated 1960. Auditor Nexia Agbo Abel & Co (non-Big4). Date_Listed_NGX filled this session as 1989 (year-only, LOW-MEDIUM confidence - multiple independent sources confirm 1989 as the year the company was registered with the then-Nigerian Stock Exchange as a public company, but no source surfaced an exact day/month). Shares outstanding constant at 693,952,117 across the full study window - confirmed against the company's own balance-sheet filings.
A31: 30 | B31: CORNERST | C31: Cornerstone Insurance Plc | D31: FINANCIAL SERVICES | E31: 1991 | F31: 1997 (year only, exact date unconfirmed) | G31: KPMG Professional Services (through 2023); Deloitte (by FY2025) | H31: 1 | K31: Cornerstone Insurance Plc - composite insurer, Financial Services sector. Incorporated 26-Jul-1991 as a private limited company, converted to a public limited company and NGX-listed in 1997 per the company's own corporate history page (multiple independent sources corroborate 1997; no exact day/month confirmed - MEDIUM confidence). Date_Listed_NGX CORRECTED this session: the value previously on file, 1-Jan-1970, was a classic software null-date placeholder bug, not a real value. Auditor KPMG Professional Services (through the FY2023 audit cycle), Deloitte by FY2025. Shares outstanding constant at 18,166,392,725 across the full study window (a fetched balance-sheet cross-check came in about 0.7% lower at ~18,039M-18,032M, immaterial to two decimal places on the computed price - kept the on-file figure).
A32: 31 | B32: CUSTODIAN | C32: Custodian Investment Plc | D32: CONGLOMERATES | E32: 1991 | F32: 29-Sep-2006 | G32: Deloitte | H32: 1 | K32: Incorporated 22-Aug-1991 as Accident and General Insurance Company Limited; became a public limited company 29-Sep-2006. Auditor: Deloitte (Messrs Deloitte), confirmed Big4.
A33: 32 | B33: CUTIX | C33: Cutix Plc | D33: INDUSTRIAL GOODS | E33: 1982 | G33: Ngozi Monica Okonkwo & Co. | H33: 0 | K33: Incorporated 4-Nov-1982. First company East of the Niger to be listed on the Nigerian Exchange. Auditor Ngozi Monica Okonkwo & Co. (appointed Nov-2020) - NOT a Big4 firm. FYE is 30 April (not 31 December) - see Panel Data notes for year-mapping convention. Received an NGX caution letter 28-Feb-2025 for insider dealing during a closed period (governance flag, not a filing-compliance issue - does not warrant exclusion).
A34: 33 | B34: CWG | C34: CWG Plc | D34: ICT | E34: 2005 | F34: 15-Nov-2013 | G34: PKF Professional Services | H34: 0 | K34: Incorporated 1-Feb-2005 as a private limited liability company (Computer Warehouse Group); became public and listed on NGX 15-Nov-2013. Auditor not confirmed this session. Auditor confirmed: PKF Professional Services (not Big4).
A35: 34 | B35: DAARCOMM | C35: DAAR Communications Plc | D35: SERVICES | E35: 1988 | F35: 2008 (became public 23-Apr-2007) | G35: Baker Tilly Nigeria | H35: 0 | I35: MRF | J35: Missed 2025 Q4 quarterly filing only - annual audited data likely unaffected | K35: Incorporated as a limited liability company 31-Aug-1988; converted to public limited company 23-Apr-2007; listed on NGX in 2008. Auditor confirmed: Baker Tilly Nigeria (not Big4).
A36: 35 | B36: DANGCEM | C36: Dangote Cement Plc | D36: INDUSTRIAL GOODS | E36: 1992 | F36: 26-Oct-2010 | G36: KPMG Professional Services | H36: 1 | K36: Incorporated as a public limited company 4-Nov-1992; listed on NGX 26-Oct-2010. Auditor KPMG Professional Services (as of 2024), Big4 confirmed.
A37: 36 | B37: DANGSUGAR | C37: Dangote Sugar Refinery Plc | D37: CONSUMER GOODS | E37: 2006 | F37: 8-Mar-2007 | G37: PricewaterhouseCoopers | H37: 1 | K37: Commenced operation 1-Jan-2006; listed on NGX 8-Mar-2007. Auditor PricewaterhouseCoopers, Big4 confirmed.
A38: 37 | B38: EKOCORP | C38: Ekocorp Plc | D38: HEALTHCARE | H38: 0 | I38: MRF | J38: Confirmed missing audited financials for part of the 2021-2025 window per official NGX RegCo X-Compliance Report (20-Feb-2026). | K38: RE-VERIFIED this session per user request to close the gap (unaudited financials permitted) - EXCLUSION CONFIRMED, not just carried over. EkoCorp Plc was suspended from NGX trading on 1-July-2022 for failing to file its FY2021 audited financial statements after the standard 90-day cure period; last trading day was 9-June-2022 at N5.79/share. The company has NOT filed ANY audited or unaudited annual financial statements for FY2021 through FY2024 since then - confirmed via WebSearch of NGX compliance reporting. It is currently in 'Delisting In Process (DIP)' status (delisting approved March 2025, on hold pending litigation as of the source consulted). The only unaudited filing found on NGX doclib for the study window is a Q2/half-year 2021 report (doc 33798, filed before the suspension) - but its Statement of Financial Position and Results-at-a-Glance pages are embedded as non-extractable scanned images in the PDF (a recurring 'SFP extraction barrier' seen elsewhere in this project); repeated fetch attempts returned only the accounting-policy boilerplate text, not the actual figures. Even if those H1 2021 figures were extracted, they would be a half-year, not full-year, data point, and would need annualising or flagging as partial-year. Separately, because trading has been suspended since June 2022, there is no NGX market price for FY2022-2025, meaning Market_Value_Equity and Tobin's Q could not be computed for those years even with balance-sheet data in hand. RECOMMENDATION: keep EKOCORP excluded from the panel - this is a genuine data-availability dead end (company stopped filing, not just a case of the aggregator lacking coverage), not a sourcing gap that a different source could close. If the researcher wants to pursue further, the only remaining option is a manual/OCR read of the scanned H1 2021 PDF tables, which would still only yield a half-year, unaudited, sub-full-year data point. | EXCLUDED FROM 'Final Sample' (stricter, 17-Aug-2026), ALL 5 YEARS: Condition 4 (Section 3.6): no firm-year in the FY2021-2025 window has usable financial/disclosure data (comprehensive data gap).
A39: 38 | B39: ELLAHLAKES | C39: Ellah Lakes Plc | D39: AGRICULTURE | E39: 1980 | F39: 16-Jun-1992 (converted to Plc; incorporated 22-Aug-1980) | G39: Olabode Akande & Co. | H39: 0 | K39: Incorporated 22-Aug-1980; converted to a public limited company 16-Jun-1992. Agricultural producer (palm oil, cassava, soybean, maize, rice plantations). Auditor Olabode Akande & Co. (Chartered Accountants), NOT Big4. FYE changed from 31-July to 31-December during 2025 (17-month transition period reported) - see Panel Data notes. Loss-making every year in the study window; heavy share dilution (1.79bn to 3.86bn shares between FY2022 and FY2025) alongside a large recent public offer (18.8bn new shares at N12.50, announced 2026, outside the study window) - flag for methodology chapter if relevant to control variable interpretation.
A40: 39 | B40: ENAMELWA | C40: Nigerian Enamelware Plc | D40: CONSUMER GOODS | E40: 1960 | F40: 28-Dec-1979 (went public); renamed to Nigerian Enamelware Plc 6-Jun-1991 | G40: OOP and Partners (Chartered Accountants) | H40: 0 | K40: Incorporated 21-May-1960 as a limited liability company; went public 28-Dec-1979 (Indigenisation Decree 1977 compliance); adopted current name 'Nigerian Enamelware Plc' 6-Jun-1991. Consumer goods manufacturer (enamelware/kitchenware). FYE is 30 April (1-May to 30-Apr), same non-standard-FYE convention as CUTIX/ENAMELWA-family firms - FYE-labelled year mapped directly to study Year column. Auditor: OOP and Partners (Chartered Accountants), NOT Big4. IMPORTANT DATA QUALITY FLAG: firm moved into negative shareholders' equity from FY2024 onward (per stockanalysis.com balance sheet: equity -N744m FY2024, -N729m FY2025, -N773m FY2026), driven by large negative retained earnings after a ~N2.6bn operating loss in FY2024. This is a real going-concern-type financial condition, not a data error - flag for methodology chapter alongside similar DAARCOMM/DANGSUGAR negative-equity cases. Total Assets/Liabilities/Net Income/Shares/Price sourced from stockanalysis.com (S&P Global Market Intelligence), MEDIUM-HIGH confidence. Study Year 2021 (FYE Apr-2021) is a GAP - stockanalysis.com data starts at FY2022 (Apr-2022), same pattern as CUTIX/ELLAHLAKES; not resolved this session.
A41: 40 | B41: ETERNA | C41: Eterna Plc | D41: OIL AND GAS | E41: 1989 | F41: Aug-1998 (listed on NGX) | G41: PricewaterhouseCoopers | H41: 1 | I41: MRF | J41: Missed 2025 Q4 quarterly filing only - annual audited data likely unaffected | K41: Eterna Plc - oil & gas downstream distribution/marketing company. Incorporated 13-Jan-1989 as Eterna Oil & Gas Limited, re-registered as a public limited company 1997, first listed on NGX 1-Aug-1998. Standard calendar FYE (31-Dec). Auditor: PricewaterhouseCoopers (PwC), Big4. Total Assets/Liabilities/Net Income/Shares/Price sourced from stockanalysis.com (S&P Global Market Intelligence), MEDIUM-HIGH confidence, full 5-year coverage (FY2021-2025), no gaps.
A42: 41 | B42: ETI | C42: Ecobank Transnational Incorporated | D42: FINANCIAL SERVICES | E42: 1985 | F42: 11-Sep-2006 | G42: Deloitte and Grant Thornton (joint auditors) | H42: 1 | K42: Ecobank Transnational Incorporated - pan-African banking group headquartered in Lome, Togo; cross-listed on NGX (also BRVM/Ghana). Reports in USD at Group level but files an official NGN-translated companion statement with NGX each period - used for this panel instead of an independently estimated FX conversion (see Panel Data notes for full source detail and the June-2023 devaluation caveat). Auditors: Deloitte and Grant Thornton (joint audit), Big4 (Deloitte). Incorporated 1985 in Lome, Togo; listed on NGX 11-Sep-2006 (also cross-listed on Ghana Stock Exchange and BRVM).
A43: 42 | B43: ETRANZACT | C43: eTranzact International Plc | D43: ICT | E43: 2003 | F43: 07-Aug-2009 | G43: Ernst & Young | H43: 1 | K43: eTranzact International Plc - fintech/electronic payments processor, ICT sector. Standard calendar FYE (31-Dec). Auditor Ernst & Young (Big4) confirmed via the FY2025 audited financial statements (EY indicated willingness to continue in office per Section 401(2) CAMA 2020, NGX doclib filing). Shares outstanding grew from 6.635bn (FY2021) to 9.2bn (FY2022 onward) via issuance during 2022 - reflected in the period-end Shares_Outstanding figures used, not the EPS-weighted-average. Incorporated 2003; listed on NGX 07-Aug-2009.
A44: 43 | B44: EUNISELL | C44: Eunisell Chemicals Plc | D44: SERVICES | E44: 1981 | F44: Renamed Eunisell Interlinked Plc 25-May-2022 (previously Interlinked Technologies Plc) | G44: ANOC Professional Services | H44: 0 | K44: Eunisell Interlinked Plc - specialty chemicals/oilfield services (Services sector per Firm Master, though the underlying business is industrial chemicals). Incorporated 1981 as Raychem Nigeria Limited; renamed Interlinked Technologies Plc in 1993; renamed Eunisell Interlinked Plc 25-May-2022 (merger/rebrand). FYE is 30 June (1-Jul to 30-Jun) - FYE-labelled year mapped directly to study Year column, same convention as CUTIX/ELLAHLAKES/ENAMELWA. FY2021 (FYE Jun-2021) is a GAP - stockanalysis.com data starts at FY2022. Auditor ANOC Professional Services (Chartered Accountants, non-Big4) confirmed via multiple NGX doclib annual financial statement filings (FY2023-2025). Share price rose sharply from N3.20 (FY2024) to N12.95 (FY2025) to N210 (FY2026, out of study window) - dramatic re-rating, consistent with the large revenue/earnings growth reported (revenue N277m FY2023 to N1.4bn FY2025).
A45: 44 | B45: FCMB | C45: FCMB Group Plc | D45: FINANCIAL SERVICES | E45: 2013 | F45: 21-Jun-2013 | G45: Deloitte and Touche | H45: 1 | K45: FCMB Group Plc - banking group, Financial Services sector. Standard calendar FYE, full 5-year coverage. Auditor Deloitte and Touche (Big4), 4 years' tenure as at FY2024 per search results. FY2025 figures are UNAUDITED as filed (per FCMB's own January-2026 filing) - flagged in Panel Data notes. Share count roughly doubled FY2023-2025 (19.8bn to 42.8bn) via capital raise(s), consistent with the sector-wide NGX recapitalisation exercise for banks. FCMB Group Plc (the listed holding entity) was incorporated June 2013 as a non-operating holding company under CBN Regulation 3 (2010), which required banks to separate non-banking businesses; listed on NGX 21-Jun-2013. The underlying First City Monument Bank Limited has an older history, incorporated 20-Apr-1982 and granted a banking licence 11-Aug-1983 - Year_Incorporation uses the listed holding entity's date for consistency with FIRSTHOLDCO/other holdco treatment.
A46: 45 | B46: FIDELITYBK | C46: Fidelity Bank Plc | D46: FINANCIAL SERVICES | E46: 1987 | F46: 17-May-2005 | G46: Deloitte & Touche | H46: 1 | K46: Fidelity Bank Plc - banking group, Financial Services sector. Standard calendar FYE, full 5-year coverage. Auditor Deloitte & Touche (Big4), confirmed via WebSearch (Nairametrics 2025 auditor-market analysis). Share count grew from 28.96bn (FY2021-2022) to 50.2bn (FY2024-2025) via capital raises, consistent with the sector-wide NGX bank recapitalisation exercise. Incorporated 19-Nov-1987 as Fidelity Union Merchant Bank; converted to a commercial bank 16-Jul-1999; re-registered as a public limited company 10-Aug-1999; listed on NGX 17-May-2005.
A47: 46 | B47: FIDSON | C47: Fidson Healthcare Plc | D47: HEALTHCARE | E47: 1995 | F47: 06-Apr-2008 | G47: Deloitte and Touche | H47: 1 | K47: Fidson Healthcare Plc - pharmaceutical manufacturer, Healthcare sector. Standard calendar FYE, full 5-year coverage, no gaps. Auditor Deloitte and Touche (Big4), confirmed via WebSearch (2023 annual report willingness-to-continue disclosure; EY was the auditor circa 2008, so a change occurred at some point pre-study-window). Strong share-price re-rating (N4.71 to N49.35 over the window) alongside consistent revenue growth. Incorporated 1995; listed on NGX 06-Apr-2008.
A48: 47 | B48: FIRSTHOLDCO | C48: FirstHoldCo Plc (First Bank Holding) | D48: FINANCIAL SERVICES | E48: 2010 | F48: 26-Nov-2012 | G48: KPMG Professional Services | H48: 1 | K48: First HoldCo Plc (formerly FBN Holdings Plc; renamed 2024) - banking group holding First Bank of Nigeria, Financial Services sector. Standard calendar FYE, full 5-year coverage, no gaps. Auditor KPMG Professional Services (Big4), confirmed via WebSearch. Net Income dropped sharply from N670.8bn (FY2024) to N132.7bn (FY2025) despite continued revenue growth - consistent with a large prior-year one-off gain (FY2024 'Gain (Loss) on Sale of Investments' was -N47bn while non-interest income was unusually elevated) reversing; not flagged as a data error, but worth a note if FY2025 profitability looks anomalous in analysis. Share count grew from 35.9bn to 44.5bn via capital raise, consistent with the sector-wide NGX bank recapitalisation exercise. FBN Holdings Plc (renamed First HoldCo Plc, 2024) was incorporated 14-Oct-2010 as a non-operating holding company under CBN Regulation 3, listed on NGX 26-Nov-2012. The underlying First Bank of Nigeria has a much older history, founded 31-Mar-1894 - Year_Incorporation uses the listed holding entity's date for consistency with FCMB/other holdco treatment.
A49: 48 | B49: FTGINSURE | C49: Fortis Global Insurance Plc (formerly Standard Alliance Insurance Plc) | D49: FINANCIAL SERVICES | E49: 1981 | F49: 19-Dec-2003 | G49: Muhtari Dangana & Co (2021-2024); TAC Professional Services (2025) | H49: 0 | K49: Fortis Global Insurance Plc (formerly Standard Alliance Insurance Plc; renamed May-2025), non-life insurer, Financial Services sector. Standard calendar FYE. IMPORTANT COMPLIANCE HISTORY: trading was SUSPENDED on NGX from 2-Jul-2019 through 4-Feb-2026 (over 6.5 years) for failing to file accounts within the cure period; suspension was lifted only after the company caught up on ALL outstanding filings. Financial statements (Total Assets/Liabilities/Net Income) WERE filed with regulators throughout and are used here for FY2021-2025, but Share_Price_YearEnd is left BLANK for all 5 years - the entire study window falls within the suspension period, so there was no active NGX market price at any fiscal year-end (stockanalysis.com shows an identical frozen 'market cap' of N2,582m for FY2021 through FY2025, confirming no real price discovery occurred; trading only resumed in Feb-2026, after the FY2025 year-end). Market_Value_Equity and Tobin's Q will not compute for this firm for any study year as a result - this is a genuine data-unavailability, not an oversight. NEGATIVE SHAREHOLDERS' EQUITY FY2021-2024 (-N3.1bn to -N1.1bn), turning positive only in FY2025 (+N9.35bn) likely via a capital injection/asset revaluation tied to the recapitalisation needed to resume trading - real financial distress, not a data error, flag alongside DAARCOMM/DANGSUGAR/ENAMELWA. Auditor: Muhtari Dangana & Co (Chartered Accountants) for FY2021-2024 (reappointed 2022, confirmed for FY2023); TAC Professional Services newly appointed for FY2025. Neither is Big4. Incorporated 1981 as Jubilee Insurance Company Limited; renamed Standard Alliance Insurance Plc Aug-1996; renamed Fortis Global Insurance Plc May-2025. Listed on NGX 19-Dec-2003 (as Standard Alliance/predecessor entity). Share_Price_YearEnd resolved using N0.20 (last traded price, 28-Jun-2019, pre-suspension) carried forward for FY2021-2025 - see Panel Data notes for full caveat on this being a stale, non-market-validated price.
A50: 49 | B50: FTNCOCOA | C50: FTN Cocoa Processors Plc | D50: AGRICULTURE | E50: 1991 | F50: Sep-2008 | G50: Baker Tilly Nigeria | H50: 0 | I50: RST | J50: Restructuring status | K50: FTN Cocoa Processors Plc - cocoa processing, Agriculture sector. Standard calendar FYE. PREVIOUSLY FLAGGED as a possible X-Compliance exclusion candidate - RE-VERIFIED this session: the firm is NOT suspended or delisted. It is under an NGX-approved restructuring status (effective Oct-2024, phased completion by Oct-2026) requiring quarterly compliance reports, but trading continued throughout the study window and financial statements were filed - included in the panel normally. Heavy losses and negative shareholders' equity in FY2021-2022, large one-off FX-translation losses drove very large FY2023/2024 net losses (N10.65bn and N9.53bn respectively, vs modest operating figures) - flag alongside DAARCOMM/DANGSUGAR/ENAMELWA/FTGINSURE as a real, not data-error, distress pattern. Share count jumped from 2.2bn to 3.9bn during 2021/2022 via a capital raise tied to the restructuring. Auditor: Baker Tilly Nigeria (Chartered Accountants), not Big4. Registered 1991 as Fantastic Traders Nigeria Limited; renamed FTN Cocoa Processors Plc; listed on NGX Sep-2008.
A51: 50 | B51: GEREGU | C51: Geregu Power Plc | D51: UTILITIES | E51: 2006 | F51: 05-Oct-2022 | G51: PKF Professional Services | H51: 0 | K51: Incorporated 10-Nov-2006 (per afx.kwayisi.org company profile); listed NGX Main Board by way of introduction on 5-Oct-2022 (2.5bn ordinary shares admitted at N100/share; first power-generating company listed on NGX). Auditor: PKF Professional Services (Chartered Accountants) - CONFIRMED HIGH CONFIDENCE, sourced directly from the company's NGX Listing Memorandum (Oct-2022), 'Relationship between the Company and its Advisers' table, which names 'Auditor to the Company: PKF Professional Services'. Not a Big 4 firm. Company's 2019 pre-listing audited FS were also filed under PKF, indicating continuity.
A52: 51 | B52: GOLDBREW | C52: Golden Guinea Breweries Plc | D52: CONSUMER GOODS | E52: 1962 | F52: 01-Jan-1979 | G52: Mokuolu Rubens & Co | H52: 0 | I52: BMF | J52: Below listing std + missed filing; missing audited FS 2025 (FYE March); SUSPENDED from trading since 6-May-2025 | K52: Incorporated 1962 (originally Independence Brewery Ltd; renamed Golden Guinea Breweries 1971). Listed NGX 1979 (exact date approximate - sources give '1-Jan-1979' as a nominal listing-year marker; precise day/month not independently confirmed). Auditor: Mokuolu Rubens & Co (Chartered Accountants, Lagos) - HIGH CONFIDENCE, confirmed directly from the company's own FY2024 Audited Financial Statements (NGX doclib primary source). Not Big4. FYE is 31 March (not 31 December) - see Panel Data notes for year-mapping convention, same as CUTIX/ENAMELWA. Currently SUSPENDED from trading since 6-May-2025 for failure to file FY2025 (FYE 31-Mar-2025) audited/unaudited financials. | EXCLUDED FROM 'Final Sample' (stricter, 17-Aug-2026), ALL 5 YEARS: Condition 5 (Section 3.6): NGX compliance status 'BMF' not among retained exceptions (BLS/MRF/RST).
A53: 52 | B53: GTCO | C53: Guaranty Trust Holding Company Plc | D53: FINANCIAL SERVICES | E53: 2020 | F53: 24-Jun-2021 | G53: Ernst & Young | H53: 1 | K53: Guaranty Trust Holding Company Plc incorporated as a public limited company 24-Jul-2020, licensed as a non-operating financial holding company by CBN 14-Apr-2021, as part of a Scheme of Arrangement restructuring the Guaranty Trust Group (bank + non-bank subsidiaries) under CBN holdco regulation. Shares listed on NGX 24-Jun-2021 (one source states 28-Jun-2021 for the closing-gong ceremony) - used the earlier listing date as Date_Listed_NGX; GDRs cross-listed on LSE 25-Jun-2021. Year_Incorporation reflects the HOLDING ENTITY itself (consistent with FCMB/FIRSTHOLDCO convention), NOT the older operating bank: Guaranty Trust Bank Plc (now Guaranty Trust Bank Ltd, GTCO's banking subsidiary) was itself incorporated 1990 and first listed on NGX in 1996 - noted here for context/consistency. Auditor: Ernst & Young (EY) - HIGH CONFIDENCE, confirmed in Nairametrics' 29-Jul-2026 Nigerian audit market survey, which explicitly lists 'Guaranty Trust Holding Company' in EY's client portfolio. Big4=1.
A54: 53 | B54: GUINEAINS | C54: Guinea Insurance Plc | D54: FINANCIAL SERVICES | E54: 1958 | F54: 17-Jan-1991 | G54: BDO Professional Services | H54: 0 | K54: Incorporated as private limited liability company 3-Dec-1958; became Public Limited Company and listed NGX same day, 17-Jan-1991. Overseas shareholders divested their 40% stake to Nigerian shareholders in 1988 (now 100% Nigerian-owned). Stopped underwriting Life business in 2007, now General insurance only. Auditor: BDO Professional Services - HIGH CONFIDENCE, confirmed in Nairametrics' 29-Jul-2026 Nigerian audit market survey, which explicitly lists 'Guinea Insurance Plc' in BDO's client portfolio. Not Big4.
A55: 54 | B55: GUINNESS | C55: Guinness Nigeria Plc | D55: CONSUMER GOODS | E55: 1950 | F55: 1965 (exact day/month not independently confirmed) | G55: PricewaterhouseCoopers | H55: 1 | K55: Incorporated 29-Apr-1950. Listed NGX 1965 (per general company-history sources; precise day/month not independently pinned down this session - flagged for a follow-up spot-check). Auditor: PricewaterhouseCoopers - HIGH CONFIDENCE, confirmed directly in the company's own FY2021 Audited Financial Statements (NGX doclib primary source), signed by partner Edafe Erhie (FRCN ICAN 00000001143). Big4=1. IMPORTANT FYE NOTE: Guinness Nigeria's fiscal year was 1-July to 30-June through FY2024 (FYE 30-Jun), then the company changed its FYE to 31-December during 2025, filing an 18-MONTH TRANSITION PERIOD statement covering 1-Jul-2024 to 31-Dec-2025 (per company announcements: 'aligns fiscal year with calendar year'). Mapped this firm's FYE-labelled year directly to the study's Year column for FY2021-FY2024 (FYE 30-Jun-2021=Year 2021, etc), same convention as CUTIX/ELLAHLAKES/ENAMELWA. For Study Year 2025, used the REGULAR 12-month FYE 30-Jun-2025 figures (NOT the 18-month transition-period figures) to preserve consistency with all other years in the panel - same approach used for ELLAHLAKES. Future data collection (Study Year 2026 onward, if the panel is extended) should expect this firm to report on a calendar-year basis.
A56: 55 | B56: HBMNG | C56: HBM Nigeria Plc (formerly Lafarge Africa) | D56: INDUSTRIAL GOODS | E56: 1959 | F56: 1979 (exact day/month not independently confirmed) | G56: Ernst & Young | H56: 1 | K56: Incorporated in Nigeria 24-Feb-1959 (as West African Portland Cement Company, ticker still WAPCO on most aggregators); listed NGX 1979. Formerly Lafarge Africa Plc - shareholders approved a rename to HBM Nigeria Plc at the 30-Apr-2026 AGM, following Holcim's Dec-2024 sale of its ~84% stake to Huaxin Building Materials (HBM) for ~$1bn; rebrand took effect during 2026, entirely outside this study's 2021-2025 window - the underlying entity, incorporation date, and listing history are unchanged. Auditor: Ernst & Young - HIGH confidence, confirmed in the company's own audited financial statements. Big4=1.
A57: 56 | B57: HMCALL | C57: Haldane McCall Plc | D57: CONSTRUCTION/REAL ESTATE | E57: 2012 | F57: 20-Nov-2024 | G57: Funsho Owoyemi & Co | H57: 0 | K57: Real Estate and Hospitality group. Incorporated 27-Mar-2012 as a private Limited Company; converted to Public Liability Company in 2021; listed on NGX Main Board by way of introduction 20-Nov-2024 (3.122bn ordinary shares of 50k each at N3.84/share, ~N11.98bn initial market cap). Auditor: Funsho Owoyemi & Co (Chartered Accountants) - HIGH confidence, confirmed directly in the company's own FY2024 Audited Financial Statements. Not Big4. Sanctioned by NGX Regulation in Apr-2025 for an insider-dealing/closed-period breach (Rule 17.18) - noted for governance context, does not affect financial figures.
A58: 57 | B58: HONYFLOUR | C58: Honeywell Flour Mills Plc | D58: CONSUMER GOODS | E58: 1983 | F58: 20-Oct-2009 | G58: Baker Tilly Nigeria (FY2021-2023); Ernst & Young (FY2024-2025) | H58: 1 | K58: Registered as Gateway Honeywell Flour Mills Ltd 21-Jun-1983; listed NGX 20-Oct-2009. FYE is 31-March, not 31-December - mapped FYE-labelled year directly to study Year, same convention as CUTIX/ENAMELWA. Became a subsidiary of Flour Mills of Nigeria Plc (FMN) following an ~N80bn acquisition around 2021-2022 - relevant context for the FY2022 loss and subsequent volatility. AUDITOR TRANSITION RESOLVED: Baker Tilly Nigeria audited FY2021-FY2023 (HIGH confidence for FY2021, from the company's own Audited FS; MEDIUM confidence for FY2022-2023 inferred from continuity). Ernst & Young took over starting FY2024 (year ended 31-Mar-2024) - confirmed HIGH confidence directly from the FY2024 Independent Auditor's Report, which states the prior year (FYE 31-Mar-2023) financial statements 'were audited by another auditor' (i.e. not EY) who signed off 28-Aug-2023, and separately lists EY as the FY2024 Independent Auditor. EY continued for FY2025 per the FY2025 annual report. Panel Data Big4_Auditor (col 25) set to 0 for 2021-2023 and 1 for 2024-2025 to reflect the year-specific auditor; Firm Master Auditor field and Big4_Auditor (col 8) reflect the current/most-recent auditor (EY).
A59: 58 | B59: IKEJAHOTEL | C59: Ikeja Hotel Plc | D59: SERVICES | E59: 1972 | F59: 1983 | G59: Ugochukwu, Ike & Co / Ahmed Zakari & Co (Joint Auditors) | H59: 0 | K59: Incorporated 18-Nov-1972 as Property Development Company; renamed Ikeja Hotel Limited in 1980; became a public company and listed on the NGX in 1983 (source: Wikipedia/company history; exact listing-day date not independently confirmed - stockanalysis.com's market-cap history series begins 11-Sep-2007, which is a data-coverage start date, not the actual IPO date). Name changed to present form 5-Feb-1991. Owns Sheraton Lagos Hotel, Sheraton Abuja Hotel (indirect via Hans Gremlins Ltd), and a shareholding in Tourist Company of Nigeria Plc (Federal Palace Hotel). Trading was suspended by NSE 10-Nov-2016 amid an Ibru-family boardroom/ownership dispute; suspension lifted 21-May-2018 - outside study window (2021-2025), no impact on data. Auditors: joint audit by Ugochukwu, Ike & Co and Ahmed Zakari & Co (both non-Big4 Nigerian firms) - MEDIUM confidence, sourced from EMIS company profile.
A60: 59 | B60: IMG | C60: Industrial and Medical Gases Nigeria Plc | D60: NATURAL RESOURCES | E60: 1959 | F60: 1979 | G60: Ernst & Young | H60: 1 | K60: Incorporated 12-Nov-1959 as Industrial Gases (Nigeria) Limited; renamed Industrial Gases Limited 10-Jul-1961, then BOC Gases Nigeria Plc 17-Mar-1997, then Industrial and Medical Gases Nigeria Plc (current name/ticker IMG) in 2021 following TY Holdings Limited's increase of its stake to 72% (Aug-2021), making the company wholly Nigerian-owned. Quoted on the NGX since 1979. Auditor: Ernst & Young (Big4) - HIGH confidence, per company's own AGM notice/annual report language ('Messrs Ernst & Young have expressed willingness to continue in office'). FY2025 Shares_Outstanding jumped from 549.44m to 731.06m per stockanalysis balance sheet (period-end count) while the income statement's weighted-average diluted count for FY2025 EPS is only ~610m - consistent with a mid-year 2025 share issuance; Shares_Outstanding entered here uses the period-end (731.06m) balance-sheet count for consistency with the Market_Value_Equity calculation convention used elsewhere in this dataset.
A61: 60 | B61: INFINITY | C61: Infinity Trust Mortgage Bank Plc | D61: FINANCIAL SERVICES | E61: 2002 | F61: 11-Dec-2013 | G61: PKF Professional Services | H61: 0 | I61: BLS | J61: Free-float deficient only (1.26%%, due Apr-2027) - no audited FS filing gap | K61: Incorporated 28-Jan-2002 as Infinity Trust Savings & Loans Limited; converted to Infinity Trust Mortgage Bank and listed on the NGX 11-Dec-2013. Auditor: Aminu Ibrahim & Co held the audit for 10 continuous years prior; PKF Professional Services (Chartered Accountants) was newly appointed at the 2024 AGM, effective for the 2024 accounting period onward - PKF entered here as the auditor of record for the study's most recent years; MEDIUM-HIGH confidence (Nairametrics/proxy coverage of AGM resolutions), not independently cross-checked against the full signed audit opinion page.
A62: 61 | B62: INTBREW | C62: International Breweries Plc | D62: CONSUMER GOODS | E62: 1971 | F62: 1995 | G62: PricewaterhouseCoopers (PwC) | H62: 1 | K62: Incorporated 22-Dec-1971 as a private company, converted to public limited company 26-Mar-1992, listed on the NGX in 1995. Majority-owned by Anheuser-Busch InBev (AB InBev) following the 2016 SABMiller merger. Auditor: PwC (Big4) confirmed for the FY2025 annual report; Deloitte & Touché was the proposed auditor as of the 2018 filing and Baker Tilly Nigeria audited FY2014 - exact year(s) of each transition within the 2021-2025 study window not individually pinned down, but all three candidate firms (PwC/Deloitte/Baker Tilly-for-2014-only) mean the Big4 status for the recent years is PwC (Big4=1) with reasonable confidence given it's the most recently confirmed auditor of record. FY2021-2023 shows heavy net losses driven largely by FX/currency translation losses (naira devaluation) and high finance costs; a large capital raise occurred in FY2024 (shares outstanding grew from 26.862bn to 168.292bn, ~6.3x) that materially reduced leverage and coincided with a return to profitability in FY2025 - consistent with AB InBev's publicly reported deleveraging of the Nigerian subsidiary.
A63: 62 | B63: INTENEGINS | C63: International Energy Insurance Plc | D63: FINANCIAL SERVICES | E63: 1969 | F63: 13-Jul-2007 | G63: Doyin Owolabi & Co | H63: 0 | I63: RST | J63: Restructuring status till 30-Nov-2025; largest late-filing penalty in report history (N28.2m) | K63: Incorporated 1969, NGX-listed 13-Jul-2007. Auditor: Doyin Owolabi & Co (Chartered Accountants, non-Big4) - MEDIUM confidence, per NGX company profile. Balance sheet shows negative shareholders' equity throughout FY2021-2024 (accumulated losses) before turning positive in FY2025, coinciding with NAPL's acquisition of a 50.61% controlling stake (649.8m shares). Trading was suspended by NGX 1-Sep-2025 for failing to file the FY2024 audited financial statements on time; suspension lifted 2-Oct-2025 once the accounts were released - the FY2024 figures entered here reflect the eventually-filed audited numbers (post-suspension), no impact on data quality, only on timing.
A64: 63 | B64: JAIZBANK | C64: Jaiz Bank Plc | D64: FINANCIAL SERVICES | E64: 2003 | F64: 10-Feb-2017 | G64: Deloitte & Touche | H64: 1 | K64: Established 2003 as a public limited liability company (Nigeria's first full-fledged non-interest/Islamic bank); NGX-listed 10-Feb-2017. Auditor: Deloitte & Touche (Big4) confirmed for the FY2025 annual report ('indicated willingness to continue in office'); one search snippet also referenced Ahmed Zakari & Co, which may reflect a joint-audit arrangement (common for Nigerian banks above a certain size under CBN rules) rather than a straightforward auditor change - not fully disambiguated this round. Big4_Auditor set to 1 based on Deloitte being the most recently confirmed primary auditor.
A65: 64 | B65: JAPAULGOLD | C65: Japaul Gold & Ventures Plc | D65: OIL AND GAS | E65: 1994 | F65: 10-Aug-2005 | G65: SIAO Partners | H65: 0 | K65: Incorporated 29-Jun-1994 as Japaul Oil & Maritime Services Plc (private co., commenced business Jan-1997); NGX-listed 10-Aug-2005; later rebranded Japaul Gold & Ventures Plc as the business pivoted toward gold mining. Auditor: SIAO Partners (Chartered Accountants, non-Big4) - MEDIUM confidence, per the FY2025 Independent Auditor's Report. Company had negative shareholders' equity FY2022-2023 (accumulated losses) before a large capital raise in FY2024 (shares outstanding grew from 6.263bn to 14.263bn) turned equity positive; also completed a further ~N20bn share listing in Sep-2024 tied to its mining capital programme.
A66: 65 | B66: JBERGER | C66: Julius Berger Nigeria Plc | D66: CONSTRUCTION/REAL ESTATE | E66: 1970 | F66: 20-Sep-1991 | G66: PricewaterhouseCoopers (PwC) | H66: 1 | K66: Incorporated 1970 (Julius Berger Nigeria Ltd, German-parent construction group); NGX-listed 20-Sep-1991. Auditor: PwC (Big4) - MEDIUM-HIGH confidence, PwC's publicly listed audit portfolio includes Julius Berger among major Nigerian corporates; not independently cross-checked against the signed opinion page of a specific year's annual report. FY2024-2025 show large negative Operating Income despite strong overall profitability - driven by big non-operating FX/interest gains, a known feature of naira-devaluation-era Nigerian corporate results in this period.
A67: 66 | B67: JOHNHOLT | C67: John Holt Plc | D67: CONGLOMERATES | E67: 1961 | F67: May-1974 | G67: Baker Tilly Nigeria | H67: 0 | K67: Nigerian entity incorporated 1961 as a subsidiary of the Liverpool-based John Holt & Co (founded 19th century); NGX-listed May-1974. FYE is 30-September, not 31-December - mapped FYE-labelled year directly to study Year, same convention as CUTIX/ENAMELWA/HONYFLOUR. Share_Price_YearEnd is approximated from stockanalysis.com's calendar Dec-31 market-cap series (nearest available annual price point to the Sep-30 fiscal year-end, ~3 months later) since no Sep-30-specific price series was available - LOW-MEDIUM confidence on price specifically, MEDIUM-HIGH on balance sheet/income figures (which are genuine FYE-Sep-30 figures). Auditor: Baker Tilly Nigeria (non-Big4) - HIGH confidence, per NGX company profile. Volatile results across the window including large FX losses in FY2023-2024 and asset writedowns most years.
A68: 67 | B68: JULI | C68: Juli Plc | D68: SERVICES | E68: 1972 | F68: 7-Nov-1986 | G68: Ayinde Saheed & Co | H68: 0 | K68: Incorporated 14-Sep-1972 (RC: 10566); NGX-listed 7-Nov-1986. Auditor: Ayinde Saheed & Co (Chartered Accountants/Tax Consultants, non-Big4) - MEDIUM-HIGH confidence, per the company's own FY2023 filing letterhead. Negative shareholders' equity throughout FY2021-2024 (accumulated losses), resolved by FY2025 via a capital raise (Common Stock 100m->275m, plus new Additional Paid-In Capital of ~525m).
A69: 68 | B69: LASACO | C69: Lasaco Assurance Plc | D69: FINANCIAL SERVICES | E69: 1979 | F69: 1991 | G69: BDO Professional Services | H69: 0 | K69: Incorporated 20-Dec-1979; NGX-listed 1991. Auditor: BDO Professional Services (Chartered Accountants, non-Big4) - HIGH confidence, confirmed consistently across the FY2022-2025 annual reports. FY2025 shares outstanding jumped from 1.834bn to 11.084bn (a ~6x capital raise) coinciding with a large market-cap increase; FY2025 also shows a net loss (-2,801,000 thousand) despite the recapitalisation, driven by a large underwriting/policy-benefits expense increase per the income statement.
A70: 69 | B70: LEARNAFRCA | C70: Learn Africa Plc | D70: SERVICES | E70: 1961 | F70: 23-Jul-1991 | G70: PKF Professional Services | H70: 0 | K70: Formerly Longman Nigeria Plc (renamed Learn Africa Plc Nov-2011); operating in Nigeria since 1961, converted to a Public Limited Company 28-May-1991 and NGX-listed 23-Jul-1991 (one source also references a 1-Jan-1971 listing date, likely a data artifact from an earlier corporate predecessor - not used here). FYE is 31-March, mapped directly to study Year per the CUTIX/ENAMELWA/HONYFLOUR convention. Auditor: PKF Professional Services (non-Big4), confirmed as of the FY2022 financial statements. FY2021 (FYE 31-Mar-2021) data point is a DOCUMENTED GAP - stockanalysis.com's balance sheet/income-statement history for this ticker starts at FY2022, and a primary-source figure for the FYE-Mar-2021 audited statement was not located this round; left blank rather than estimated. Share_Price_YearEnd for FY2022-2025 approximated from the nearest PRECEDING calendar Dec-31 market-cap point (3 months before the Mar-31 fiscal year-end, closer than the following Dec-31 which is 9 months after) - e.g. study Year 2022 (FYE Mar-2022) paired with the Dec-31-2021 market cap.
A71: 70 | B71: LEGENDINT | C71: Legend Internet Plc | D71: ICT | E71: 2021 | F71: 24-Apr-2025 | G71: Poju Professional Services | H71: 0 | K71: Incorporated 17-Aug-2021; listed on the NGX Main Board 24-Apr-2025 (2 billion ordinary shares), the first new NGX listing of 2025. FYE is 31-July. Auditor: Poju Professional Services (non-Big4), per the company's own FY2024 (year ended 31-Jul-2024) Audited FS. FY2021-2024 marked EXCLUDED BY DESIGN per the ARADEL/BUAFOODS/GEREGU/HMCALL pre-listing convention - not NGX-listed until Apr-2025, so no NGX market value existed for those years; all data fields left blank. FY2025 (the listing year) uses the nearest-year-end-price convention: Dec-31-2025 market cap (10.58B) / 2bn shares as a low-medium confidence proxy reflecting only a partial year of post-listing market discovery. FY2025 Total_Assets/Total_Liabilities are INDIRECTLY DERIVED (LOW-MEDIUM confidence): press coverage (Nairametrics) reported Shareholders' Funds of N2.87bn representing ~86% of total assets for the year ended 31-Jul-2025, implying Total_Assets ~N3.337bn and Total_Liabilities ~N0.467bn by subtraction - not independently verified against the primary audited FS line items. Net_Income (N142,457,000, profit after tax) is HIGH confidence, taken directly from the reported figure.
A72: 71 | B72: LINKASSURE | C72: Linkage Assurance Plc | D72: FINANCIAL SERVICES | E72: 1991 | F72: 18-Nov-2003 | G72: Ernst & Young (FY2021-2024); KPMG Professional Services (FY2025) | H72: 1 | K72: Incorporated 26-Mar-1991; NGX-listed 18-Nov-2003. Auditor transitioned from EY to KPMG at/around FY2025 - both Big4, so Big4_Auditor=1 throughout, but Panel Data Auditor_Name/Big4 per-row reflects the actual auditor for that year. Shares outstanding constant at 18.48bn across all 5 years. Source: stockanalysis.com (S&P Global Market Intelligence aggregator).
A73: 72 | B73: LIVESTOCK | C73: Livestock Feeds Plc | D73: AGRICULTURE | E73: 1963 | F73: 1978 | G73: Ernst & Young (since 20-Sep-2018 AGM) | H73: 1 | K73: Incorporated 20-Mar-1963; NGX-listed 1978. Auditor Ernst & Young (Big4) appointed at the 20-Sep-2018 AGM, held throughout the study window. Shares outstanding constant at 3.0bn across all 5 years. Source: stockanalysis.com (S&P Global Market Intelligence aggregator).
A74: 73 | B74: LIVINGTRUST | C74: Living Trust Mortgage Bank Plc | D74: FINANCIAL SERVICES | E74: 1993 | F74: 11-Dec-2013 | G74: PKF Professional Services | H74: 0 | K74: Formerly Omoluabi Savings & Loans Plc (to 2016), then Omoluabi Mortgage Bank Plc (to 2020); renamed LivingTrust Mortgage Bank Plc in 2020 after Cititrust Holdings Plc took a controlling stake. Incorporated 9-Mar-1993 (as Osun State-owned entity); converted to Plc 25-Jan-2013 and NGX-listed 11-Dec-2013 (per the company's own FY2024 Audited FS corporate profile - doclib.ngxgroup.com). Auditor: PKF Professional Services (non-Big4) - confirmed via the FY2024 Audited FS 'Corporate Information' page (HIGH confidence, resolved this round after WebSearch alone was inconclusive). Shares outstanding constant at 5.0bn across all 5 years.
A75: 74 | B75: MANSARD | C75: AXA Mansard Insurance Plc | D75: FINANCIAL SERVICES | E75: 1989 | F75: Nov-2009 | G75: KPMG Professional Services | H75: 1 | K75: Incorporated 1989; NGX-listed Nov-2009. Auditor KPMG Professional Services (Big4) - confirmed via search cross-referencing KPMG's published major-client list. Shares outstanding constant at 8.944bn (balance sheet period-end figure) across all 5 years. Source: stockanalysis.com (S&P Global Market Intelligence aggregator).
... A83: 82 | B83: MTNN | C83: MTN Nigeria Communications Plc | D83: ICT | E83: 2000 | F83: 16-May-2019 | G83: Ernst & Young | H83: 1 | K83: Incorporated as a private company 8-Nov-2000; re-registered as a Plc 18-Apr-2019 and NGX-listed by introduction on the Premium Board 16-May-2019. Auditor Ernst & Young (Big4) - confirmed for FY2025; assumed consistent across the study window. Nigeria's largest mobile network operator by revenue/market cap. FY2023-2024 show large reported net losses driven by naira-devaluation FX losses (a well-documented sector-wide phenomenon for telecom/import-heavy Nigerian corporates in this period), with a strong recovery in FY2025.
A84: 83 | B84: MULTITREX | C84: Multi-Trex Integrated Foods Plc | D84: CONSUMER GOODS | E84: 1999 | F84: 2-Nov-2010 | G84: Baker Tilly Nigeria | H84: 0 | I84: DWL | J84: Delisting watchlist (2yr); missing audited FS 2025 (FYE April) | K84: Incorporated 1999; NGX-listed c. 2-Nov-2010 (approximated from the earliest available market-cap history date - MEDIUM confidence, not independently verified against a primary listing notice). FYE 30-April, mapped directly to the study Year per the established FYE-mapping convention (e.g. FYE 30-Apr-2025 -> study Year 2025). Auditor Baker Tilly Nigeria (non-Big4). Illiquid stock with an unchanged market cap (N1.34bn) across Dec-2021 to Dec-2023, reflected in the flat Share_Price_YearEnd for study Years 2021-2023. Share_Price_YearEnd approximated using the nearest PRECEDING calendar Dec-31 market cap (closer in time to the Apr-30 FYE than the following Dec-31), per the LEARNAFRCA/JOHNHOLT precedent; for study Year 2021 the true preceding point (Dec-2020) was unavailable from the source, so the nearest available point (Dec-2021, same value as neighbors) was used as a LOW-MEDIUM confidence fallback. | EXCLUDED FROM 'Final Sample' (stricter, 17-Aug-2026), ALL 5 YEARS: Condition 5 (Section 3.6): NGX compliance status 'DWL' not among retained exceptions (BLS/MRF/RST).
A85: 84 | B85: MULTIVERSE | C85: Multiverse Mining and Exploration Plc | D85: NATURAL RESOURCES | E85: 2002 | F85: 8-Oct-2008 | G85: Olukayode Aina & Co | H85: 0 | K85: Solid-minerals miner (lead, zinc, copper, gold, tantalite, tin, barite). Incorporated 20-Jun-2002 (per the company's own Corporate Information page); NGX-listed 8-Oct-2008. Auditor Olukayode Aina & Co (Chartered Accountants, non-Big4) - confirmed via the company's own Corporate Information page (HIGH confidence). Constant 426.19m shares across all 5 years; steady growth in revenue/net income and declining leverage across the study window.
A86: 85 | B86: NAHCO | C86: Nigerian Aviation Handling Company (NAHCO) Plc | D86: SERVICES | E86: 1979 | F86: 27-Nov-2006 | G86: Ernst & Young | H86: 1 | K86: Nigerian Aviation Handling Company Plc - ground-handling/cargo services provider at Nigerian airports. Incorporated 1979; NGX-listed 27-Nov-2006. Auditor Ernst & Young (Big4). Strong revenue/profit growth across the study window (aviation-sector post-pandemic recovery), with a 1.1428571429 forward stock split in May-2026 (after the study window, not applied retroactively).
A87: 86 | B87: NASCON | C87: NASCON Allied Industries Plc | D87: CONSUMER GOODS | E87: 1973 | F87: 20-Oct-1992 | G87: PricewaterhouseCoopers (PwC) | H87: 1 | K87: NASCON Allied Industries Plc - salt/seasoning/edible-oil manufacturer, a Dangote Group subsidiary. Incorporated 30-Apr-1973; NGX-listed 20-Oct-1992. Auditor PricewaterhouseCoopers (PwC, Big4). Constant 2.702bn shares across the study window; strong, consistent revenue and net income growth throughout FY2021-2025.
